Workbook

Sheet Sales Quantity
A1: =Data!B1 -> MONTH | B1: =Data!C1 -> Region | C1: =Data!D1 -> City | D1: =Data!E1 -> PRD | E1: =Data!F1 -> OPQ (Old plan Quantity) | F1: =Data!G1 -> NPQ(New plan Quantity) | G1: Old Price | H1: New Price | I1: Old Revenue | J1: New Revenue | K1: Old Price per Unit | L1: New Price per Unit | M1: =Data!M2
A2: =Data!B2 -> Month1 | B2: =Data!C2 -> N | C2: =Data!D2 -> Chennai | D2: =Data!E2 -> PowerSip | E2: =Data!F2 -> 21497 | F2: =Data!G2 -> 22572 | G2: =IF(D2="PowerSip", 135, IF(D2="HappyGrow", 60, "")) -> 135 | H2: =IF(D2="PowerSip", 140, IF(D2="HappyGrow", 70, "")) -> 140 | I2: =E2 * G2 -> 2902095 | J2: =F2 * H2 -> 3160080 | K2: =IF(E2=0, "", I2 / E2) -> 135 | L2: =IF(F2=0, "", J2 / F2) -> 140
A3: =Data!B3 -> Month1 | B3: =Data!C3 -> N | C3: =Data!D3 -> Chennai | D3: =Data!E3 -> HappyGrow | E3: =Data!F3 -> 16650 | F3: =Data!G3 -> 16817 | G3: =IF(D3="PowerSip", 135, IF(D3="HappyGrow", 60, "")) -> 60 | H3: =IF(D3="PowerSip", 140, IF(D3="HappyGrow", 70, "")) -> 70 | I3: =E3 * G3 -> 999000 | J3: =F3 * H3 -> 1177190 | K3: =IF(E3=0, "", I3 / E3) -> 60 | L3: =IF(F3=0, "", J3 / F3) -> 70
A4: =Data!B4 -> Month1 | B4: =Data!C4 -> E | C4: =Data!D4 -> Chennai | D4: =Data!E4 -> PowerSip | E4: =Data!F4 -> 11470 | F4: =Data!G4 -> 12044 | G4: =IF(D4="PowerSip", 135, IF(D4="HappyGrow", 60, "")) -> 135 | H4: =IF(D4="PowerSip", 140, IF(D4="HappyGrow", 70, "")) -> 140 | I4: =E4 * G4 -> 1548450 | J4: =F4 * H4 -> 1686160 | K4: =IF(E4=0, "", I4 / E4) -> 135 | L4: =IF(F4=0, "", J4 / F4) -> 140
A5: =Data!B5 -> Month1 | B5: =Data!C5 -> E | C5: =Data!D5 -> Chennai | D5: =Data!E5 -> HappyGrow | E5: =Data!F5 -> 22348 | F5: =Data!G5 -> 22572 | G5: =IF(D5="PowerSip", 135, IF(D5="HappyGrow", 60, "")) -> 60 | H5: =IF(D5="PowerSip", 140, IF(D5="HappyGrow", 70, "")) -> 70 | I5: =E5 * G5 -> 1340880 | J5: =F5 * H5 -> 1580040 | K5: =IF(E5=0, "", I5 / E5) -> 60 | L5: =IF(F5=0, "", J5 / F5) -> 70
A6: =Data!B6 -> Month1 | B6: =Data!C6 -> W | C6: =Data!D6 -> Chennai | D6: =Data!E6 -> PowerSip | E6: =Data!F6 -> 13727 | F6: =Data!G6 -> 14551 | G6: =IF(D6="PowerSip", 135, IF(D6="HappyGrow", 60, "")) -> 135 | H6: =IF(D6="PowerSip", 140, IF(D6="HappyGrow", 70, "")) -> 140 | I6: =E6 * G6 -> 1853145 | J6: =F6 * H6 -> 2037140 | K6: =IF(E6=0, "", I6 / E6) -> 135 | L6: =IF(F6=0, "", J6 / F6) -> 140
A7: =Data!B7 -> Month1 | B7: =Data!C7 -> W | C7: =Data!D7 -> Chennai | D7: =Data!E7 -> HappyGrow | E7: =Data!F7 -> 15799 | F7: =Data!G7 -> 15957 | G7: =IF(D7="PowerSip", 135, IF(D7="HappyGrow", 60, "")) -> 60 | H7: =IF(D7="PowerSip", 140, IF(D7="HappyGrow", 70, "")) -> 70 | I7: =E7 * G7 -> 947940 | J7: =F7 * H7 -> 1116990 | K7: =IF(E7=0, "", I7 / E7) -> 60 | L7: =IF(F7=0, "", J7 / F7) -> 70
A8: =Data!B8 -> Month1 | B8: =Data!C8 -> S | C8: =Data!D8 -> Chennai | D8: =Data!E8 -> PowerSip | E8: =Data!F8 -> 24827 | F8: =Data!G8 -> 26565 | G8: =IF(D8="PowerSip", 135, IF(D8="HappyGrow", 60, "")) -> 135 | H8: =IF(D8="PowerSip", 140, IF(D8="HappyGrow", 70, "")) -> 140 | I8: =E8 * G8 -> 3351645 | J8: =F8 * H8 -> 3719100 | K8: =G8 * I8 -> 452472075 | L8: =IF(F8=0, "", J8 / F8) -> 140
A9: =Data!B9 -> Month1 | B9: =Data!C9 -> S | C9: =Data!D9 -> Chennai | D9: =Data!E9 -> HappyGrow | E9: =Data!F9 -> 13468 | F9: =Data!G9 -> 13603 | G9: =IF(D9="PowerSip", 135, IF(D9="HappyGrow", 60, "")) -> 60 | H9: =IF(D9="PowerSip", 140, IF(D9="HappyGrow", 70, "")) -> 70 | I9: =E9 * G9 -> 808080 | J9: =F9 * H9 -> 952210 | K9: =IF(E9=0, "", I9 / E9) -> 60 | L9: =IF(F9=0, "", J9 / F9) -> 70
A10: =Data!B10 -> Month1 | B10: =Data!C10 -> N | C10: =Data!D10 -> Mumbai | D10: =Data!E10 -> PowerSip | E10: =Data!F10 -> 22237 | F10: =Data!G10 -> 23794 | G10: =IF(D10="PowerSip", 135, IF(D10="HappyGrow", 60, "")) -> 135 | H10: =IF(D10="PowerSip", 140, IF(D10="HappyGrow", 70, "")) -> 140 | I10: =E10 * G10 -> 3001995 | J10: =F10 * H10 -> 3331160 | K10: =IF(E10=0, "", I10 / E10) -> 135 | L10: =IF(F10=0, "", J10 / F10) -> 140
A11: =Data!B11 -> Month1 | B11: =Data!C11 -> N | C11: =Data!D11 -> Mumbai | D11: =Data!E11 -> HappyGrow | E11: =Data!F11 -> 23421 | F11: =Data!G11 -> 23656 | G11: =IF(D11="PowerSip", 135, IF(D11="HappyGrow", 60, "")) -> 60 | H11: =IF(D11="PowerSip", 140, IF(D11="HappyGrow", 70, "")) -> 70 | I11: =E11 * G11 -> 1405260 | J11: =F11 * H11 -> 1655920 | K11: =IF(E11=0, "", I11 / E11) -> 60 | L11: =IF(F11=0, "", J11 / F11) -> 70
A12: =Data!B12 -> Month1 | B12: =Data!C12 -> E | C12: =Data!D12 -> Mumbai | D12: =Data!E12 -> PowerSip | E12: =Data!F12 -> 12469 | F12: =Data!G12 -> 13467 | G12: =IF(D12="PowerSip", 135, IF(D12="HappyGrow", 60, "")) -> 135 | H12: =IF(D12="PowerSip", 140, IF(D12="HappyGrow", 70, "")) -> 140 | I12: =E12 * G12 -> 1683315 | J12: =F12 * H12 -> 1885380 | K12: =IF(E12=0, "", I12 / E12) -> 135 | L12: =IF(F12=0, "", J12 / F12) -> 140
A13: =Data!B13 -> Month1 | B13: =Data!C13 -> E | C13: =Data!D13 -> Mumbai | D13: =Data!E13 -> HappyGrow | E13: =Data!F13 -> 16354 | F13: =Data!G13 -> 16518 | G13: =IF(D13="PowerSip", 135, IF(D13="HappyGrow", 60, "")) -> 60 | H13: =IF(D13="PowerSip", 140, IF(D13="HappyGrow", 70, "")) -> 70 | I13: =E13 * G13 -> 981240 | J13: =F13 * H13 -> 1156260 | K13: =IF(E13=0, "", I13 / E13) -> 60 | L13: =IF(F13=0, "", J13 / F13) -> 70
A14: =Data!B14 -> Month1 | B14: =Data!C14 -> W | C14: =Data!D14 -> Mumbai | D14: =Data!E14 -> PowerSip | E14: =Data!F14 -> 19536 | F14: =Data!G14 -> 21099 | G14: =IF(D14="PowerSip", 135, IF(D14="HappyGrow", 60, "")) -> 135 | H14: =IF(D14="PowerSip", 140, IF(D14="HappyGrow", 70, "")) -> 140 | I14: =E14 * G14 -> 2637360 | J14: =F14 * H14 -> 2953860 | K14: =IF(E14=0, "", I14 / E14) -> 135 | L14: =IF(F14=0, "", J14 / F14) -> 140
A15: =Data!B15 -> Month1 | B15: =Data!C15 -> W | C15: =Data!D15 -> Mumbai | D15: =Data!E15 -> HappyGrow | E15: =Data!F15 -> 11359 | F15: =Data!G15 -> 11587 | G15: =IF(D15="PowerSip", 135, IF(D15="HappyGrow", 60, "")) -> 60 | H15: =IF(D15="PowerSip", 140, IF(D15="HappyGrow", 70, "")) -> 70 | I15: =E15 * G15 -> 681540 | J15: =F15 * H15 -> 811090 | K15: =IF(E15=0, "", I15 / E15) -> 60 | L15: =IF(F15=0, "", J15 / F15) -> 70
A16: =Data!B16 -> Month1 | B16: =Data!C16 -> S | C16: =Data!D16 -> Mumbai | D16: =Data!E16 -> PowerSip | E16: =Data!F16 -> 12062 | F16: =Data!G16 -> 13148 | G16: =IF(D16="PowerSip", 135, IF(D16="HappyGrow", 60, "")) -> 135 | H16: =IF(D16="PowerSip", 140, IF(D16="HappyGrow", 70, "")) -> 140 | I16: =E16 * G16 -> 1628370 | J16: =F16 * H16 -> 1840720 | K16: =IF(E16=0, "", I16 / E16) -> 135 | L16: =IF(F16=0, "", J16 / F16) -> 140
A17: =Data!B17 -> Month1 | B17: =Data!C17 -> S | C17: =Data!D17 -> Mumbai | D17: =Data!E17 -> HappyGrow | E17: =Data!F17 -> 13579 | F17: =Data!G17 -> 13851 | G17: =IF(D17="PowerSip", 135, IF(D17="HappyGrow", 60, "")) -> 60 | H17: =IF(D17="PowerSip", 140, IF(D17="HappyGrow", 70, "")) -> 70 | I17: =E17 * G17 -> 814740 | J17: =F17 * H17 -> 969570 | K17: =IF(E17=0, "", I17 / E17) -> 60 | L17: =IF(F17=0, "", J17 / F17) -> 70
A18: =Data!B18 -> Month1 | B18: =Data!C18 -> N | C18: =Data!D18 -> Bengaluru | D18: =Data!E18 -> PowerSip | E18: =Data!F18 -> 21275 | F18: =Data!G18 -> 23190 | G18: =IF(D18="PowerSip", 135, IF(D18="HappyGrow", 60, "")) -> 135 | H18: =IF(D18="PowerSip", 140, IF(D18="HappyGrow", 70, "")) -> 140 | I18: =E18 * G18 -> 2872125 | J18: =F18 * H18 -> 3246600 | K18: =IF(E18=0, "", I18 / E18) -> 135 | L18: =IF(F18=0, "", J18 / F18) -> 140
A19: =Data!B19 -> Month1 | B19: =Data!C19 -> N | C19: =Data!D19 -> Bengaluru | D19: =Data!E19 -> HappyGrow | E19: =Data!F19 -> 18611 | F19: =Data!G19 -> 18984 | G19: =IF(D19="PowerSip", 135, IF(D19="HappyGrow", 60, "")) -> 60 | H19: =IF(D19="PowerSip", 140, IF(D19="HappyGrow", 70, "")) -> 70 | I19: =E19 * G19 -> 1116660 | J19: =F19 * H19 -> 1328880 | K19: =IF(E19=0, "", I19 / E19) -> 60 | L19: =IF(F19=0, "", J19 / F19) -> 70
A20: =Data!B20 -> Month1 | B20: =Data!C20 -> E | C20: =Data!D20 -> Bengaluru | D20: =Data!E20 -> PowerSip | E20: =Data!F20 -> 24050 | F20: =Data!G20 -> 26215 | G20: =IF(D20="PowerSip", 135, IF(D20="HappyGrow", 60, "")) -> 135 | H20: =IF(D20="PowerSip", 140, IF(D20="HappyGrow", 70, "")) -> 140 | I20: =E20 * G20 -> 3246750 | J20: =F20 * H20 -> 3670100 | K20: =IF(E20=0, "", I20 / E20) -> 135 | L20: =IF(F20=0, "", J20 / F20) -> 140
... A193: =Data!B193 -> Month6 | B193: =Data!C193 -> S | C193: =Data!D193 -> Delhi | D193: =Data!E193 -> HappyGrow | E193: =Data!F193 -> 32072 | F193: =Data!G193 -> 40090 | G193: =IF(D193="PowerSip", 135, IF(D193="HappyGrow", 60, "")) -> 60 | H193: =IF(D193="PowerSip", 140, IF(D193="HappyGrow", 70, "")) -> 70 | I193: =E193 * G193 -> 1924320 | J193: =F193 * H193 -> 2806300 | K193: =IF(E193=0, "", I193 / E193) -> 60 | L193: =IF(F193=0, "", J193 / F193) -> 70
A194: =Data!B194 | B194: =Data!C194 | C194: =Data!D194 | D194: =Data!E194 | E194: =Data!F194 | F194: =Data!G194 | G194: =IF(D194="PowerSip", 135, IF(D194="HappyGrow", 60, "")) | H194: =IF(D194="PowerSip", 140, IF(D194="HappyGrow", 70, ""))
A195: =Data!B195 | B195: =Data!C195 | C195: =Data!D195 | D195: =Data!E195 | E195: =Data!F195 | F195: =Data!G195 | G195: =IF(D195="PowerSip", 135, IF(D195="HappyGrow", 60, "")) | H195: =IF(D195="PowerSip", 140, IF(D195="HappyGrow", 70, ""))
A196: =Data!B196 | B196: =Data!C196 | C196: =Data!D196 | D196: =Data!E196 | E196: =Data!F196 | F196: =Data!G196 | G196: =IF(D196="PowerSip", 135, IF(D196="HappyGrow", 60, "")) | H196: =IF(D196="PowerSip", 140, IF(D196="HappyGrow", 70, ""))
A197: =Data!B197 | B197: =Data!C197 | C197: =Data!D197 | D197: =Data!E197 | E197: =Data!F197 | F197: =Data!G197 | G197: =IF(D197="PowerSip", 135, IF(D197="HappyGrow", 60, "")) | H197: =IF(D197="PowerSip", 140, IF(D197="HappyGrow", 70, ""))
A198: =Data!B198 | B198: =Data!C198 | C198: =Data!D198 | D198: =Data!E198 | E198: =Data!F198 | F198: =Data!G198 | G198: =IF(D198="PowerSip", 135, IF(D198="HappyGrow", 60, "")) | H198: =IF(D198="PowerSip", 140, IF(D198="HappyGrow", 70, ""))
A199: =Data!B199 | B199: =Data!C199 | C199: =Data!D199 | D199: =Data!E199 | E199: =Data!F199 | F199: =Data!G199 | G199: =IF(D199="PowerSip", 135, IF(D199="HappyGrow", 60, "")) | H199: =IF(D199="PowerSip", 140, IF(D199="HappyGrow", 70, ""))
A200: =Data!B200 | B200: =Data!C200 | C200: =Data!D200 | D200: =Data!E200 | E200: =Data!F200 | F200: =Data!G200 | G200: =IF(D200="PowerSip", 135, IF(D200="HappyGrow", 60, "")) | H200: =IF(D200="PowerSip", 140, IF(D200="HappyGrow", 70, ""))
A201: =Data!B201 | B201: =Data!C201 | C201: =Data!D201 | D201: =Data!E201 | E201: =Data!F201 | F201: =Data!G201 | G201: =IF(D201="PowerSip", 135, IF(D201="HappyGrow", 60, "")) | H201: =IF(D201="PowerSip", 140, IF(D201="HappyGrow", 70, ""))
A202: =Data!B202 | B202: =Data!C202 | C202: =Data!D202 | D202: =Data!E202 | E202: =Data!F202 | F202: =Data!G202 | G202: =IF(D202="PowerSip", 135, IF(D202="HappyGrow", 60, "")) | H202: =IF(D202="PowerSip", 140, IF(D202="HappyGrow", 70, ""))
A203: =Data!B203 | B203: =Data!C203 | C203: =Data!D203 | D203: =Data!E203 | E203: =Data!F203 | F203: =Data!G203 | G203: =IF(D203="PowerSip", 135, IF(D203="HappyGrow", 60, "")) | H203: =IF(D203="PowerSip", 140, IF(D203="HappyGrow", 70, ""))
A204: =Data!B204 | B204: =Data!C204 | C204: =Data!D204 | D204: =Data!E204 | E204: =Data!F204 | F204: =Data!G204 | G204: =IF(D204="PowerSip", 135, IF(D204="HappyGrow", 60, "")) | H204: =IF(D204="PowerSip", 140, IF(D204="HappyGrow", 70, ""))
A205: =Data!B205 | B205: =Data!C205 | C205: =Data!D205 | D205: =Data!E205 | E205: =Data!F205 | F205: =Data!G205 | G205: =IF(D205="PowerSip", 135, IF(D205="HappyGrow", 60, "")) | H205: =IF(D205="PowerSip", 140, IF(D205="HappyGrow", 70, ""))
... A270: =Data!B270 | B270: =Data!C270 | C270: =Data!D270 | D270: =Data!E270 | E270: =Data!F270 | F270: =Data!G270 | G270: =IF(D270="PowerSip", 135, IF(D270="HappyGrow", 60, "")) | H270: =IF(D270="PowerSip", 140, IF(D270="HappyGrow", 70, ""))

Sheet Assumption
A1: Quantity
A2: Item | B2: Pack (in ml) | C2: Existing Price (in Rs. per Pack) | D2: New Price (in Rs. per Pack)
A3: PowerSip | B3: 300 | C3: 135 | D3: 140
A4: HappyGrow | B4: 200 | C4: 60 | D4: 70
A7: Material Details of each Pack
A8: PowerSip
A9: Item | B9: Price/litre in Rs. | C9: Material %
A10: Water | B10: 8 | C10: 0.35
A11: Milk | B11: 50 | C11: 0.35
A12: Pea Protein Extract | B12: 400 | C12: 0.1
A13: Coffee Bean Extract | B13: 300 | C13: 0.1
A14: Dates Extract | B14: 90 | C14: 0.05
A15: Monk Fruit Extract | B15: 1100 | C15: 0.02
A16: Other Ingredients | B16: 1200 | C16: 0.03
A18: HappyGrow
A19: Item | B19: Price/kg in Rs. | C19: Material %
A20: Water | B20: 8 | C20: 0.42
A21: Oats Extract | B21: 80 | C21: 0.2
A22: Ragi Extract | B22: 40 | C22: 0.15
A23: Jowar Extract | B23: 29 | C23: 0.07
A24: Bajra Extract | B24: 25 | C24: 0.07
A25: Dates Extract | B25: 90 | C25: 0.06
A26: Other Ingredients | B26: 1200 | C26: 0.03
B28: Existing Pack | C28: New Pack
A29: Pack Cost (in Rs.) | B29: 2 | C29: 3
A30: Processing Cost (in Rs.) | B30: 8 | C30: 8
A32: Factory Expenses (in Rs.)
A33: Factory Rent | B33: 150000
A34: Cold Storage Cost | B34: 75000
A36: MARKETING Expenses (in Rs.) | B36: March Budget | C36: Month on Month Growth%
A37: Old marketing Budget | B37: 80000 | C37: 0.1
A39: Incremental marketing Cost (in Rs.) | B39: 1st Month
A40: Ads Preparation | B40: 10000000
A41: New Design | B41: 10000
A42: Incremental Advertising | B42: 30000000

Sheet Cost-Benefit Analysis
A1: Amount (in Rs) | B1: January | C1: February | D1: March | E1: April | F1: May | G1: June
A2: Contribution
A3: =Contribution_Old!A2 -> Old Plan | B3: =Contribution_Old!B$31 -> 33769679 | C3: =Contribution_Old!C$31 -> 36856628 | D3: =Contribution_Old!D$31 -> 40232112 | E3: =Contribution_Old!E$31 -> 43923260 | F3: =Contribution_Old!F$31 -> 47960310 | G3: =Contribution_Old!G$31 -> 52376138 | H3: =SUM(B3:G3) -> 255118127
A4: =Contribution_New!A2 -> New Plan | B4: =Contribution_New!B$31 -> 39957792 | C4: =Contribution_New!C$31 -> 45981864 | D4: =Contribution_New!D$31 -> 51788976 | E4: =Contribution_New!E$31 -> 59140498 | F4: =Contribution_New!F$31 -> 67713064 | G4: =Contribution_New!G$31 -> 77149409 | H4: =SUM(B4:G4) -> 3.417316e+08
A6: Incremental Contribution | B6: =B$4-B$3 -> 6188113.2 | C6: =C$4-C$3 -> 9125235.8 | D6: =D$4-D$3 -> 11556864 | E6: =E$4-E$3 -> 15217238 | F6: =F$4-F$3 -> 19752754 | G6: =G$4-G$3 -> 24773271 | H6: =SUM(B6:G6) -> 86613477
A8: Incremental Contribution
A9: =Assumption!A40 -> Ads Preparation | B9: =Assumption!B40 -> 10000000 | C9: 0 | D9: 0 | E9: 0 | F9: 0 | G9: 0
A10: =Assumption!A41 -> New Design | B10: =Assumption!B41 -> 10000 | C10: 0 | D10: 0 | E10: 0 | F10: 0 | G10: 0
A11: =Assumption!A42 -> Incremental Advertising | B11: =Assumption!$B$42/6 -> 5000000 | C11: =Assumption!$B$42/6 -> 5000000 | D11: =Assumption!$B$42/6 -> 5000000 | E11: =Assumption!$B$42/6 -> 5000000 | F11: =Assumption!$B$42/6 -> 5000000 | G11: =Assumption!$B$42/6 -> 5000000
A12: Total | B12: =SUM(B9:B11) -> 15010000 | C12: =SUM(C9:C11) -> 5000000 | D12: =SUM(D9:D11) -> 5000000 | E12: =SUM(E9:E11) -> 5000000 | F12: =SUM(F9:F11) -> 5000000 | G12: =SUM(G9:G11) -> 5000000
A14: Incremental Profits | B14: =B$6-B$12 -> -8821886.8 | C14: =C$6-C$12 -> 4125235.8 | D14: =D$6-D$12 -> 6556864.3 | E14: =E$6-E$12 -> 10217238 | F14: =F$6-F$12 -> 14752754 | G14: =G$6-G$12 -> 19773271 | H14: =SUM(B14:G14) -> 46603477

Sheet Dashboard 

Sheet Insight

Sheet Contribution_New
A1: Amount (in Rs) | B1: January | C1: February | D1: March | E1: April | F1: May | G1: June
A2: New Plan
A4: Sales
A5: PowerSip | B5: =SUMIFS('Sales Quantity'!$J:$J, 'Sales Quantity'!$A:$A, Details!A$14, 'Sales Quantity'!$D:$D, $A$5) -> 46463760 | C5: =SUMIFS('Sales Quantity'!$J:$J, 'Sales Quantity'!$A:$A, Details!B$14, 'Sales Quantity'!$D:$D, $A$5) -> 54229420 | D5: =SUMIFS('Sales Quantity'!$J:$J, 'Sales Quantity'!$A:$A, Details!C$14, 'Sales Quantity'!$D:$D, $A$5) -> 61464620 | E5: =SUMIFS('Sales Quantity'!$J:$J, 'Sales Quantity'!$A:$A, Details!D$14, 'Sales Quantity'!$D:$D, $A$5) -> 70967680 | F5: =SUMIFS('Sales Quantity'!$J:$J, 'Sales Quantity'!$A:$A, Details!E$14, 'Sales Quantity'!$D:$D, $A$5) -> 82241600 | G5: =SUMIFS('Sales Quantity'!$J:$J, 'Sales Quantity'!$A:$A, Details!F$14, 'Sales Quantity'!$D:$D, $A$5) -> 94788540
A6: HappyGrow | B6: =SUMIFS('Sales Quantity'!$J:$J, 'Sales Quantity'!$A:$A, Details!A$14, 'Sales Quantity'!$D:$D, $A$6) -> 19270300 | C6: =SUMIFS('Sales Quantity'!$J:$J, 'Sales Quantity'!$A:$A, Details!B$14, 'Sales Quantity'!$D:$D, $A$6) -> 21470890 | D6: =SUMIFS('Sales Quantity'!$J:$J, 'Sales Quantity'!$A:$A, Details!C$14, 'Sales Quantity'!$D:$D, $A$6) -> 23824500 | E6: =SUMIFS('Sales Quantity'!$J:$J, 'Sales Quantity'!$A:$A, Details!D$14, 'Sales Quantity'!$D:$D, $A$6) -> 26485760 | F6: =SUMIFS('Sales Quantity'!$J:$J, 'Sales Quantity'!$A:$A, Details!E$14, 'Sales Quantity'!$D:$D, $A$6) -> 29410780 | G6: =SUMIFS('Sales Quantity'!$J:$J, 'Sales Quantity'!$A:$A, Details!F$14, 'Sales Quantity'!$D:$D, $A$6) -> 32503590
A7: Total | B7: =SUM(B5:B6) -> 65734060 | C7: =SUM(C5:C6) -> 75700310 | D7: =SUM(D5:D6) -> 85289120 | E7: =SUM(E5:E6) -> 97453440 | F7: =SUM(F5:F6) -> 111652380 | G7: =SUM(G5:G6) -> 127292130
A9: Variable Cost
A10: =A5 -> PowerSip
A11: Material Cost | B11: ='Cost-RM'!B$39 -> 15213563 | C11: ='Cost-RM'!C$39 -> 17756262 | D11: ='Cost-RM'!D$39 -> 20125273 | E11: ='Cost-RM'!E$39 -> 23236846 | F11: ='Cost-RM'!F$39 -> 26928250 | G11: ='Cost-RM'!G$39 -> 31036476
A12: Packing Cost | B12: =Assumption!$C$29*'RM Consumed_PowerSip'!B$14 -> 995652 | C12: =Assumption!$C$29*'RM Consumed_PowerSip'!C$14 -> 1162059 | D12: =Assumption!$C$29*'RM Consumed_PowerSip'!D$14 -> 1317099 | E12: =Assumption!$C$29*'RM Consumed_PowerSip'!E$14 -> 1520736 | F12: =Assumption!$C$29*'RM Consumed_PowerSip'!F$14 -> 1762320 | G12: =Assumption!$C$29*'RM Consumed_PowerSip'!G$14 -> 2031183
A13: Processing Cost | B13: =Assumption!$C$30*'RM Consumed_PowerSip'!B$14 -> 2655072 | C13: =Assumption!$C$30*'RM Consumed_PowerSip'!C$14 -> 3098824 | D13: =Assumption!$C$30*'RM Consumed_PowerSip'!D$14 -> 3512264 | E13: =Assumption!$C$30*'RM Consumed_PowerSip'!E$14 -> 4055296 | F13: =Assumption!$C$30*'RM Consumed_PowerSip'!F$14 -> 4699520 | G13: =Assumption!$C$30*'RM Consumed_PowerSip'!G$14 -> 5416488
A14: Total | B14: =SUM(B11:B13) -> 18864287 | C14: =SUM(C11:C13) -> 22017145 | D14: =SUM(D11:D13) -> 24954636 | E14: =SUM(E11:E13) -> 28812878 | F14: =SUM(F11:F13) -> 33390090 | G14: =SUM(G11:G13) -> 38484147
A16: =A6 -> HappyGrow
A17: Material Cost | B17: ='Cost-RM'!B$49 -> 3883791.3 | C17: ='Cost-RM'!C$49 -> 4327304.5 | D17: ='Cost-RM'!D$49 -> 4801657.8 | E17: ='Cost-RM'!E$49 -> 5338015.7 | F17: ='Cost-RM'!F$49 -> 5927532.6 | G17: ='Cost-RM'!G$49 -> 6550866.4
A18: Packing Cost | B18: =Assumption!$C$29*'RM Consumed_HappyGrow'!B$14 -> 825870 | C18: =Assumption!$C$29*'RM Consumed_HappyGrow'!C$14 -> 920181 | D18: =Assumption!$C$29*'RM Consumed_HappyGrow'!D$14 -> 1021050 | E18: =Assumption!$C$29*'RM Consumed_HappyGrow'!E$14 -> 1135104 | F18: =Assumption!$C$29*'RM Consumed_HappyGrow'!F$14 -> 1260462 | G18: =Assumption!$C$29*'RM Consumed_HappyGrow'!G$14 -> 1393011
A19: Processing Cost | B19: =Assumption!$C$30*'RM Consumed_HappyGrow'!B$14 -> 2202320 | C19: =Assumption!$C$30*'RM Consumed_HappyGrow'!C$14 -> 2453816 | D19: =Assumption!$C$30*'RM Consumed_HappyGrow'!D$14 -> 2722800 | E19: =Assumption!$C$30*'RM Consumed_HappyGrow'!E$14 -> 3026944 | F19: =Assumption!$C$30*'RM Consumed_HappyGrow'!F$14 -> 3361232 | G19: =Assumption!$C$30*'RM Consumed_HappyGrow'!G$14 -> 3714696
A20: Total | B20: =SUM(B17:B19) -> 6911981.3 | C20: =SUM(C17:C19) -> 7701301.5 | D20: =SUM(D17:D19) -> 8545507.8 | E20: =SUM(E17:E19) -> 9500063.7 | F20: =SUM(F17:F19) -> 10549227 | G20: =SUM(G17:G19) -> 11658573
A22: Total Variable Cost
A23: =A5 -> PowerSip | B23: =B$14 -> 18864287 | C23: =C$14 -> 22017145 | D23: =D$14 -> 24954636 | E23: =E$14 -> 28812878 | F23: =F$14 -> 33390090 | G23: =G$14 -> 38484147
A24: =A6 -> HappyGrow | B24: =B$20 -> 6911981.3 | C24: =C$20 -> 7701301.5 | D24: =D$20 -> 8545507.8 | E24: =E$20 -> 9500063.7 | F24: =F$20 -> 10549227 | G24: =G$20 -> 11658573
A25: =A22 -> Total Variable Cost | B25: =SUM(B23:B24) -> 25776268 | C25: =SUM(C23:C24) -> 29718446 | D25: =SUM(D23:D24) -> 33500144 | E25: =SUM(E23:E24) -> 38312942 | F25: =SUM(F23:F24) -> 43939316 | G25: =SUM(G23:G24) -> 50142721
A28: Contribution (Sales-Variable Cost)
A29: =A5 -> PowerSip | B29: =B$5-B$23 -> 27599473 | C29: =C$5-C$23 -> 32212275 | D29: =D$5-D$23 -> 36509984 | E29: =E$5-E$23 -> 42154802 | F29: =F$5-F$23 -> 48851510 | G29: =G$5-G$23 -> 56304393
A30: =A6 -> HappyGrow | B30: =B$6-B$24 -> 12358319 | C30: =C$6-C$24 -> 13769588 | D30: =D$6-D$24 -> 15278992 | E30: =E$6-E$24 -> 16985696 | F30: =F$6-F$24 -> 18861553 | G30: =G$6-G$24 -> 20845017
A31: Total | B31: =SUM(B29:B30) -> 39957792 | C31: =SUM(C29:C30) -> 45981864 | D31: =SUM(D29:D30) -> 51788976 | E31: =SUM(E29:E30) -> 59140498 | F31: =SUM(F29:F30) -> 67713064 | G31: =SUM(G29:G30) -> 77149409
A33: Contribution Per Unit(in Rs.)
A34: =A5 -> PowerSip | B34: =Assumption!$D$3-('Cost-RM'!B$52+Assumption!$C$29+Assumption!$C$30) -> 83.16 | C34: =Assumption!$D$3-('Cost-RM'!C$52+Assumption!$C$29+Assumption!$C$30) -> 83.16 | D34: =Assumption!$D$3-('Cost-RM'!D$52+Assumption!$C$29+Assumption!$C$30) -> 83.16 | E34: =Assumption!$D$3-('Cost-RM'!E$52+Assumption!$C$29+Assumption!$C$30) -> 83.16 | F34: =Assumption!$D$3-('Cost-RM'!F$52+Assumption!$C$29+Assumption!$C$30) -> 83.16 | G34: =Assumption!$D$3-('Cost-RM'!G$52+Assumption!$C$29+Assumption!$C$30) -> 83.16
A35: =A6 -> HappyGrow | B35: =Assumption!$D$4-('Cost-RM'!B$53+Assumption!$C$29+Assumption!$C$30) -> 44.892 | C35: =Assumption!$D$4-('Cost-RM'!C$53+Assumption!$C$29+Assumption!$C$30) -> 44.892 | D35: =Assumption!$D$4-('Cost-RM'!D$53+Assumption!$C$29+Assumption!$C$30) -> 44.892 | E35: =Assumption!$D$4-('Cost-RM'!E$53+Assumption!$C$29+Assumption!$C$30) -> 44.892 | F35: =Assumption!$D$4-('Cost-RM'!F$53+Assumption!$C$29+Assumption!$C$30) -> 44.892 | G35: =Assumption!$D$4-('Cost-RM'!G$53+Assumption!$C$29+Assumption!$C$30) -> 44.892
A36: Total | B36: =SUM(B34:B35) -> 128.052 | C36: =SUM(C34:C35) -> 128.052 | D36: =SUM(D34:D35) -> 128.052 | E36: =SUM(E34:E35) -> 128.052 | F36: =SUM(F34:F35) -> 128.052 | G36: =SUM(G34:G35) -> 128.052

Sheet Contribution_Old
A1: Amount (in Rs) | B1: January | C1: February | D1: March | E1: April | F1: May | G1: June
A2: Old Plan
A4: Sales
A5: PowerSip | B5: =SUMIFS('Sales Quantity'!$I:$I, 'Sales Quantity'!$A:$A, Details!A$14, 'Sales Quantity'!$D:$D, $A$5) -> 41098860 | C5: =SUMIFS('Sales Quantity'!$I:$I, 'Sales Quantity'!$A:$A, Details!B$14, 'Sales Quantity'!$D:$D, $A$5) -> 45208935 | D5: =SUMIFS('Sales Quantity'!$I:$I, 'Sales Quantity'!$A:$A, Details!C$14, 'Sales Quantity'!$D:$D, $A$5) -> 49730220 | E5: =SUMIFS('Sales Quantity'!$I:$I, 'Sales Quantity'!$A:$A, Details!D$14, 'Sales Quantity'!$D:$D, $A$5) -> 54703350 | F5: =SUMIFS('Sales Quantity'!$I:$I, 'Sales Quantity'!$A:$A, Details!E$14, 'Sales Quantity'!$D:$D, $A$5) -> 60173955 | G5: =SUMIFS('Sales Quantity'!$I:$I, 'Sales Quantity'!$A:$A, Details!F$14, 'Sales Quantity'!$D:$D, $A$5) -> 66191310
A6: HappyGrow | B6: =SUMIFS('Sales Quantity'!$I:$I, 'Sales Quantity'!$A:$A, Details!A$14, 'Sales Quantity'!$D:$D, $A$6) -> 16166040 | C6: =SUMIFS('Sales Quantity'!$I:$I, 'Sales Quantity'!$A:$A, Details!B$14, 'Sales Quantity'!$D:$D, $A$6) -> 17297640 | D6: =SUMIFS('Sales Quantity'!$I:$I, 'Sales Quantity'!$A:$A, Details!C$14, 'Sales Quantity'!$D:$D, $A$6) -> 18508500 | E6: =SUMIFS('Sales Quantity'!$I:$I, 'Sales Quantity'!$A:$A, Details!D$14, 'Sales Quantity'!$D:$D, $A$6) -> 19804140 | F6: =SUMIFS('Sales Quantity'!$I:$I, 'Sales Quantity'!$A:$A, Details!E$14, 'Sales Quantity'!$D:$D, $A$6) -> 21190380 | G6: =SUMIFS('Sales Quantity'!$I:$I, 'Sales Quantity'!$A:$A, Details!F$14, 'Sales Quantity'!$D:$D, $A$6) -> 22673880
A7: Total | B7: =SUM(B5:B6) -> 57264900 | C7: =SUM(C5:C6) -> 62506575 | D7: =SUM(D5:D6) -> 68238720 | E7: =SUM(E5:E6) -> 74507490 | F7: =SUM(F5:F6) -> 81364335 | G7: =SUM(G5:G6) -> 88865190
A9: Variable Cost
A10: =A5 -> PowerSip
A11: Material Cost | B11: ='Cost-RM'!B$12 -> 13955346 | C11: ='Cost-RM'!C$12 -> 15350945 | D11: ='Cost-RM'!D$12 -> 16886172 | E11: ='Cost-RM'!E$12 -> 18574826 | F11: ='Cost-RM'!F$12 -> 20432401 | G11: ='Cost-RM'!G$12 -> 22475627
A12: Packing Cost | B12: =Assumption!$B$29*'RM Consumed_PowerSip'!B$13 -> 608872 | C12: =Assumption!$B$29*'RM Consumed_PowerSip'!C$13 -> 669762 | D12: =Assumption!$B$29*'RM Consumed_PowerSip'!D$13 -> 736744 | E12: =Assumption!$B$29*'RM Consumed_PowerSip'!E$13 -> 810420 | F12: =Assumption!$B$29*'RM Consumed_PowerSip'!F$13 -> 891466 | G12: =Assumption!$B$29*'RM Consumed_PowerSip'!G$13 -> 980612
A13: Processing Cost | B13: =Assumption!$B$30*'RM Consumed_PowerSip'!B$13 -> 2435488 | C13: =Assumption!$B$30*'RM Consumed_PowerSip'!C$13 -> 2679048 | D13: =Assumption!$B$30*'RM Consumed_PowerSip'!D$13 -> 2946976 | E13: =Assumption!$B$30*'RM Consumed_PowerSip'!E$13 -> 3241680 | F13: =Assumption!$B$30*'RM Consumed_PowerSip'!F$13 -> 3565864 | G13: =Assumption!$B$30*'RM Consumed_PowerSip'!G$13 -> 3922448
A14: Total | B14: =SUM(B11:B13) -> 16999706 | C14: =SUM(C11:C13) -> 18699755 | D14: =SUM(D11:D13) -> 20569892 | E14: =SUM(E11:E13) -> 22626926 | F14: =SUM(F11:F13) -> 24889731 | G14: =SUM(G11:G13) -> 27378687
A16: =A6 -> HappyGrow
A17: Material Cost | B17: ='Cost-RM'!B$22 -> 3801174.9 | C17: ='Cost-RM'!C$22 -> 4067251.8 | D17: ='Cost-RM'!D$22 -> 4351965.3 | E17: ='Cost-RM'!E$22 -> 4656613.5 | F17: ='Cost-RM'!F$22 -> 4982564.7 | G17: ='Cost-RM'!G$22 -> 5331385
A18: Packing Cost | B18: =Assumption!$B$29*'RM Consumed_HappyGrow'!B$13 -> 538868 | C18: =Assumption!$B$29*'RM Consumed_HappyGrow'!C$13 -> 576588 | D18: =Assumption!$B$29*'RM Consumed_HappyGrow'!D$13 -> 616950 | E18: =Assumption!$B$29*'RM Consumed_HappyGrow'!E$13 -> 660138 | F18: =Assumption!$B$29*'RM Consumed_HappyGrow'!F$13 -> 706346 | G18: =Assumption!$B$29*'RM Consumed_HappyGrow'!G$13 -> 755796
A19: Processing Cost | B19: =Assumption!$B$30*'RM Consumed_HappyGrow'!B$13 -> 2155472 | C19: =Assumption!$B$30*'RM Consumed_HappyGrow'!C$13 -> 2306352 | D19: =Assumption!$B$30*'RM Consumed_HappyGrow'!D$13 -> 2467800 | E19: =Assumption!$B$30*'RM Consumed_HappyGrow'!E$13 -> 2640552 | F19: =Assumption!$B$30*'RM Consumed_HappyGrow'!F$13 -> 2825384 | G19: =Assumption!$B$30*'RM Consumed_HappyGrow'!G$13 -> 3023184
A20: Total | B20: =SUM(B17:B19) -> 6495514.9 | C20: =SUM(C17:C19) -> 6950191.8 | D20: =SUM(D17:D19) -> 7436715.3 | E20: =SUM(E17:E19) -> 7957303.5 | F20: =SUM(F17:F19) -> 8514294.7 | G20: =SUM(G17:G19) -> 9110365
A22: Total Variable Cost
A23: =A5 -> PowerSip | B23: =B$14 -> 16999706 | C23: =C$14 -> 18699755 | D23: =D$14 -> 20569892 | E23: =E$14 -> 22626926 | F23: =F$14 -> 24889731 | G23: =G$14 -> 27378687
A24: =A6 -> HappyGrow | B24: =B$20 -> 6495514.9 | C24: =C$20 -> 6950191.8 | D24: =D$20 -> 7436715.3 | E24: =E$20 -> 7957303.5 | F24: =F$20 -> 8514294.7 | G24: =G$20 -> 9110365
A25: =A22 -> Total Variable Cost | B25: =SUM(B23:B24) -> 23495221 | C25: =SUM(C23:C24) -> 25649947 | D25: =SUM(D23:D24) -> 28006608 | E25: =SUM(E23:E24) -> 30584230 | F25: =SUM(F23:F24) -> 33404025 | G25: =SUM(G23:G24) -> 36489052
A28: Contribution (Sales-Variable Cost)
A29: =A5 -> PowerSip | B29: =B$5-B$23 -> 24099154 | C29: =C$5-C$23 -> 26509180 | D29: =D$5-D$23 -> 29160328 | E29: =E$5-E$23 -> 32076424 | F29: =F$5-F$23 -> 35284224 | G29: =G$5-G$23 -> 38812623
A30: =A6 -> HappyGrow | B30: =B$6-B$24 -> 9670525.1 | C30: =C$6-C$24 -> 10347448 | D30: =D$6-D$24 -> 11071785 | E30: =E$6-E$24 -> 11846837 | F30: =F$6-F$24 -> 12676085 | G30: =G$6-G$24 -> 13563515
A31: Total | B31: =SUM(B29:B30) -> 33769679 | C31: =SUM(C29:C30) -> 36856628 | D31: =SUM(D29:D30) -> 40232112 | E31: =SUM(E29:E30) -> 43923260 | F31: =SUM(F29:F30) -> 47960310 | G31: =SUM(G29:G30) -> 52376138
A33: Contribution Per Unit(in Rs.)
A34: =A5 -> PowerSip | B34: =Assumption!$C$3-('Cost-RM'!B$52+Assumption!$B$29+Assumption!$B$30) -> 79.16 | C34: =Assumption!$C$3-('Cost-RM'!C$52+Assumption!$B$29+Assumption!$B$30) -> 79.16 | D34: =Assumption!$C$3-('Cost-RM'!D$52+Assumption!$B$29+Assumption!$B$30) -> 79.16 | E34: =Assumption!$C$3-('Cost-RM'!E$52+Assumption!$B$29+Assumption!$B$30) -> 79.16 | F34: =Assumption!$C$3-('Cost-RM'!F$52+Assumption!$B$29+Assumption!$B$30) -> 79.16 | G34: =Assumption!$C$3-('Cost-RM'!G$52+Assumption!$B$29+Assumption!$B$30) -> 79.16
A35: =A6 -> HappyGrow | B35: =Assumption!$C$4-('Cost-RM'!B$53+Assumption!$B$29+Assumption!$B$30) -> 35.892 | C35: =Assumption!$C$4-('Cost-RM'!C$53+Assumption!$B$29+Assumption!$B$30) -> 35.892 | D35: =Assumption!$C$4-('Cost-RM'!D$53+Assumption!$B$29+Assumption!$B$30) -> 35.892 | E35: =Assumption!$C$4-('Cost-RM'!E$53+Assumption!$B$29+Assumption!$B$30) -> 35.892 | F35: =Assumption!$C$4-('Cost-RM'!F$53+Assumption!$B$29+Assumption!$B$30) -> 35.892 | G35: =Assumption!$C$4-('Cost-RM'!G$53+Assumption!$B$29+Assumption!$B$30) -> 35.892
A36: Total | B36: =SUM(B34:B35) -> 115.052 | C36: =SUM(C34:C35) -> 115.052 | D36: =SUM(D34:D35) -> 115.052 | E36: =SUM(E34:E35) -> 115.052 | F36: =SUM(F34:F35) -> 115.052 | G36: =SUM(G34:G35) -> 115.052

Sheet Cost-RM
A1: Cost In(Rs) | B1: =Details!A15 -> January | C1: =Details!B15 -> February | D1: =Details!C15 -> March | E1: =Details!D15 -> April | F1: =Details!E15 -> May | G1: =Details!F15 -> June
A2: Old Plan
A4: =Assumption!A8 -> PowerSip
A5: =Assumption!A10 -> Water | B5: =(Assumption!$C10 * Assumption!$B$3 *'RM Consumed_PowerSip'!B$13)*Assumption!$B10/1000 -> 255726.24 | C5: =(Assumption!$C10 * Assumption!$B$3 *'RM Consumed_PowerSip'!C$13)*Assumption!$B10/1000 -> 281300.04 | D5: =(Assumption!$C10 * Assumption!$B$3 *'RM Consumed_PowerSip'!D$13)*Assumption!$B10/1000 -> 309432.48 | E5: =(Assumption!$C10 * Assumption!$B$3 *'RM Consumed_PowerSip'!E$13)*Assumption!$B10/1000 -> 340376.4 | F5: =(Assumption!$C10 * Assumption!$B$3 *'RM Consumed_PowerSip'!F$13)*Assumption!$B10/1000 -> 374415.72 | G5: =(Assumption!$C10 * Assumption!$B$3 *'RM Consumed_PowerSip'!G$13)*Assumption!$B10/1000 -> 411857.04
A6: =Assumption!A11 -> Milk | B6: =(Assumption!$C11 * Assumption!$B$3 *'RM Consumed_PowerSip'!B$13)*Assumption!$B11/1000 -> 1598289 | C6: =(Assumption!$C11 * Assumption!$B$3 *'RM Consumed_PowerSip'!C$13)*Assumption!$B11/1000 -> 1758125.2 | D6: =(Assumption!$C11 * Assumption!$B$3 *'RM Consumed_PowerSip'!D$13)*Assumption!$B11/1000 -> 1933953 | E6: =(Assumption!$C11 * Assumption!$B$3 *'RM Consumed_PowerSip'!E$13)*Assumption!$B11/1000 -> 2127352.5 | F6: =(Assumption!$C11 * Assumption!$B$3 *'RM Consumed_PowerSip'!F$13)*Assumption!$B11/1000 -> 2340098.2 | G6: =(Assumption!$C11 * Assumption!$B$3 *'RM Consumed_PowerSip'!G$13)*Assumption!$B11/1000 -> 2574106.5
A7: =Assumption!A12 -> Pea Protein Extract | B7: =(Assumption!$C12 * Assumption!$B$3 *'RM Consumed_PowerSip'!B$13)*Assumption!$B12/1000 -> 3653232 | C7: =(Assumption!$C12 * Assumption!$B$3 *'RM Consumed_PowerSip'!C$13)*Assumption!$B12/1000 -> 4018572 | D7: =(Assumption!$C12 * Assumption!$B$3 *'RM Consumed_PowerSip'!D$13)*Assumption!$B12/1000 -> 4420464 | E7: =(Assumption!$C12 * Assumption!$B$3 *'RM Consumed_PowerSip'!E$13)*Assumption!$B12/1000 -> 4862520 | F7: =(Assumption!$C12 * Assumption!$B$3 *'RM Consumed_PowerSip'!F$13)*Assumption!$B12/1000 -> 5348796 | G7: =(Assumption!$C12 * Assumption!$B$3 *'RM Consumed_PowerSip'!G$13)*Assumption!$B12/1000 -> 5883672
A8: =Assumption!A13 -> Coffee Bean Extract | B8: =(Assumption!$C13 * Assumption!$B$3 *'RM Consumed_PowerSip'!B$13)*Assumption!$B13/1000 -> 2739924 | C8: =(Assumption!$C13 * Assumption!$B$3 *'RM Consumed_PowerSip'!C$13)*Assumption!$B13/1000 -> 3013929 | D8: =(Assumption!$C13 * Assumption!$B$3 *'RM Consumed_PowerSip'!D$13)*Assumption!$B13/1000 -> 3315348 | E8: =(Assumption!$C13 * Assumption!$B$3 *'RM Consumed_PowerSip'!E$13)*Assumption!$B13/1000 -> 3646890 | F8: =(Assumption!$C13 * Assumption!$B$3 *'RM Consumed_PowerSip'!F$13)*Assumption!$B13/1000 -> 4011597 | G8: =(Assumption!$C13 * Assumption!$B$3 *'RM Consumed_PowerSip'!G$13)*Assumption!$B13/1000 -> 4412754
A9: =Assumption!A14 -> Dates Extract | B9: =(Assumption!$C14 * Assumption!$B$3 *'RM Consumed_PowerSip'!B$13)*Assumption!$B14/1000 -> 410988.6 | C9: =(Assumption!$C14 * Assumption!$B$3 *'RM Consumed_PowerSip'!C$13)*Assumption!$B14/1000 -> 452089.35 | D9: =(Assumption!$C14 * Assumption!$B$3 *'RM Consumed_PowerSip'!D$13)*Assumption!$B14/1000 -> 497302.2 | E9: =(Assumption!$C14 * Assumption!$B$3 *'RM Consumed_PowerSip'!E$13)*Assumption!$B14/1000 -> 547033.5 | F9: =(Assumption!$C14 * Assumption!$B$3 *'RM Consumed_PowerSip'!F$13)*Assumption!$B14/1000 -> 601739.55 | G9: =(Assumption!$C14 * Assumption!$B$3 *'RM Consumed_PowerSip'!G$13)*Assumption!$B14/1000 -> 661913.1
A10: =Assumption!A15 -> Monk Fruit Extract | B10: =(Assumption!$C15 * Assumption!$B$3 *'RM Consumed_PowerSip'!B$13)*Assumption!$B15/1000 -> 2009277.6 | C10: =(Assumption!$C15 * Assumption!$B$3 *'RM Consumed_PowerSip'!C$13)*Assumption!$B15/1000 -> 2210214.6 | D10: =(Assumption!$C15 * Assumption!$B$3 *'RM Consumed_PowerSip'!D$13)*Assumption!$B15/1000 -> 2431255.2 | E10: =(Assumption!$C15 * Assumption!$B$3 *'RM Consumed_PowerSip'!E$13)*Assumption!$B15/1000 -> 2674386 | F10: =(Assumption!$C15 * Assumption!$B$3 *'RM Consumed_PowerSip'!F$13)*Assumption!$B15/1000 -> 2941837.8 | G10: =(Assumption!$C15 * Assumption!$B$3 *'RM Consumed_PowerSip'!G$13)*Assumption!$B15/1000 -> 3236019.6
A11: =Assumption!A16 -> Other Ingredients | B11: =(Assumption!$C16 * Assumption!$B$3 *'RM Consumed_PowerSip'!B$13)*Assumption!$B16/1000 -> 3287908.8 | C11: =(Assumption!$C16 * Assumption!$B$3 *'RM Consumed_PowerSip'!C$13)*Assumption!$B16/1000 -> 3616714.8 | D11: =(Assumption!$C16 * Assumption!$B$3 *'RM Consumed_PowerSip'!D$13)*Assumption!$B16/1000 -> 3978417.6 | E11: =(Assumption!$C16 * Assumption!$B$3 *'RM Consumed_PowerSip'!E$13)*Assumption!$B16/1000 -> 4376268 | F11: =(Assumption!$C16 * Assumption!$B$3 *'RM Consumed_PowerSip'!F$13)*Assumption!$B16/1000 -> 4813916.4 | G11: =(Assumption!$C16 * Assumption!$B$3 *'RM Consumed_PowerSip'!G$13)*Assumption!$B16/1000 -> 5295304.8
A12: Total | B12: =SUM(B5:B11) -> 13955346 | C12: =SUM(C5:C11) -> 15350945 | D12: =SUM(D5:D11) -> 16886172 | E12: =SUM(E5:E11) -> 18574826 | F12: =SUM(F5:F11) -> 20432401 | G12: =SUM(G5:G11) -> 22475627
A13: =Assumption!A17
A14: =Assumption!A18 -> HappyGrow
A15: =Assumption!A20 -> Water | B15: =(Assumption!$C20*Assumption!$B$4*'RM Consumed_HappyGrow'!B$13)*Assumption!$B20/1000 -> 181059.65 | C15: =(Assumption!$C20*Assumption!$B$4*'RM Consumed_HappyGrow'!C$13)*Assumption!$B20/1000 -> 193733.57 | D15: =(Assumption!$C20*Assumption!$B$4*'RM Consumed_HappyGrow'!D$13)*Assumption!$B20/1000 -> 207295.2 | E15: =(Assumption!$C20*Assumption!$B$4*'RM Consumed_HappyGrow'!E$13)*Assumption!$B20/1000 -> 221806.37 | F15: =(Assumption!$C20*Assumption!$B$4*'RM Consumed_HappyGrow'!F$13)*Assumption!$B20/1000 -> 237332.26 | G15: =(Assumption!$C20*Assumption!$B$4*'RM Consumed_HappyGrow'!G$13)*Assumption!$B20/1000 -> 253947.46
A16: =Assumption!A21 -> Oats Extract | B16: =(Assumption!$C21*Assumption!$B$4*'RM Consumed_HappyGrow'!B$13)*Assumption!$B21/1000 -> 862188.8 | C16: =(Assumption!$C21*Assumption!$B$4*'RM Consumed_HappyGrow'!C$13)*Assumption!$B21/1000 -> 922540.8 | D16: =(Assumption!$C21*Assumption!$B$4*'RM Consumed_HappyGrow'!D$13)*Assumption!$B21/1000 -> 987120 | E16: =(Assumption!$C21*Assumption!$B$4*'RM Consumed_HappyGrow'!E$13)*Assumption!$B21/1000 -> 1056220.8 | F16: =(Assumption!$C21*Assumption!$B$4*'RM Consumed_HappyGrow'!F$13)*Assumption!$B21/1000 -> 1130153.6 | G16: =(Assumption!$C21*Assumption!$B$4*'RM Consumed_HappyGrow'!G$13)*Assumption!$B21/1000 -> 1209273.6
A17: =Assumption!A22 -> Ragi Extract | B17: =(Assumption!$C22*Assumption!$B$4*'RM Consumed_HappyGrow'!B$13)*Assumption!$B22/1000 -> 323320.8 | C17: =(Assumption!$C22*Assumption!$B$4*'RM Consumed_HappyGrow'!C$13)*Assumption!$B22/1000 -> 345952.8 | D17: =(Assumption!$C22*Assumption!$B$4*'RM Consumed_HappyGrow'!D$13)*Assumption!$B22/1000 -> 370170 | E17: =(Assumption!$C22*Assumption!$B$4*'RM Consumed_HappyGrow'!E$13)*Assumption!$B22/1000 -> 396082.8 | F17: =(Assumption!$C22*Assumption!$B$4*'RM Consumed_HappyGrow'!F$13)*Assumption!$B22/1000 -> 423807.6 | G17: =(Assumption!$C22*Assumption!$B$4*'RM Consumed_HappyGrow'!G$13)*Assumption!$B22/1000 -> 453477.6
A18: =Assumption!A23 -> Jowar Extract | B18: =(Assumption!$C23*Assumption!$B$4*'RM Consumed_HappyGrow'!B$13)*Assumption!$B23/1000 -> 109390.2 | C18: =(Assumption!$C23*Assumption!$B$4*'RM Consumed_HappyGrow'!C$13)*Assumption!$B23/1000 -> 117047.36 | D18: =(Assumption!$C23*Assumption!$B$4*'RM Consumed_HappyGrow'!D$13)*Assumption!$B23/1000 -> 125240.85 | E18: =(Assumption!$C23*Assumption!$B$4*'RM Consumed_HappyGrow'!E$13)*Assumption!$B23/1000 -> 134008.01 | F18: =(Assumption!$C23*Assumption!$B$4*'RM Consumed_HappyGrow'!F$13)*Assumption!$B23/1000 -> 143388.24 | G18: =(Assumption!$C23*Assumption!$B$4*'RM Consumed_HappyGrow'!G$13)*Assumption!$B23/1000 -> 153426.59
A19: =Assumption!A24 -> Bajra Extract | B19: =(Assumption!$C24*Assumption!$B$4*'RM Consumed_HappyGrow'!B$13)*Assumption!$B24/1000 -> 94301.9 | C19: =(Assumption!$C24*Assumption!$B$4*'RM Consumed_HappyGrow'!C$13)*Assumption!$B24/1000 -> 100902.9 | D19: =(Assumption!$C24*Assumption!$B$4*'RM Consumed_HappyGrow'!D$13)*Assumption!$B24/1000 -> 107966.25 | E19: =(Assumption!$C24*Assumption!$B$4*'RM Consumed_HappyGrow'!E$13)*Assumption!$B24/1000 -> 115524.15 | F19: =(Assumption!$C24*Assumption!$B$4*'RM Consumed_HappyGrow'!F$13)*Assumption!$B24/1000 -> 123610.55 | G19: =(Assumption!$C24*Assumption!$B$4*'RM Consumed_HappyGrow'!G$13)*Assumption!$B24/1000 -> 132264.3
A20: =Assumption!A25 -> Dates Extract | B20: =(Assumption!$C25*Assumption!$B$4*'RM Consumed_HappyGrow'!B$13)*Assumption!$B25/1000 -> 290988.72 | C20: =(Assumption!$C25*Assumption!$B$4*'RM Consumed_HappyGrow'!C$13)*Assumption!$B25/1000 -> 311357.52 | D20: =(Assumption!$C25*Assumption!$B$4*'RM Consumed_HappyGrow'!D$13)*Assumption!$B25/1000 -> 333153 | E20: =(Assumption!$C25*Assumption!$B$4*'RM Consumed_HappyGrow'!E$13)*Assumption!$B25/1000 -> 356474.52 | F20: =(Assumption!$C25*Assumption!$B$4*'RM Consumed_HappyGrow'!F$13)*Assumption!$B25/1000 -> 381426.84 | G20: =(Assumption!$C25*Assumption!$B$4*'RM Consumed_HappyGrow'!G$13)*Assumption!$B25/1000 -> 408129.84
A21: =Assumption!A26 -> Other Ingredients | B21: =(Assumption!$C26*Assumption!$B$4*'RM Consumed_HappyGrow'!B$13)*Assumption!$B26/1000 -> 1939924.8 | C21: =(Assumption!$C26*Assumption!$B$4*'RM Consumed_HappyGrow'!C$13)*Assumption!$B26/1000 -> 2075716.8 | D21: =(Assumption!$C26*Assumption!$B$4*'RM Consumed_HappyGrow'!D$13)*Assumption!$B26/1000 -> 2221020 | E21: =(Assumption!$C26*Assumption!$B$4*'RM Consumed_HappyGrow'!E$13)*Assumption!$B26/1000 -> 2376496.8 | F21: =(Assumption!$C26*Assumption!$B$4*'RM Consumed_HappyGrow'!F$13)*Assumption!$B26/1000 -> 2542845.6 | G21: =(Assumption!$C26*Assumption!$B$4*'RM Consumed_HappyGrow'!G$13)*Assumption!$B26/1000 -> 2720865.6
A22: Total | B22: =SUM(B15:B21) -> 3801174.9 | C22: =SUM(C15:C21) -> 4067251.8 | D22: =SUM(D15:D21) -> 4351965.3 | E22: =SUM(E15:E21) -> 4656613.5 | F22: =SUM(F15:F21) -> 4982564.7 | G22: =SUM(G15:G21) -> 5331385
A24: Cost Per Unit (Rs.)
A25: =A4 -> PowerSip | B25: =(B$12/'RM Consumed_PowerSip'!B$13) -> 45.84 | C25: =(C$12/'RM Consumed_PowerSip'!C$13) -> 45.84 | D25: =(D$12/'RM Consumed_PowerSip'!D$13) -> 45.84 | E25: =(E$12/'RM Consumed_PowerSip'!E$13) -> 45.84 | F25: =(F$12/'RM Consumed_PowerSip'!F$13) -> 45.84 | G25: =(G$12/'RM Consumed_PowerSip'!G$13) -> 45.84
A26: =A14 -> HappyGrow | B26: =(B22/'RM Consumed_HappyGrow'!B13) -> 14.108 | C26: =(C22/'RM Consumed_HappyGrow'!C13) -> 14.108 | D26: =(D22/'RM Consumed_HappyGrow'!D13) -> 14.108 | E26: =(E22/'RM Consumed_HappyGrow'!E13) -> 14.108 | F26: =(F22/'RM Consumed_HappyGrow'!F13) -> 14.108 | G26: =(G22/'RM Consumed_HappyGrow'!G13) -> 14.108
A29: New Plan
A31: =Assumption!A8 -> PowerSip
A32: =Assumption!A10 -> Water | B32: =(Assumption!$C10*Assumption!$B$3*'RM Consumed_PowerSip'!B$14)*Assumption!$B10/1000 -> 278782.56 | C32: =(Assumption!$C10*Assumption!$B$3*'RM Consumed_PowerSip'!C$14)*Assumption!$B10/1000 -> 325376.52 | D32: =(Assumption!$C10*Assumption!$B$3*'RM Consumed_PowerSip'!D$14)*Assumption!$B10/1000 -> 368787.72 | E32: =(Assumption!$C10*Assumption!$B$3*'RM Consumed_PowerSip'!E$14)*Assumption!$B10/1000 -> 425806.08 | F32: =(Assumption!$C10*Assumption!$B$3*'RM Consumed_PowerSip'!F$14)*Assumption!$B10/1000 -> 493449.6 | G32: =(Assumption!$C10*Assumption!$B$3*'RM Consumed_PowerSip'!G$14)*Assumption!$B10/1000 -> 568731.24
A33: =Assumption!A11 -> Milk | B33: =(Assumption!$C11*Assumption!$B$3*'RM Consumed_PowerSip'!B$14)*Assumption!$B11/1000 -> 1742391 | C33: =(Assumption!$C11*Assumption!$B$3*'RM Consumed_PowerSip'!C$14)*Assumption!$B11/1000 -> 2033603.2 | D33: =(Assumption!$C11*Assumption!$B$3*'RM Consumed_PowerSip'!D$14)*Assumption!$B11/1000 -> 2304923.2 | E33: =(Assumption!$C11*Assumption!$B$3*'RM Consumed_PowerSip'!E$14)*Assumption!$B11/1000 -> 2661288 | F33: =(Assumption!$C11*Assumption!$B$3*'RM Consumed_PowerSip'!F$14)*Assumption!$B11/1000 -> 3084060 | G33: =(Assumption!$C11*Assumption!$B$3*'RM Consumed_PowerSip'!G$14)*Assumption!$B11/1000 -> 3554570.2
A34: =Assumption!A12 -> Pea Protein Extract | B34: =(Assumption!$C12*Assumption!$B$3*'RM Consumed_PowerSip'!B$14)*Assumption!$B12/1000 -> 3982608 | C34: =(Assumption!$C12*Assumption!$B$3*'RM Consumed_PowerSip'!C$14)*Assumption!$B12/1000 -> 4648236 | D34: =(Assumption!$C12*Assumption!$B$3*'RM Consumed_PowerSip'!D$14)*Assumption!$B12/1000 -> 5268396 | E34: =(Assumption!$C12*Assumption!$B$3*'RM Consumed_PowerSip'!E$14)*Assumption!$B12/1000 -> 6082944 | F34: =(Assumption!$C12*Assumption!$B$3*'RM Consumed_PowerSip'!F$14)*Assumption!$B12/1000 -> 7049280 | G34: =(Assumption!$C12*Assumption!$B$3*'RM Consumed_PowerSip'!G$14)*Assumption!$B12/1000 -> 8124732
A35: =Assumption!A13 -> Coffee Bean Extract | B35: =(Assumption!$C13*Assumption!$B$3*'RM Consumed_PowerSip'!B$14)*Assumption!$B13/1000 -> 2986956 | C35: =(Assumption!$C13*Assumption!$B$3*'RM Consumed_PowerSip'!C$14)*Assumption!$B13/1000 -> 3486177 | D35: =(Assumption!$C13*Assumption!$B$3*'RM Consumed_PowerSip'!D$14)*Assumption!$B13/1000 -> 3951297 | E35: =(Assumption!$C13*Assumption!$B$3*'RM Consumed_PowerSip'!E$14)*Assumption!$B13/1000 -> 4562208 | F35: =(Assumption!$C13*Assumption!$B$3*'RM Consumed_PowerSip'!F$14)*Assumption!$B13/1000 -> 5286960 | G35: =(Assumption!$C13*Assumption!$B$3*'RM Consumed_PowerSip'!G$14)*Assumption!$B13/1000 -> 6093549
A36: =Assumption!A14 -> Dates Extract | B36: =(Assumption!$C14*Assumption!$B$3*'RM Consumed_PowerSip'!B$14)*Assumption!$B14/1000 -> 448043.4 | C36: =(Assumption!$C14*Assumption!$B$3*'RM Consumed_PowerSip'!C$14)*Assumption!$B14/1000 -> 522926.55 | D36: =(Assumption!$C14*Assumption!$B$3*'RM Consumed_PowerSip'!D$14)*Assumption!$B14/1000 -> 592694.55 | E36: =(Assumption!$C14*Assumption!$B$3*'RM Consumed_PowerSip'!E$14)*Assumption!$B14/1000 -> 684331.2 | F36: =(Assumption!$C14*Assumption!$B$3*'RM Consumed_PowerSip'!F$14)*Assumption!$B14/1000 -> 793044 | G36: =(Assumption!$C14*Assumption!$B$3*'RM Consumed_PowerSip'!G$14)*Assumption!$B14/1000 -> 914032.35
A37: =Assumption!A15 -> Monk Fruit Extract | B37: =(Assumption!$C15*Assumption!$B$3*'RM Consumed_PowerSip'!B$14)*Assumption!$B15/1000 -> 2190434.4 | C37: =(Assumption!$C15*Assumption!$B$3*'RM Consumed_PowerSip'!C$14)*Assumption!$B15/1000 -> 2556529.8 | D37: =(Assumption!$C15*Assumption!$B$3*'RM Consumed_PowerSip'!D$14)*Assumption!$B15/1000 -> 2897617.8 | E37: =(Assumption!$C15*Assumption!$B$3*'RM Consumed_PowerSip'!E$14)*Assumption!$B15/1000 -> 3345619.2 | F37: =(Assumption!$C15*Assumption!$B$3*'RM Consumed_PowerSip'!F$14)*Assumption!$B15/1000 -> 3877104 | G37: =(Assumption!$C15*Assumption!$B$3*'RM Consumed_PowerSip'!G$14)*Assumption!$B15/1000 -> 4468602.6
A38: =Assumption!A16 -> Other Ingredients | B38: =(Assumption!$C16*Assumption!$B$3*'RM Consumed_PowerSip'!B$14)*Assumption!$B16/1000 -> 3584347.2 | C38: =(Assumption!$C16*Assumption!$B$3*'RM Consumed_PowerSip'!C$14)*Assumption!$B16/1000 -> 4183412.4 | D38: =(Assumption!$C16*Assumption!$B$3*'RM Consumed_PowerSip'!D$14)*Assumption!$B16/1000 -> 4741556.4 | E38: =(Assumption!$C16*Assumption!$B$3*'RM Consumed_PowerSip'!E$14)*Assumption!$B16/1000 -> 5474649.6 | F38: =(Assumption!$C16*Assumption!$B$3*'RM Consumed_PowerSip'!F$14)*Assumption!$B16/1000 -> 6344352 | G38: =(Assumption!$C16*Assumption!$B$3*'RM Consumed_PowerSip'!G$14)*Assumption!$B16/1000 -> 7312258.8
A39: Total | B39: =SUM(B32:B38) -> 15213563 | C39: =SUM(C32:C38) -> 17756262 | D39: =SUM(D32:D38) -> 20125273 | E39: =SUM(E32:E38) -> 23236846 | F39: =SUM(F32:F38) -> 26928250 | G39: =SUM(G32:G38) -> 31036476
A40: =Assumption!A17
A41: =Assumption!A18 -> HappyGrow
A42: =Assumption!A20 -> Water | B42: =(Assumption!$C20*Assumption!$B$4*'RM Consumed_HappyGrow'!B$14)*Assumption!$B20/1000 -> 184994.88 | C42: =(Assumption!$C20*Assumption!$B$4*'RM Consumed_HappyGrow'!C$14)*Assumption!$B20/1000 -> 206120.54 | D42: =(Assumption!$C20*Assumption!$B$4*'RM Consumed_HappyGrow'!D$14)*Assumption!$B20/1000 -> 228715.2 | E42: =(Assumption!$C20*Assumption!$B$4*'RM Consumed_HappyGrow'!E$14)*Assumption!$B20/1000 -> 254263.3 | F42: =(Assumption!$C20*Assumption!$B$4*'RM Consumed_HappyGrow'!F$14)*Assumption!$B20/1000 -> 282343.49 | G42: =(Assumption!$C20*Assumption!$B$4*'RM Consumed_HappyGrow'!G$14)*Assumption!$B20/1000 -> 312034.46
A43: =Assumption!A21 -> Oats Extract | B43: =(Assumption!$C21*Assumption!$B$4*'RM Consumed_HappyGrow'!B$14)*Assumption!$B21/1000 -> 880928 | C43: =(Assumption!$C21*Assumption!$B$4*'RM Consumed_HappyGrow'!C$14)*Assumption!$B21/1000 -> 981526.4 | D43: =(Assumption!$C21*Assumption!$B$4*'RM Consumed_HappyGrow'!D$14)*Assumption!$B21/1000 -> 1089120 | E43: =(Assumption!$C21*Assumption!$B$4*'RM Consumed_HappyGrow'!E$14)*Assumption!$B21/1000 -> 1210777.6 | F43: =(Assumption!$C21*Assumption!$B$4*'RM Consumed_HappyGrow'!F$14)*Assumption!$B21/1000 -> 1344492.8 | G43: =(Assumption!$C21*Assumption!$B$4*'RM Consumed_HappyGrow'!G$14)*Assumption!$B21/1000 -> 1485878.4
A44: =Assumption!A22 -> Ragi Extract | B44: =(Assumption!$C22*Assumption!$B$4*'RM Consumed_HappyGrow'!B$14)*Assumption!$B22/1000 -> 330348 | C44: =(Assumption!$C22*Assumption!$B$4*'RM Consumed_HappyGrow'!C$14)*Assumption!$B22/1000 -> 368072.4 | D44: =(Assumption!$C22*Assumption!$B$4*'RM Consumed_HappyGrow'!D$14)*Assumption!$B22/1000 -> 408420 | E44: =(Assumption!$C22*Assumption!$B$4*'RM Consumed_HappyGrow'!E$14)*Assumption!$B22/1000 -> 454041.6 | F44: =(Assumption!$C22*Assumption!$B$4*'RM Consumed_HappyGrow'!F$14)*Assumption!$B22/1000 -> 504184.8 | G44: =(Assumption!$C22*Assumption!$B$4*'RM Consumed_HappyGrow'!G$14)*Assumption!$B22/1000 -> 557204.4
A45: =Assumption!A23 -> Jowar Extract | B45: =(Assumption!$C23*Assumption!$B$4*'RM Consumed_HappyGrow'!B$14)*Assumption!$B23/1000 -> 111767.74 | C45: =(Assumption!$C23*Assumption!$B$4*'RM Consumed_HappyGrow'!C$14)*Assumption!$B23/1000 -> 124531.16 | D45: =(Assumption!$C23*Assumption!$B$4*'RM Consumed_HappyGrow'!D$14)*Assumption!$B23/1000 -> 138182.1 | E45: =(Assumption!$C23*Assumption!$B$4*'RM Consumed_HappyGrow'!E$14)*Assumption!$B23/1000 -> 153617.41 | F45: =(Assumption!$C23*Assumption!$B$4*'RM Consumed_HappyGrow'!F$14)*Assumption!$B23/1000 -> 170582.52 | G45: =(Assumption!$C23*Assumption!$B$4*'RM Consumed_HappyGrow'!G$14)*Assumption!$B23/1000 -> 188520.82
A46: =Assumption!A24 -> Bajra Extract | B46: =(Assumption!$C24*Assumption!$B$4*'RM Consumed_HappyGrow'!B$14)*Assumption!$B24/1000 -> 96351.5 | C46: =(Assumption!$C24*Assumption!$B$4*'RM Consumed_HappyGrow'!C$14)*Assumption!$B24/1000 -> 107354.45 | D46: =(Assumption!$C24*Assumption!$B$4*'RM Consumed_HappyGrow'!D$14)*Assumption!$B24/1000 -> 119122.5 | E46: =(Assumption!$C24*Assumption!$B$4*'RM Consumed_HappyGrow'!E$14)*Assumption!$B24/1000 -> 132428.8 | F46: =(Assumption!$C24*Assumption!$B$4*'RM Consumed_HappyGrow'!F$14)*Assumption!$B24/1000 -> 147053.9 | G46: =(Assumption!$C24*Assumption!$B$4*'RM Consumed_HappyGrow'!G$14)*Assumption!$B24/1000 -> 162517.95
A47: =Assumption!A25 -> Dates Extract | B47: =(Assumption!$C25*Assumption!$B$4*'RM Consumed_HappyGrow'!B$14)*Assumption!$B25/1000 -> 297313.2 | C47: =(Assumption!$C25*Assumption!$B$4*'RM Consumed_HappyGrow'!C$14)*Assumption!$B25/1000 -> 331265.16 | D47: =(Assumption!$C25*Assumption!$B$4*'RM Consumed_HappyGrow'!D$14)*Assumption!$B25/1000 -> 367578 | E47: =(Assumption!$C25*Assumption!$B$4*'RM Consumed_HappyGrow'!E$14)*Assumption!$B25/1000 -> 408637.44 | F47: =(Assumption!$C25*Assumption!$B$4*'RM Consumed_HappyGrow'!F$14)*Assumption!$B25/1000 -> 453766.32 | G47: =(Assumption!$C25*Assumption!$B$4*'RM Consumed_HappyGrow'!G$14)*Assumption!$B25/1000 -> 501483.96
A48: =Assumption!A26 -> Other Ingredients | B48: =(Assumption!$C26*Assumption!$B$4*'RM Consumed_HappyGrow'!B$14)*Assumption!$B26/1000 -> 1982088 | C48: =(Assumption!$C26*Assumption!$B$4*'RM Consumed_HappyGrow'!C$14)*Assumption!$B26/1000 -> 2208434.4 | D48: =(Assumption!$C26*Assumption!$B$4*'RM Consumed_HappyGrow'!D$14)*Assumption!$B26/1000 -> 2450520 | E48: =(Assumption!$C26*Assumption!$B$4*'RM Consumed_HappyGrow'!E$14)*Assumption!$B26/1000 -> 2724249.6 | F48: =(Assumption!$C26*Assumption!$B$4*'RM Consumed_HappyGrow'!F$14)*Assumption!$B26/1000 -> 3025108.8 | G48: =(Assumption!$C26*Assumption!$B$4*'RM Consumed_HappyGrow'!G$14)*Assumption!$B26/1000 -> 3343226.4
A49: Total | B49: =SUM(B42:B48) -> 3883791.3 | C49: =SUM(C42:C48) -> 4327304.5 | D49: =SUM(D42:D48) -> 4801657.8 | E49: =SUM(E42:E48) -> 5338015.7 | F49: =SUM(F42:F48) -> 5927532.6 | G49: =SUM(G42:G48) -> 6550866.4
A50: =Assumption!A28
A51: Cost Per Unit (Rs.)
A52: =A31 -> PowerSip | B52: =(B39/'RM Consumed_PowerSip'!B14) -> 45.84 | C52: =(C39/'RM Consumed_PowerSip'!C14) -> 45.84 | D52: =(D39/'RM Consumed_PowerSip'!D14) -> 45.84 | E52: =(E39/'RM Consumed_PowerSip'!E14) -> 45.84 | F52: =(F39/'RM Consumed_PowerSip'!F14) -> 45.84 | G52: =(G39/'RM Consumed_PowerSip'!G14) -> 45.84
A53: =A41 -> HappyGrow | B53: =(B49/'RM Consumed_HappyGrow'!B14) -> 14.108 | C53: =(C49/'RM Consumed_HappyGrow'!C14) -> 14.108 | D53: =(D49/'RM Consumed_HappyGrow'!D14) -> 14.108 | E53: =(E49/'RM Consumed_HappyGrow'!E14) -> 14.108 | F53: =(F49/'RM Consumed_HappyGrow'!F14) -> 14.108 | G53: =(G49/'RM Consumed_HappyGrow'!G14) -> 14.108
A65: =Assumption!A43
A66: =Assumption!A44
A67: =Assumption!A45
A68: =Assumption!A46
A69: =Assumption!A47

Sheet RM Consumed_PowerSip
B1: January | C1: February | D1: March | E1: April | F1: May | G1: June
A2: PowerSip
A3: Per Unit Material Consumption (in ml)
A4: =Assumption!A10 -> Water | B4: =Assumption!$B$3*Assumption!$C10 -> 105 | C4: =Assumption!$B$3*Assumption!$C10 -> 105 | D4: =Assumption!$B$3*Assumption!$C10 -> 105 | E4: =Assumption!$B$3*Assumption!$C10 -> 105 | F4: =Assumption!$B$3*Assumption!$C10 -> 105 | G4: =Assumption!$B$3*Assumption!$C10 -> 105
A5: =Assumption!A11 -> Milk | B5: =Assumption!$B$3*Assumption!$C11 -> 105 | C5: =Assumption!$B$3*Assumption!$C11 -> 105 | D5: =Assumption!$B$3*Assumption!$C11 -> 105 | E5: =Assumption!$B$3*Assumption!$C11 -> 105 | F5: =Assumption!$B$3*Assumption!$C11 -> 105 | G5: =Assumption!$B$3*Assumption!$C11 -> 105
A6: =Assumption!A12 -> Pea Protein Extract | B6: =Assumption!$B$3*Assumption!$C12 -> 30 | C6: =Assumption!$B$3*Assumption!$C12 -> 30 | D6: =Assumption!$B$3*Assumption!$C12 -> 30 | E6: =Assumption!$B$3*Assumption!$C12 -> 30 | F6: =Assumption!$B$3*Assumption!$C12 -> 30 | G6: =Assumption!$B$3*Assumption!$C12 -> 30
A7: =Assumption!A13 -> Coffee Bean Extract | B7: =Assumption!$B$3*Assumption!$C13 -> 30 | C7: =Assumption!$B$3*Assumption!$C13 -> 30 | D7: =Assumption!$B$3*Assumption!$C13 -> 30 | E7: =Assumption!$B$3*Assumption!$C13 -> 30 | F7: =Assumption!$B$3*Assumption!$C13 -> 30 | G7: =Assumption!$B$3*Assumption!$C13 -> 30
A8: =Assumption!A14 -> Dates Extract | B8: =Assumption!$B$3*Assumption!$C14 -> 15 | C8: =Assumption!$B$3*Assumption!$C14 -> 15 | D8: =Assumption!$B$3*Assumption!$C14 -> 15 | E8: =Assumption!$B$3*Assumption!$C14 -> 15 | F8: =Assumption!$B$3*Assumption!$C14 -> 15 | G8: =Assumption!$B$3*Assumption!$C14 -> 15
A9: =Assumption!A15 -> Monk Fruit Extract | B9: =Assumption!$B$3*Assumption!$C15 -> 6 | C9: =Assumption!$B$3*Assumption!$C15 -> 6 | D9: =Assumption!$B$3*Assumption!$C15 -> 6 | E9: =Assumption!$B$3*Assumption!$C15 -> 6 | F9: =Assumption!$B$3*Assumption!$C15 -> 6 | G9: =Assumption!$B$3*Assumption!$C15 -> 6
A10: =Assumption!A16 -> Other Ingredients | B10: =Assumption!$B$3*Assumption!$C16 -> 9 | C10: =Assumption!$B$3*Assumption!$C16 -> 9 | D10: =Assumption!$B$3*Assumption!$C16 -> 9 | E10: =Assumption!$B$3*Assumption!$C16 -> 9 | F10: =Assumption!$B$3*Assumption!$C16 -> 9 | G10: =Assumption!$B$3*Assumption!$C16 -> 9
A12: Sales Units
A13: Old Plan | B13: =SUMIFS('Sales Quantity'!I:I, 'Sales Quantity'!A:A, "Month1", 'Sales Quantity'!D:D, "PowerSip") / 135 -> 304436 | C13: =SUMIFS('Sales Quantity'!I:I, 'Sales Quantity'!A:A, "Month2", 'Sales Quantity'!D:D, "PowerSip") / 135 -> 334881 | D13: =SUMIFS('Sales Quantity'!I:I, 'Sales Quantity'!A:A, "Month3", 'Sales Quantity'!D:D, "PowerSip") / 135 -> 368372 | E13: =SUMIFS('Sales Quantity'!I:I, 'Sales Quantity'!A:A, "Month4", 'Sales Quantity'!D:D, "PowerSip") / 135 -> 405210 | F13: =SUMIFS('Sales Quantity'!I:I, 'Sales Quantity'!A:A, "Month5", 'Sales Quantity'!D:D, "PowerSip") / 135 -> 445733 | G13: =SUMIFS('Sales Quantity'!I:I, 'Sales Quantity'!A:A, "Month6", 'Sales Quantity'!D:D, "PowerSip") / 135 -> 490306
A14: New Plan | B14: =SUMIFS('Sales Quantity'!J:J, 'Sales Quantity'!$A:$A, "Month1", 'Sales Quantity'!$D:$D, "PowerSip") / 140 -> 331884 | C14: =SUMIFS('Sales Quantity'!J:J, 'Sales Quantity'!A:A, "Month2", 'Sales Quantity'!D:D, "PowerSip") / 140 -> 387353 | D14: =SUMIFS('Sales Quantity'!J:J, 'Sales Quantity'!A:A, "Month3", 'Sales Quantity'!D:D, "PowerSip") / 140 -> 439033 | E14: =SUMIFS('Sales Quantity'!J:J, 'Sales Quantity'!A:A, "Month4", 'Sales Quantity'!D:D, "PowerSip") / 140 -> 506912 | F14: =SUMIFS('Sales Quantity'!J:J, 'Sales Quantity'!A:A, "Month5", 'Sales Quantity'!D:D, "PowerSip") / 140 -> 587440 | G14: =SUMIFS('Sales Quantity'!J:J, 'Sales Quantity'!A:A, "Month6", 'Sales Quantity'!D:D, "PowerSip") / 140 -> 677061
A16: Raw Material
A17: Old plan
A19: =Assumption!A10 -> Water | B19: =B$13 * 300 *Assumption!$C10 / 1000 -> 31965.78 | C19: =C$13 * 300 *Assumption!$C10 / 1000 -> 35162.505 | D19: =D$13 * 300 *Assumption!$C10 / 1000 -> 38679.06 | E19: =E$13 * 300 *Assumption!$C10 / 1000 -> 42547.05 | F19: =F$13 * 300 *Assumption!$C10 / 1000 -> 46801.965 | G19: =G$13 * 300 *Assumption!$C10 / 1000 -> 51482.13
A20: =Assumption!A11 -> Milk | B20: =B$13 * 300 *Assumption!$C11 / 1000 -> 31965.78 | C20: =C$13 * 300 *Assumption!$C11 / 1000 -> 35162.505 | D20: =D$13 * 300 *Assumption!$C11 / 1000 -> 38679.06 | E20: =E$13 * 300 *Assumption!$C11 / 1000 -> 42547.05 | F20: =F$13 * 300 *Assumption!$C11 / 1000 -> 46801.965 | G20: =G$13 * 300 *Assumption!$C11 / 1000 -> 51482.13
A21: =Assumption!A12 -> Pea Protein Extract | B21: =B$13 * 300 *Assumption!$C12 / 1000 -> 9133.08 | C21: =C$13 * 300 *Assumption!$C12 / 1000 -> 10046.43 | D21: =D$13 * 300 *Assumption!$C12 / 1000 -> 11051.16 | E21: =E$13 * 300 *Assumption!$C12 / 1000 -> 12156.3 | F21: =F$13 * 300 *Assumption!$C12 / 1000 -> 13371.99 | G21: =G$13 * 300 *Assumption!$C12 / 1000 -> 14709.18
A22: =Assumption!A13 -> Coffee Bean Extract | B22: =B$13 * 300 *Assumption!$C13 / 1000 -> 9133.08 | C22: =C$13 * 300 *Assumption!$C13 / 1000 -> 10046.43 | D22: =D$13 * 300 *Assumption!$C13 / 1000 -> 11051.16 | E22: =E$13 * 300 *Assumption!$C13 / 1000 -> 12156.3 | F22: =F$13 * 300 *Assumption!$C13 / 1000 -> 13371.99 | G22: =G$13 * 300 *Assumption!$C13 / 1000 -> 14709.18
A23: =Assumption!A14 -> Dates Extract | B23: =B$13 * 300 *Assumption!$C14 / 1000 -> 4566.54 | C23: =C$13 * 300 *Assumption!$C14 / 1000 -> 5023.215 | D23: =D$13 * 300 *Assumption!$C14 / 1000 -> 5525.58 | E23: =E$13 * 300 *Assumption!$C14 / 1000 -> 6078.15 | F23: =F$13 * 300 *Assumption!$C14 / 1000 -> 6685.995 | G23: =G$13 * 300 *Assumption!$C14 / 1000 -> 7354.59
A24: =Assumption!A15 -> Monk Fruit Extract | B24: =B$13 * 300 *Assumption!$C15 / 1000 -> 1826.616 | C24: =C$13 * 300 *Assumption!$C15 / 1000 -> 2009.286 | D24: =D$13 * 300 *Assumption!$C15 / 1000 -> 2210.232 | E24: =E$13 * 300 *Assumption!$C15 / 1000 -> 2431.26 | F24: =F$13 * 300 *Assumption!$C15 / 1000 -> 2674.398 | G24: =G$13 * 300 *Assumption!$C15 / 1000 -> 2941.836
A25: =Assumption!A16 -> Other Ingredients | B25: =B$13 * 300 *Assumption!$C16 / 1000 -> 2739.924 | C25: =C$13 * 300 *Assumption!$C16 / 1000 -> 3013.929 | D25: =D$13 * 300 *Assumption!$C16 / 1000 -> 3315.348 | E25: =E$13 * 300 *Assumption!$C16 / 1000 -> 3646.89 | F25: =F$13 * 300 *Assumption!$C16 / 1000 -> 4011.597 | G25: =G$13 * 300 *Assumption!$C16 / 1000 -> 4412.754
A26: =Assumption!A17
A27: New Plan
A29: =Assumption!A10 -> Water | B29: =B$14 * 300 *Assumption!$C10 / 1000 -> 34847.82 | C29: =C$14 * 300 *Assumption!$C10 / 1000 -> 40672.065 | D29: =D$14 * 300 *Assumption!$C10 / 1000 -> 46098.465 | E29: =E$14 * 300 *Assumption!$C10 / 1000 -> 53225.76 | F29: =F$14 * 300 *Assumption!$C10 / 1000 -> 61681.2 | G29: =G$14 * 300 *Assumption!$C10 / 1000 -> 71091.405
A30: =Assumption!A11 -> Milk | B30: =B$14 * 300 *Assumption!$C11 / 1000 -> 34847.82 | C30: =C$14 * 300 *Assumption!$C11 / 1000 -> 40672.065 | D30: =D$14 * 300 *Assumption!$C11 / 1000 -> 46098.465 | E30: =E$14 * 300 *Assumption!$C11 / 1000 -> 53225.76 | F30: =F$14 * 300 *Assumption!$C11 / 1000 -> 61681.2 | G30: =G$14 * 300 *Assumption!$C11 / 1000 -> 71091.405
A31: =Assumption!A12 -> Pea Protein Extract | B31: =B$14 * 300 *Assumption!$C12 / 1000 -> 9956.52 | C31: =C$14 * 300 *Assumption!$C12 / 1000 -> 11620.59 | D31: =D$14 * 300 *Assumption!$C12 / 1000 -> 13170.99 | E31: =E$14 * 300 *Assumption!$C12 / 1000 -> 15207.36 | F31: =F$14 * 300 *Assumption!$C12 / 1000 -> 17623.2 | G31: =G$14 * 300 *Assumption!$C12 / 1000 -> 20311.83
A32: =Assumption!A13 -> Coffee Bean Extract | B32: =B$14 * 300 *Assumption!$C13 / 1000 -> 9956.52 | C32: =C$14 * 300 *Assumption!$C13 / 1000 -> 11620.59 | D32: =D$14 * 300 *Assumption!$C13 / 1000 -> 13170.99 | E32: =E$14 * 300 *Assumption!$C13 / 1000 -> 15207.36 | F32: =F$14 * 300 *Assumption!$C13 / 1000 -> 17623.2 | G32: =G$14 * 300 *Assumption!$C13 / 1000 -> 20311.83
A33: =Assumption!A14 -> Dates Extract | B33: =B$14 * 300 *Assumption!$C14 / 1000 -> 4978.26 | C33: =C$14 * 300 *Assumption!$C14 / 1000 -> 5810.295 | D33: =D$14 * 300 *Assumption!$C14 / 1000 -> 6585.495 | E33: =E$14 * 300 *Assumption!$C14 / 1000 -> 7603.68 | F33: =F$14 * 300 *Assumption!$C14 / 1000 -> 8811.6 | G33: =G$14 * 300 *Assumption!$C14 / 1000 -> 10155.915
A34: =Assumption!A15 -> Monk Fruit Extract | B34: =B$14 * 300 *Assumption!$C15 / 1000 -> 1991.304 | C34: =C$14 * 300 *Assumption!$C15 / 1000 -> 2324.118 | D34: =D$14 * 300 *Assumption!$C15 / 1000 -> 2634.198 | E34: =E$14 * 300 *Assumption!$C15 / 1000 -> 3041.472 | F34: =F$14 * 300 *Assumption!$C15 / 1000 -> 3524.64 | G34: =G$14 * 300 *Assumption!$C15 / 1000 -> 4062.366
A35: =Assumption!A16 -> Other Ingredients | B35: =B$14 * 300 *Assumption!$C16 / 1000 -> 2986.956 | C35: =C$14 * 300 *Assumption!$C16 / 1000 -> 3486.177 | D35: =D$14 * 300 *Assumption!$C16 / 1000 -> 3951.297 | E35: =E$14 * 300 *Assumption!$C16 / 1000 -> 4562.208 | F35: =F$14 * 300 *Assumption!$C16 / 1000 -> 5286.96 | G35: =G$14 * 300 *Assumption!$C16 / 1000 -> 6093.549

Sheet RM Consumed_HappyGrow
B1: January | C1: February | D1: March | E1: April | F1: May | G1: June
A2: HappyGrow
A3: Per Unit Material Consumption (in ml)
A4: =Assumption!A20 -> Water | B4: =Assumption!$B$4*Assumption!$C20 -> 84 | C4: =Assumption!$B$4*Assumption!$C20 -> 84 | D4: =Assumption!$B$4*Assumption!$C20 -> 84 | E4: =Assumption!$B$4*Assumption!$C20 -> 84 | F4: =Assumption!$B$4*Assumption!$C20 -> 84 | G4: =Assumption!$B$4*Assumption!$C20 -> 84
A5: =Assumption!A21 -> Oats Extract | B5: =Assumption!$B$4*Assumption!$C21 -> 40 | C5: =Assumption!$B$4*Assumption!$C21 -> 40 | D5: =Assumption!$B$4*Assumption!$C21 -> 40 | E5: =Assumption!$B$4*Assumption!$C21 -> 40 | F5: =Assumption!$B$4*Assumption!$C21 -> 40 | G5: =Assumption!$B$4*Assumption!$C21 -> 40
A6: =Assumption!A22 -> Ragi Extract | B6: =Assumption!$B$4*Assumption!$C22 -> 30 | C6: =Assumption!$B$4*Assumption!$C22 -> 30 | D6: =Assumption!$B$4*Assumption!$C22 -> 30 | E6: =Assumption!$B$4*Assumption!$C22 -> 30 | F6: =Assumption!$B$4*Assumption!$C22 -> 30 | G6: =Assumption!$B$4*Assumption!$C22 -> 30
A7: =Assumption!A23 -> Jowar Extract | B7: =Assumption!$B$4*Assumption!$C23 -> 14 | C7: =Assumption!$B$4*Assumption!$C23 -> 14 | D7: =Assumption!$B$4*Assumption!$C23 -> 14 | E7: =Assumption!$B$4*Assumption!$C23 -> 14 | F7: =Assumption!$B$4*Assumption!$C23 -> 14 | G7: =Assumption!$B$4*Assumption!$C23 -> 14
A8: =Assumption!A24 -> Bajra Extract | B8: =Assumption!$B$4*Assumption!$C24 -> 14 | C8: =Assumption!$B$4*Assumption!$C24 -> 14 | D8: =Assumption!$B$4*Assumption!$C24 -> 14 | E8: =Assumption!$B$4*Assumption!$C24 -> 14 | F8: =Assumption!$B$4*Assumption!$C24 -> 14 | G8: =Assumption!$B$4*Assumption!$C24 -> 14
A9: =Assumption!A25 -> Dates Extract | B9: =Assumption!$B$4*Assumption!$C25 -> 12 | C9: =Assumption!$B$4*Assumption!$C25 -> 12 | D9: =Assumption!$B$4*Assumption!$C25 -> 12 | E9: =Assumption!$B$4*Assumption!$C25 -> 12 | F9: =Assumption!$B$4*Assumption!$C25 -> 12 | G9: =Assumption!$B$4*Assumption!$C25 -> 12
A10: =Assumption!A26 -> Other Ingredients | B10: =Assumption!$B$4*Assumption!$C26 -> 6 | C10: =Assumption!$B$4*Assumption!$C26 -> 6 | D10: =Assumption!$B$4*Assumption!$C26 -> 6 | E10: =Assumption!$B$4*Assumption!$C26 -> 6 | F10: =Assumption!$B$4*Assumption!$C26 -> 6 | G10: =Assumption!$B$4*Assumption!$C26 -> 6
A12: Sales Units
A13: Old Plan | B13: =SUMIFS('Sales Quantity'!$I:$I, 'Sales Quantity'!$A:$A, "Month1", 'Sales Quantity'!$D:$D, "HappyGrow")/60 -> 269434 | C13: =SUMIFS('Sales Quantity'!$I:$I, 'Sales Quantity'!$A:$A, "Month2", 'Sales Quantity'!$D:$D, "HappyGrow")/60 -> 288294 | D13: =SUMIFS('Sales Quantity'!$I:$I, 'Sales Quantity'!$A:$A, "Month3", 'Sales Quantity'!$D:$D, "HappyGrow")/60 -> 308475 | E13: =SUMIFS('Sales Quantity'!$I:$I, 'Sales Quantity'!$A:$A, "Month4", 'Sales Quantity'!$D:$D, "HappyGrow")/60 -> 330069 | F13: =SUMIFS('Sales Quantity'!$I:$I, 'Sales Quantity'!$A:$A, "Month5", 'Sales Quantity'!$D:$D, "HappyGrow")/60 -> 353173 | G13: =SUMIFS('Sales Quantity'!$I:$I, 'Sales Quantity'!$A:$A, "Month6", 'Sales Quantity'!$D:$D, "HappyGrow")/60 -> 377898
A14: New Plan | B14: =SUMIFS('Sales Quantity'!$J:$J, 'Sales Quantity'!$A:$A, "Month1", 'Sales Quantity'!$D:$D, "HappyGrow")/70 -> 275290 | C14: =SUMIFS('Sales Quantity'!$J:$J, 'Sales Quantity'!$A:$A, "Month2", 'Sales Quantity'!$D:$D, "HappyGrow")/70 -> 306727 | D14: =SUMIFS('Sales Quantity'!$J:$J, 'Sales Quantity'!$A:$A, "Month3", 'Sales Quantity'!$D:$D, "HappyGrow")/70 -> 340350 | E14: =SUMIFS('Sales Quantity'!$J:$J, 'Sales Quantity'!$A:$A, "Month4", 'Sales Quantity'!$D:$D, "HappyGrow")/70 -> 378368 | F14: =SUMIFS('Sales Quantity'!$J:$J, 'Sales Quantity'!$A:$A, "Month5", 'Sales Quantity'!$D:$D, "HappyGrow")/70 -> 420154 | G14: =SUMIFS('Sales Quantity'!$J:$J, 'Sales Quantity'!$A:$A, "Month6", 'Sales Quantity'!$D:$D, "HappyGrow")/70 -> 464337
A16: Raw Material
A17: Old plan
A19: =Assumption!A20 -> Water | B19: =B$13 * 200 *Assumption!$C20 / 1000 -> 22632.456 | C19: =C$13 * 200 *Assumption!$C20 / 1000 -> 24216.696 | D19: =D$13 * 200 *Assumption!$C20 / 1000 -> 25911.9 | E19: =E$13 * 200 *Assumption!$C20 / 1000 -> 27725.796 | F19: =F$13 * 200 *Assumption!$C20 / 1000 -> 29666.532 | G19: =G$13 * 200 *Assumption!$C20 / 1000 -> 31743.432
A20: =Assumption!A21 -> Oats Extract | B20: =B$13 * 200 *Assumption!$C21 / 1000 -> 10777.36 | C20: =C$13 * 200 *Assumption!$C21 / 1000 -> 11531.76 | D20: =D$13 * 200 *Assumption!$C21 / 1000 -> 12339 | E20: =E$13 * 200 *Assumption!$C21 / 1000 -> 13202.76 | F20: =F$13 * 200 *Assumption!$C21 / 1000 -> 14126.92 | G20: =G$13 * 200 *Assumption!$C21 / 1000 -> 15115.92
A21: =Assumption!A22 -> Ragi Extract | B21: =B$13 * 200 *Assumption!$C22 / 1000 -> 8083.02 | C21: =C$13 * 200 *Assumption!$C22 / 1000 -> 8648.82 | D21: =D$13 * 200 *Assumption!$C22 / 1000 -> 9254.25 | E21: =E$13 * 200 *Assumption!$C22 / 1000 -> 9902.07 | F21: =F$13 * 200 *Assumption!$C22 / 1000 -> 10595.19 | G21: =G$13 * 200 *Assumption!$C22 / 1000 -> 11336.94
A22: =Assumption!A23 -> Jowar Extract | B22: =B$13 * 200 *Assumption!$C23 / 1000 -> 3772.076 | C22: =C$13 * 200 *Assumption!$C23 / 1000 -> 4036.116 | D22: =D$13 * 200 *Assumption!$C23 / 1000 -> 4318.65 | E22: =E$13 * 200 *Assumption!$C23 / 1000 -> 4620.966 | F22: =F$13 * 200 *Assumption!$C23 / 1000 -> 4944.422 | G22: =G$13 * 200 *Assumption!$C23 / 1000 -> 5290.572
A23: =Assumption!A24 -> Bajra Extract | B23: =B$13 * 200 *Assumption!$C24 / 1000 -> 3772.076 | C23: =C$13 * 200 *Assumption!$C24 / 1000 -> 4036.116 | D23: =D$13 * 200 *Assumption!$C24 / 1000 -> 4318.65 | E23: =E$13 * 200 *Assumption!$C24 / 1000 -> 4620.966 | F23: =F$13 * 200 *Assumption!$C24 / 1000 -> 4944.422 | G23: =G$13 * 200 *Assumption!$C24 / 1000 -> 5290.572
A24: =Assumption!A25 -> Dates Extract | B24: =B$13 * 200 *Assumption!$C25 / 1000 -> 3233.208 | C24: =C$13 * 200 *Assumption!$C25 / 1000 -> 3459.528 | D24: =D$13 * 200 *Assumption!$C25 / 1000 -> 3701.7 | E24: =E$13 * 200 *Assumption!$C25 / 1000 -> 3960.828 | F24: =F$13 * 200 *Assumption!$C25 / 1000 -> 4238.076 | G24: =G$13 * 200 *Assumption!$C25 / 1000 -> 4534.776
A25: =Assumption!A26 -> Other Ingredients | B25: =B$13 * 200 *Assumption!$C26 / 1000 -> 1616.604 | C25: =C$13 * 200 *Assumption!$C26 / 1000 -> 1729.764 | D25: =D$13 * 200 *Assumption!$C26 / 1000 -> 1850.85 | E25: =E$13 * 200 *Assumption!$C26 / 1000 -> 1980.414 | F25: =F$13 * 200 *Assumption!$C26 / 1000 -> 2119.038 | G25: =G$13 * 200 *Assumption!$C26 / 1000 -> 2267.388
A27: New Plan
A29: =Assumption!A20 -> Water | B29: =B$14 * 200 *Assumption!$C20 / 1000 -> 23124.36 | C29: =C$14 * 200 *Assumption!$C20 / 1000 -> 25765.068 | D29: =D$14 * 200 *Assumption!$C20 / 1000 -> 28589.4 | E29: =E$14 * 200 *Assumption!$C20 / 1000 -> 31782.912 | F29: =F$14 * 200 *Assumption!$C20 / 1000 -> 35292.936 | G29: =G$14 * 200 *Assumption!$C20 / 1000 -> 39004.308
A30: =Assumption!A21 -> Oats Extract | B30: =B$14 * 200 *Assumption!$C21 / 1000 -> 11011.6 | C30: =C$14 * 200 *Assumption!$C21 / 1000 -> 12269.08 | D30: =D$14 * 200 *Assumption!$C21 / 1000 -> 13614 | E30: =E$14 * 200 *Assumption!$C21 / 1000 -> 15134.72 | F30: =F$14 * 200 *Assumption!$C21 / 1000 -> 16806.16 | G30: =G$14 * 200 *Assumption!$C21 / 1000 -> 18573.48
A31: =Assumption!A22 -> Ragi Extract | B31: =B$14 * 200 *Assumption!$C22 / 1000 -> 8258.7 | C31: =C$14 * 200 *Assumption!$C22 / 1000 -> 9201.81 | D31: =D$14 * 200 *Assumption!$C22 / 1000 -> 10210.5 | E31: =E$14 * 200 *Assumption!$C22 / 1000 -> 11351.04 | F31: =F$14 * 200 *Assumption!$C22 / 1000 -> 12604.62 | G31: =G$14 * 200 *Assumption!$C22 / 1000 -> 13930.11
A32: =Assumption!A23 -> Jowar Extract | B32: =B$14 * 200 *Assumption!$C23 / 1000 -> 3854.06 | C32: =C$14 * 200 *Assumption!$C23 / 1000 -> 4294.178 | D32: =D$14 * 200 *Assumption!$C23 / 1000 -> 4764.9 | E32: =E$14 * 200 *Assumption!$C23 / 1000 -> 5297.152 | F32: =F$14 * 200 *Assumption!$C23 / 1000 -> 5882.156 | G32: =G$14 * 200 *Assumption!$C23 / 1000 -> 6500.718
A33: =Assumption!A24 -> Bajra Extract | B33: =B$14 * 200 *Assumption!$C24 / 1000 -> 3854.06 | C33: =C$14 * 200 *Assumption!$C24 / 1000 -> 4294.178 | D33: =D$14 * 200 *Assumption!$C24 / 1000 -> 4764.9 | E33: =E$14 * 200 *Assumption!$C24 / 1000 -> 5297.152 | F33: =F$14 * 200 *Assumption!$C24 / 1000 -> 5882.156 | G33: =G$14 * 200 *Assumption!$C24 / 1000 -> 6500.718
A34: =Assumption!A25 -> Dates Extract | B34: =B$14 * 200 *Assumption!$C25 / 1000 -> 3303.48 | C34: =C$14 * 200 *Assumption!$C25 / 1000 -> 3680.724 | D34: =D$14 * 200 *Assumption!$C25 / 1000 -> 4084.2 | E34: =E$14 * 200 *Assumption!$C25 / 1000 -> 4540.416 | F34: =F$14 * 200 *Assumption!$C25 / 1000 -> 5041.848 | G34: =G$14 * 200 *Assumption!$C25 / 1000 -> 5572.044
A35: =Assumption!A26 -> Other Ingredients | B35: =B$14 * 200 *Assumption!$C26 / 1000 -> 1651.74 | C35: =C$14 * 200 *Assumption!$C26 / 1000 -> 1840.362 | D35: =D$14 * 200 *Assumption!$C26 / 1000 -> 2042.1 | E35: =E$14 * 200 *Assumption!$C26 / 1000 -> 2270.208 | F35: =F$14 * 200 *Assumption!$C26 / 1000 -> 2520.924 | G35: =G$14 * 200 *Assumption!$C26 / 1000 -> 2786.022

Sheet Case
A1: Get Started
A2: PureVibe Co. is a renowned health drink company offering specialized beverages for adults and children. The adult-focused health drink is marketed under the brand name PowerSip, while the children's product is sold under the brand name HappyGrow.
A3: For the upcoming IPL season, which begins in March, PureVibe plans to capitalize on the tournament's widespread popularity by co-branding with the IPL to drive sales. Although the IPL season kicks off in March, the MARKETING team has launched its promotional campaigns starting January to build early momentum.
A4: As part of this initiative, PureVibe will introduce IPL-themed packaging for both PowerSip and HappyGrow. This special packaging will replace their regular designs for a duration of five months. The project entails additional costs for creating and producing the new packaging, alongside higher production and distribution expenses to meet anticipated demand.
A5: The finance team has requested a detailed cost-benefit analysis to evaluate the return on investment for this campaign. As a data analyst in the MARKETING department, you are tasked with preparing a comprehensive analysis and presenting the findings through a dashboard to the MARKETING head. The analysis will highlight projected sales increases, advertising costs, and the overall impact on profitability during the campaign.
A6: This co-branding effort aims to strengthen brand visibility, attract new customers, and maximize sales during one of the most-watched events of the year.
A8: Details
A9: PureVibe Co. produces PowerSip in 300 ml pack and HappyGrow in 200 ml pack. Below are the key details for these products:
A11: Pricing
A12: The selling price per regular pack of PowerSip is Rs. 135, and for HappyGrow, it is Rs. 60. For the new IPL-themed pack, the prices are Rs. 140 and Rs. 70, respectively.
A14: Sales Quantity and Growth
A15: Details regarding sales are provided in the tab named "Data."
... A46: The explanation of the data format is provided in the "Data Format" tab.

Sheet Data
A1: Data | B1: MONTH | C1: Region | D1: City | E1: PRD | F1: OPQ (Old plan Quantity) | G1: NPQ(New plan Quantity)
A2: //Month1 //#N#City_Chennai//PRD-PowerSip//OPQ 21497/NPQ[IPLMARKETING]22572 | B2: =IFERROR(__xludf.DUMMYFUNCTION("REGEXEXTRACT(A2, ""Month\d+"")"),"Month1") -> Month1 | C2: =IFERROR(__xludf.DUMMYFUNCTION("REGEXEXTRACT(A2, ""#([A-Z])#"") "),"N") -> N | D2: =IFERROR(__xludf.DUMMYFUNCTION("REGEXEXTRACT(A2, ""City_([^/]+)"")"),"Chennai") -> Chennai | E2: =IFERROR(__xludf.DUMMYFUNCTION("REGEXEXTRACT(A2, ""PRD-([^/]+)"")"),"PowerSip") -> PowerSip | F2: =IFERROR(__xludf.DUMMYFUNCTION("REGEXEXTRACT(A2, ""OPQ\s+(\d+)"")"),"21497") -> 21497 | G2: =IFERROR(__xludf.DUMMYFUNCTION("REGEXEXTRACT(A2, ""NPQ\[.*?\](\d+)"")"),"22572") -> 22572
A3: //Month1 //#N#City_Chennai//PRD-HappyGrow//OPQ 16650/NPQ[IPLMARKETING]16817 | B3: =IFERROR(__xludf.DUMMYFUNCTION("REGEXEXTRACT(A3, ""Month\d+"")"),"Month1") -> Month1 | C3: =IFERROR(__xludf.DUMMYFUNCTION("REGEXEXTRACT(A3, ""#([A-Z])#"") "),"N") -> N | D3: =IFERROR(__xludf.DUMMYFUNCTION("REGEXEXTRACT(A3, ""City_([^/]+)"")"),"Chennai") -> Chennai | E3: =IFERROR(__xludf.DUMMYFUNCTION("REGEXEXTRACT(A3, ""PRD-([^/]+)"")"),"HappyGrow") -> HappyGrow | F3: =IFERROR(__xludf.DUMMYFUNCTION("REGEXEXTRACT(A3, ""OPQ\s+(\d+)"")"),"16650") -> 16650 | G3: =IFERROR(__xludf.DUMMYFUNCTION("REGEXEXTRACT(A3, ""NPQ\[.*?\](\d+)"")"),"16817") -> 16817
A4: //Month1 //#E#City_Chennai//PRD-PowerSip//OPQ 11470/NPQ[IPLMARKETING]12044 | B4: =IFERROR(__xludf.DUMMYFUNCTION("REGEXEXTRACT(A4, ""Month\d+"")"),"Month1") -> Month1 | C4: =IFERROR(__xludf.DUMMYFUNCTION("REGEXEXTRACT(A4, ""#([A-Z])#"") "),"E") -> E | D4: =IFERROR(__xludf.DUMMYFUNCTION("REGEXEXTRACT(A4, ""City_([^/]+)"")"),"Chennai") -> Chennai | E4: =IFERROR(__xludf.DUMMYFUNCTION("REGEXEXTRACT(A4, ""PRD-([^/]+)"")"),"PowerSip") -> PowerSip | F4: =IFERROR(__xludf.DUMMYFUNCTION("REGEXEXTRACT(A4, ""OPQ\s+(\d+)"")"),"11470") -> 11470 | G4: =IFERROR(__xludf.DUMMYFUNCTION("REGEXEXTRACT(A4, ""NPQ\[.*?\](\d+)"")"),"12044") -> 12044
A5: //Month1 //#E#City_Chennai//PRD-HappyGrow//OPQ 22348/NPQ[IPLMARKETING]22572 | B5: =IFERROR(__xludf.DUMMYFUNCTION("REGEXEXTRACT(A5, ""Month\d+"")"),"Month1") -> Month1 | C5: =IFERROR(__xludf.DUMMYFUNCTION("REGEXEXTRACT(A5, ""#([A-Z])#"") "),"E") -> E | D5: =IFERROR(__xludf.DUMMYFUNCTION("REGEXEXTRACT(A5, ""City_([^/]+)"")"),"Chennai") -> Chennai | E5: =IFERROR(__xludf.DUMMYFUNCTION("REGEXEXTRACT(A5, ""PRD-([^/]+)"")"),"HappyGrow") -> HappyGrow | F5: =IFERROR(__xludf.DUMMYFUNCTION("REGEXEXTRACT(A5, ""OPQ\s+(\d+)"")"),"22348") -> 22348 | G5: =IFERROR(__xludf.DUMMYFUNCTION("REGEXEXTRACT(A5, ""NPQ\[.*?\](\d+)"")"),"22572") -> 22572
A6: //Month1 //#W#City_Chennai//PRD-PowerSip//OPQ 13727/NPQ[IPLMARKETING]14551 | B6: =IFERROR(__xludf.DUMMYFUNCTION("REGEXEXTRACT(A6, ""Month\d+"")"),"Month1") -> Month1 | C6: =IFERROR(__xludf.DUMMYFUNCTION("REGEXEXTRACT(A6, ""#([A-Z])#"") "),"W") -> W | D6: =IFERROR(__xludf.DUMMYFUNCTION("REGEXEXTRACT(A6, ""City_([^/]+)"")"),"Chennai") -> Chennai | E6: =IFERROR(__xludf.DUMMYFUNCTION("REGEXEXTRACT(A6, ""PRD-([^/]+)"")"),"PowerSip") -> PowerSip | F6: =IFERROR(__xludf.DUMMYFUNCTION("REGEXEXTRACT(A6, ""OPQ\s+(\d+)"")"),"13727") -> 13727 | G6: =IFERROR(__xludf.DUMMYFUNCTION("REGEXEXTRACT(A6, ""NPQ\[.*?\](\d+)"")"),"14551") -> 14551
A7: //Month1 //#W#City_Chennai//PRD-HappyGrow//OPQ 15799/NPQ[IPLMARKETING]15957 | B7: =IFERROR(__xludf.DUMMYFUNCTION("REGEXEXTRACT(A7, ""Month\d+"")"),"Month1") -> Month1 | C7: =IFERROR(__xludf.DUMMYFUNCTION("REGEXEXTRACT(A7, ""#([A-Z])#"") "),"W") -> W | D7: =IFERROR(__xludf.DUMMYFUNCTION("REGEXEXTRACT(A7, ""City_([^/]+)"")"),"Chennai") -> Chennai | E7: =IFERROR(__xludf.DUMMYFUNCTION("REGEXEXTRACT(A7, ""PRD-([^/]+)"")"),"HappyGrow") -> HappyGrow | F7: =IFERROR(__xludf.DUMMYFUNCTION("REGEXEXTRACT(A7, ""OPQ\s+(\d+)"")"),"15799") -> 15799 | G7: =IFERROR(__xludf.DUMMYFUNCTION("REGEXEXTRACT(A7, ""NPQ\[.*?\](\d+)"")"),"15957") -> 15957
A8: //Month1 //#S#City_Chennai//PRD-PowerSip//OPQ 24827/NPQ[IPLMARKETING]26565 | B8: =IFERROR(__xludf.DUMMYFUNCTION("REGEXEXTRACT(A8, ""Month\d+"")"),"Month1") -> Month1 | C8: =IFERROR(__xludf.DUMMYFUNCTION("REGEXEXTRACT(A8, ""#([A-Z])#"") "),"S") -> S | D8: =IFERROR(__xludf.DUMMYFUNCTION("REGEXEXTRACT(A8, ""City_([^/]+)"")"),"Chennai") -> Chennai | E8: =IFERROR(__xludf.DUMMYFUNCTION("REGEXEXTRACT(A8, ""PRD-([^/]+)"")"),"PowerSip") -> PowerSip | F8: =IFERROR(__xludf.DUMMYFUNCTION("REGEXEXTRACT(A8, ""OPQ\s+(\d+)"")"),"24827") -> 24827 | G8: =IFERROR(__xludf.DUMMYFUNCTION("REGEXEXTRACT(A8, ""NPQ\[.*?\](\d+)"")"),"26565") -> 26565
A9: //Month1 //#S#City_Chennai//PRD-HappyGrow//OPQ 13468/NPQ[IPLMARKETING]13603 | B9: =IFERROR(__xludf.DUMMYFUNCTION("REGEXEXTRACT(A9, ""Month\d+"")"),"Month1") -> Month1 | C9: =IFERROR(__xludf.DUMMYFUNCTION("REGEXEXTRACT(A9, ""#([A-Z])#"") "),"S") -> S | D9: =IFERROR(__xludf.DUMMYFUNCTION("REGEXEXTRACT(A9, ""City_([^/]+)"")"),"Chennai") -> Chennai | E9: =IFERROR(__xludf.DUMMYFUNCTION("REGEXEXTRACT(A9, ""PRD-([^/]+)"")"),"HappyGrow") -> HappyGrow | F9: =IFERROR(__xludf.DUMMYFUNCTION("REGEXEXTRACT(A9, ""OPQ\s+(\d+)"")"),"13468") -> 13468 | G9: =IFERROR(__xludf.DUMMYFUNCTION("REGEXEXTRACT(A9, ""NPQ\[.*?\](\d+)"")"),"13603") -> 13603
A10: //Month1 //#N#City_Mumbai//PRD-PowerSip//OPQ 22237/NPQ[IPLMARKETING]23794 | B10: =IFERROR(__xludf.DUMMYFUNCTION("REGEXEXTRACT(A10, ""Month\d+"")"),"Month1") -> Month1 | C10: =IFERROR(__xludf.DUMMYFUNCTION("REGEXEXTRACT(A10, ""#([A-Z])#"") "),"N") -> N | D10: =IFERROR(__xludf.DUMMYFUNCTION("REGEXEXTRACT(A10, ""City_([^/]+)"")"),"Mumbai") -> Mumbai | E10: =IFERROR(__xludf.DUMMYFUNCTION("REGEXEXTRACT(A10, ""PRD-([^/]+)"")"),"PowerSip") -> PowerSip | F10: =IFERROR(__xludf.DUMMYFUNCTION("REGEXEXTRACT(A10, ""OPQ\s+(\d+)"")"),"22237") -> 22237 | G10: =IFERROR(__xludf.DUMMYFUNCTION("REGEXEXTRACT(A10, ""NPQ\[.*?\](\d+)"")"),"23794") -> 23794
A11: //Month1 //#N#City_Mumbai//PRD-HappyGrow//OPQ 23421/NPQ[IPLMARKETING]23656 | B11: =IFERROR(__xludf.DUMMYFUNCTION("REGEXEXTRACT(A11, ""Month\d+"")"),"Month1") -> Month1 | C11: =IFERROR(__xludf.DUMMYFUNCTION("REGEXEXTRACT(A11, ""#([A-Z])#"") "),"N") -> N | D11: =IFERROR(__xludf.DUMMYFUNCTION("REGEXEXTRACT(A11, ""City_([^/]+)"")"),"Mumbai") -> Mumbai | E11: =IFERROR(__xludf.DUMMYFUNCTION("REGEXEXTRACT(A11, ""PRD-([^/]+)"")"),"HappyGrow") -> HappyGrow | F11: =IFERROR(__xludf.DUMMYFUNCTION("REGEXEXTRACT(A11, ""OPQ\s+(\d+)"")"),"23421") -> 23421 | G11: =IFERROR(__xludf.DUMMYFUNCTION("REGEXEXTRACT(A11, ""NPQ\[.*?\](\d+)"")"),"23656") -> 23656
A12: //Month1 //#E#City_Mumbai//PRD-PowerSip//OPQ 12469/NPQ[IPLMARKETING]13467 | B12: =IFERROR(__xludf.DUMMYFUNCTION("REGEXEXTRACT(A12, ""Month\d+"")"),"Month1") -> Month1 | C12: =IFERROR(__xludf.DUMMYFUNCTION("REGEXEXTRACT(A12, ""#([A-Z])#"") "),"E") -> E | D12: =IFERROR(__xludf.DUMMYFUNCTION("REGEXEXTRACT(A12, ""City_([^/]+)"")"),"Mumbai") -> Mumbai | E12: =IFERROR(__xludf.DUMMYFUNCTION("REGEXEXTRACT(A12, ""PRD-([^/]+)"")"),"PowerSip") -> PowerSip | F12: =IFERROR(__xludf.DUMMYFUNCTION("REGEXEXTRACT(A12, ""OPQ\s+(\d+)"")"),"12469") -> 12469 | G12: =IFERROR(__xludf.DUMMYFUNCTION("REGEXEXTRACT(A12, ""NPQ\[.*?\](\d+)"")"),"13467") -> 13467
A13: //Month1 //#E#City_Mumbai//PRD-HappyGrow//OPQ 16354/NPQ[IPLMARKETING]16518 | B13: =IFERROR(__xludf.DUMMYFUNCTION("REGEXEXTRACT(A13, ""Month\d+"")"),"Month1") -> Month1 | C13: =IFERROR(__xludf.DUMMYFUNCTION("REGEXEXTRACT(A13, ""#([A-Z])#"") "),"E") -> E | D13: =IFERROR(__xludf.DUMMYFUNCTION("REGEXEXTRACT(A13, ""City_([^/]+)"")"),"Mumbai") -> Mumbai | E13: =IFERROR(__xludf.DUMMYFUNCTION("REGEXEXTRACT(A13, ""PRD-([^/]+)"")"),"HappyGrow") -> HappyGrow | F13: =IFERROR(__xludf.DUMMYFUNCTION("REGEXEXTRACT(A13, ""OPQ\s+(\d+)"")"),"16354") -> 16354 | G13: =IFERROR(__xludf.DUMMYFUNCTION("REGEXEXTRACT(A13, ""NPQ\[.*?\](\d+)"")"),"16518") -> 16518
A14: //Month1 //#W#City_Mumbai//PRD-PowerSip//OPQ 19536/NPQ[IPLMARKETING]21099 | B14: =IFERROR(__xludf.DUMMYFUNCTION("REGEXEXTRACT(A14, ""Month\d+"")"),"Month1") -> Month1 | C14: =IFERROR(__xludf.DUMMYFUNCTION("REGEXEXTRACT(A14, ""#([A-Z])#"") "),"W") -> W | D14: =IFERROR(__xludf.DUMMYFUNCTION("REGEXEXTRACT(A14, ""City_([^/]+)"")"),"Mumbai") -> Mumbai | E14: =IFERROR(__xludf.DUMMYFUNCTION("REGEXEXTRACT(A14, ""PRD-([^/]+)"")"),"PowerSip") -> PowerSip | F14: =IFERROR(__xludf.DUMMYFUNCTION("REGEXEXTRACT(A14, ""OPQ\s+(\d+)"")"),"19536") -> 19536 | G14: =IFERROR(__xludf.DUMMYFUNCTION("REGEXEXTRACT(A14, ""NPQ\[.*?\](\d+)"")"),"21099") -> 21099
A15: //Month1 //#W#City_Mumbai//PRD-HappyGrow//OPQ 11359/NPQ[IPLMARKETING]11587 | B15: =IFERROR(__xludf.DUMMYFUNCTION("REGEXEXTRACT(A15, ""Month\d+"")"),"Month1") -> Month1 | C15: =IFERROR(__xludf.DUMMYFUNCTION("REGEXEXTRACT(A15, ""#([A-Z])#"") "),"W") -> W | D15: =IFERROR(__xludf.DUMMYFUNCTION("REGEXEXTRACT(A15, ""City_([^/]+)"")"),"Mumbai") -> Mumbai | E15: =IFERROR(__xludf.DUMMYFUNCTION("REGEXEXTRACT(A15, ""PRD-([^/]+)"")"),"HappyGrow") -> HappyGrow | F15: =IFERROR(__xludf.DUMMYFUNCTION("REGEXEXTRACT(A15, ""OPQ\s+(\d+)"")"),"11359") -> 11359 | G15: =IFERROR(__xludf.DUMMYFUNCTION("REGEXEXTRACT(A15, ""NPQ\[.*?\](\d+)"")"),"11587") -> 11587
A16: //Month1 //#S#City_Mumbai//PRD-PowerSip//OPQ 12062/NPQ[IPLMARKETING]13148 | B16: =IFERROR(__xludf.DUMMYFUNCTION("REGEXEXTRACT(A16, ""Month\d+"")"),"Month1") -> Month1 | C16: =IFERROR(__xludf.DUMMYFUNCTION("REGEXEXTRACT(A16, ""#([A-Z])#"") "),"S") -> S | D16: =IFERROR(__xludf.DUMMYFUNCTION("REGEXEXTRACT(A16, ""City_([^/]+)"")"),"Mumbai") -> Mumbai | E16: =IFERROR(__xludf.DUMMYFUNCTION("REGEXEXTRACT(A16, ""PRD-([^/]+)"")"),"PowerSip") -> PowerSip | F16: =IFERROR(__xludf.DUMMYFUNCTION("REGEXEXTRACT(A16, ""OPQ\s+(\d+)"")"),"12062") -> 12062 | G16: =IFERROR(__xludf.DUMMYFUNCTION("REGEXEXTRACT(A16, ""NPQ\[.*?\](\d+)"")"),"13148") -> 13148
A17: //Month1 //#S#City_Mumbai//PRD-HappyGrow//OPQ 13579/NPQ[IPLMARKETING]13851 | B17: =IFERROR(__xludf.DUMMYFUNCTION("REGEXEXTRACT(A17, ""Month\d+"")"),"Month1") -> Month1 | C17: =IFERROR(__xludf.DUMMYFUNCTION("REGEXEXTRACT(A17, ""#([A-Z])#"") "),"S") -> S | D17: =IFERROR(__xludf.DUMMYFUNCTION("REGEXEXTRACT(A17, ""City_([^/]+)"")"),"Mumbai") -> Mumbai | E17: =IFERROR(__xludf.DUMMYFUNCTION("REGEXEXTRACT(A17, ""PRD-([^/]+)"")"),"HappyGrow") -> HappyGrow | F17: =IFERROR(__xludf.DUMMYFUNCTION("REGEXEXTRACT(A17, ""OPQ\s+(\d+)"")"),"13579") -> 13579 | G17: =IFERROR(__xludf.DUMMYFUNCTION("REGEXEXTRACT(A17, ""NPQ\[.*?\](\d+)"")"),"13851") -> 13851
A18: //Month1 //#N#City_Bengaluru//PRD-PowerSip//OPQ 21275/NPQ[IPLMARKETING]23190 | B18: =IFERROR(__xludf.DUMMYFUNCTION("REGEXEXTRACT(A18, ""Month\d+"")"),"Month1") -> Month1 | C18: =IFERROR(__xludf.DUMMYFUNCTION("REGEXEXTRACT(A18, ""#([A-Z])#"") "),"N") -> N | D18: =IFERROR(__xludf.DUMMYFUNCTION("REGEXEXTRACT(A18, ""City_([^/]+)"")"),"Bengaluru") -> Bengaluru | E18: =IFERROR(__xludf.DUMMYFUNCTION("REGEXEXTRACT(A18, ""PRD-([^/]+)"")"),"PowerSip") -> PowerSip | F18: =IFERROR(__xludf.DUMMYFUNCTION("REGEXEXTRACT(A18, ""OPQ\s+(\d+)"")"),"21275") -> 21275 | G18: =IFERROR(__xludf.DUMMYFUNCTION("REGEXEXTRACT(A18, ""NPQ\[.*?\](\d+)"")"),"23190") -> 23190
A19: //Month1 //#N#City_Bengaluru//PRD-HappyGrow//OPQ 18611/NPQ[IPLMARKETING]18984 | B19: =IFERROR(__xludf.DUMMYFUNCTION("REGEXEXTRACT(A19, ""Month\d+"")"),"Month1") -> Month1 | C19: =IFERROR(__xludf.DUMMYFUNCTION("REGEXEXTRACT(A19, ""#([A-Z])#"") "),"N") -> N | D19: =IFERROR(__xludf.DUMMYFUNCTION("REGEXEXTRACT(A19, ""City_([^/]+)"")"),"Bengaluru") -> Bengaluru | E19: =IFERROR(__xludf.DUMMYFUNCTION("REGEXEXTRACT(A19, ""PRD-([^/]+)"")"),"HappyGrow") -> HappyGrow | F19: =IFERROR(__xludf.DUMMYFUNCTION("REGEXEXTRACT(A19, ""OPQ\s+(\d+)"")"),"18611") -> 18611 | G19: =IFERROR(__xludf.DUMMYFUNCTION("REGEXEXTRACT(A19, ""NPQ\[.*?\](\d+)"")"),"18984") -> 18984
A20: //Month1 //#E#City_Bengaluru//PRD-PowerSip//OPQ 24050/NPQ[IPLMARKETING]26215 | B20: =IFERROR(__xludf.DUMMYFUNCTION("REGEXEXTRACT(A20, ""Month\d+"")"),"Month1") -> Month1 | C20: =IFERROR(__xludf.DUMMYFUNCTION("REGEXEXTRACT(A20, ""#([A-Z])#"") "),"E") -> E | D20: =IFERROR(__xludf.DUMMYFUNCTION("REGEXEXTRACT(A20, ""City_([^/]+)"")"),"Bengaluru") -> Bengaluru | E20: =IFERROR(__xludf.DUMMYFUNCTION("REGEXEXTRACT(A20, ""PRD-([^/]+)"")"),"PowerSip") -> PowerSip | F20: =IFERROR(__xludf.DUMMYFUNCTION("REGEXEXTRACT(A20, ""OPQ\s+(\d+)"")"),"24050") -> 24050 | G20: =IFERROR(__xludf.DUMMYFUNCTION("REGEXEXTRACT(A20, ""NPQ\[.*?\](\d+)"")"),"26215") -> 26215
A21: //Month1 //#E#City_Bengaluru//PRD-HappyGrow//OPQ 15133/NPQ[IPLMARKETING]15436 | B21: =IFERROR(__xludf.DUMMYFUNCTION("REGEXEXTRACT(A21, ""Month\d+"")"),"Month1") -> Month1 | C21: =IFERROR(__xludf.DUMMYFUNCTION("REGEXEXTRACT(A21, ""#([A-Z])#"") "),"E") -> E | D21: =IFERROR(__xludf.DUMMYFUNCTION("REGEXEXTRACT(A21, ""City_([^/]+)"")"),"Bengaluru") -> Bengaluru | E21: =IFERROR(__xludf.DUMMYFUNCTION("REGEXEXTRACT(A21, ""PRD-([^/]+)"")"),"HappyGrow") -> HappyGrow | F21: =IFERROR(__xludf.DUMMYFUNCTION("REGEXEXTRACT(A21, ""OPQ\s+(\d+)"")"),"15133") -> 15133 | G21: =IFERROR(__xludf.DUMMYFUNCTION("REGEXEXTRACT(A21, ""NPQ\[.*?\](\d+)"")"),"15436") -> 15436
A22: //Month1 //#W#City_Bengaluru//PRD-PowerSip//OPQ 17834/NPQ[IPLMARKETING]19618 | B22: =IFERROR(__xludf.DUMMYFUNCTION("REGEXEXTRACT(A22, ""Month\d+"")"),"Month1") -> Month1 | C22: =IFERROR(__xludf.DUMMYFUNCTION("REGEXEXTRACT(A22, ""#([A-Z])#"") "),"W") -> W | D22: =IFERROR(__xludf.DUMMYFUNCTION("REGEXEXTRACT(A22, ""City_([^/]+)"")"),"Bengaluru") -> Bengaluru | E22: =IFERROR(__xludf.DUMMYFUNCTION("REGEXEXTRACT(A22, ""PRD-([^/]+)"")"),"PowerSip") -> PowerSip | F22: =IFERROR(__xludf.DUMMYFUNCTION("REGEXEXTRACT(A22, ""OPQ\s+(\d+)"")"),"17834") -> 17834 | G22: =IFERROR(__xludf.DUMMYFUNCTION("REGEXEXTRACT(A22, ""NPQ\[.*?\](\d+)"")"),"19618") -> 19618
A23: //Month1 //#W#City_Bengaluru//PRD-HappyGrow//OPQ 14097/NPQ[IPLMARKETING]14520 | B23: =IFERROR(__xludf.DUMMYFUNCTION("REGEXEXTRACT(A23, ""Month\d+"")"),"Month1") -> Month1 | C23: =IFERROR(__xludf.DUMMYFUNCTION("REGEXEXTRACT(A23, ""#([A-Z])#"") "),"W") -> W | D23: =IFERROR(__xludf.DUMMYFUNCTION("REGEXEXTRACT(A23, ""City_([^/]+)"")"),"Bengaluru") -> Bengaluru | E23: =IFERROR(__xludf.DUMMYFUNCTION("REGEXEXTRACT(A23, ""PRD-([^/]+)"")"),"HappyGrow") -> HappyGrow | F23: =IFERROR(__xludf.DUMMYFUNCTION("REGEXEXTRACT(A23, ""OPQ\s+(\d+)"")"),"14097") -> 14097 | G23: =IFERROR(__xludf.DUMMYFUNCTION("REGEXEXTRACT(A23, ""NPQ\[.*?\](\d+)"")"),"14520") -> 14520
A24: //Month1 //#S#City_Bengaluru//PRD-PowerSip//OPQ 24642/NPQ[IPLMARKETING]27353 | B24: =IFERROR(__xludf.DUMMYFUNCTION("REGEXEXTRACT(A24, ""Month\d+"")"),"Month1") -> Month1 | C24: =IFERROR(__xludf.DUMMYFUNCTION("REGEXEXTRACT(A24, ""#([A-Z])#"") "),"S") -> S | D24: =IFERROR(__xludf.DUMMYFUNCTION("REGEXEXTRACT(A24, ""City_([^/]+)"")"),"Bengaluru") -> Bengaluru | E24: =IFERROR(__xludf.DUMMYFUNCTION("REGEXEXTRACT(A24, ""PRD-([^/]+)"")"),"PowerSip") -> PowerSip | F24: =IFERROR(__xludf.DUMMYFUNCTION("REGEXEXTRACT(A24, ""OPQ\s+(\d+)"")"),"24642") -> 24642 | G24: =IFERROR(__xludf.DUMMYFUNCTION("REGEXEXTRACT(A24, ""NPQ\[.*?\](\d+)"")"),"27353") -> 27353
A25: //Month1 //#S#City_Bengaluru//PRD-HappyGrow//OPQ 24864/NPQ[IPLMARKETING]25610 | B25: =IFERROR(__xludf.DUMMYFUNCTION("REGEXEXTRACT(A25, ""Month\d+"")"),"Month1") -> Month1 | C25: =IFERROR(__xludf.DUMMYFUNCTION("REGEXEXTRACT(A25, ""#([A-Z])#"") "),"S") -> S | D25: =IFERROR(__xludf.DUMMYFUNCTION("REGEXEXTRACT(A25, ""City_([^/]+)"")"),"Bengaluru") -> Bengaluru | E25: =IFERROR(__xludf.DUMMYFUNCTION("REGEXEXTRACT(A25, ""PRD-([^/]+)"")"),"HappyGrow") -> HappyGrow | F25: =IFERROR(__xludf.DUMMYFUNCTION("REGEXEXTRACT(A25, ""OPQ\s+(\d+)"")"),"24864") -> 24864 | G25: =IFERROR(__xludf.DUMMYFUNCTION("REGEXEXTRACT(A25, ""NPQ\[.*?\](\d+)"")"),"25610") -> 25610
A26: //Month1 //#N#City_Delhi//PRD-PowerSip//OPQ 19832/NPQ[IPLMARKETING]22212 | B26: =IFERROR(__xludf.DUMMYFUNCTION("REGEXEXTRACT(A26, ""Month\d+"")"),"Month1") -> Month1 | C26: =IFERROR(__xludf.DUMMYFUNCTION("REGEXEXTRACT(A26, ""#([A-Z])#"") "),"N") -> N | D26: =IFERROR(__xludf.DUMMYFUNCTION("REGEXEXTRACT(A26, ""City_([^/]+)"")"),"Delhi") -> Delhi | E26: =IFERROR(__xludf.DUMMYFUNCTION("REGEXEXTRACT(A26, ""PRD-([^/]+)"")"),"PowerSip") -> PowerSip | F26: =IFERROR(__xludf.DUMMYFUNCTION("REGEXEXTRACT(A26, ""OPQ\s+(\d+)"")"),"19832") -> 19832 | G26: =IFERROR(__xludf.DUMMYFUNCTION("REGEXEXTRACT(A26, ""NPQ\[.*?\](\d+)"")"),"22212") -> 22212
A27: //Month1 //#N#City_Delhi//PRD-HappyGrow//OPQ 12321/NPQ[IPLMARKETING]12691 | B27: =IFERROR(__xludf.DUMMYFUNCTION("REGEXEXTRACT(A27, ""Month\d+"")"),"Month1") -> Month1 | C27: =IFERROR(__xludf.DUMMYFUNCTION("REGEXEXTRACT(A27, ""#([A-Z])#"") "),"N") -> N | D27: =IFERROR(__xludf.DUMMYFUNCTION("REGEXEXTRACT(A27, ""City_([^/]+)"")"),"Delhi") -> Delhi | E27: =IFERROR(__xludf.DUMMYFUNCTION("REGEXEXTRACT(A27, ""PRD-([^/]+)"")"),"HappyGrow") -> HappyGrow | F27: =IFERROR(__xludf.DUMMYFUNCTION("REGEXEXTRACT(A27, ""OPQ\s+(\d+)"")"),"12321") -> 12321 | G27: =IFERROR(__xludf.DUMMYFUNCTION("REGEXEXTRACT(A27, ""NPQ\[.*?\](\d+)"")"),"12691") -> 12691
A28: //Month1 //#E#City_Delhi//PRD-PowerSip//OPQ 21571/NPQ[IPLMARKETING]24160 | B28: =IFERROR(__xludf.DUMMYFUNCTION("REGEXEXTRACT(A28, ""Month\d+"")"),"Month1") -> Month1 | C28: =IFERROR(__xludf.DUMMYFUNCTION("REGEXEXTRACT(A28, ""#([A-Z])#"") "),"E") -> E | D28: =IFERROR(__xludf.DUMMYFUNCTION("REGEXEXTRACT(A28, ""City_([^/]+)"")"),"Delhi") -> Delhi | E28: =IFERROR(__xludf.DUMMYFUNCTION("REGEXEXTRACT(A28, ""PRD-([^/]+)"")"),"PowerSip") -> PowerSip | F28: =IFERROR(__xludf.DUMMYFUNCTION("REGEXEXTRACT(A28, ""OPQ\s+(\d+)"")"),"21571") -> 21571 | G28: =IFERROR(__xludf.DUMMYFUNCTION("REGEXEXTRACT(A28, ""NPQ\[.*?\](\d+)"")"),"24160") -> 24160
A29: //Month1 //#E#City_Delhi//PRD-HappyGrow//OPQ 13320/NPQ[IPLMARKETING]13853 | B29: =IFERROR(__xludf.DUMMYFUNCTION("REGEXEXTRACT(A29, ""Month\d+"")"),"Month1") -> Month1 | C29: =IFERROR(__xludf.DUMMYFUNCTION("REGEXEXTRACT(A29, ""#([A-Z])#"") "),"E") -> E | D29: =IFERROR(__xludf.DUMMYFUNCTION("REGEXEXTRACT(A29, ""City_([^/]+)"")"),"Delhi") -> Delhi | E29: =IFERROR(__xludf.DUMMYFUNCTION("REGEXEXTRACT(A29, ""PRD-([^/]+)"")"),"HappyGrow") -> HappyGrow | F29: =IFERROR(__xludf.DUMMYFUNCTION("REGEXEXTRACT(A29, ""OPQ\s+(\d+)"")"),"13320") -> 13320 | G29: =IFERROR(__xludf.DUMMYFUNCTION("REGEXEXTRACT(A29, ""NPQ\[.*?\](\d+)"")"),"13853") -> 13853
A30: //Month1 //#W#City_Delhi//PRD-PowerSip//OPQ 20091/NPQ[IPLMARKETING]22502 | B30: =IFERROR(__xludf.DUMMYFUNCTION("REGEXEXTRACT(A30, ""Month\d+"")"),"Month1") -> Month1 | C30: =IFERROR(__xludf.DUMMYFUNCTION("REGEXEXTRACT(A30, ""#([A-Z])#"") "),"W") -> W | D30: =IFERROR(__xludf.DUMMYFUNCTION("REGEXEXTRACT(A30, ""City_([^/]+)"")"),"Delhi") -> Delhi | E30: =IFERROR(__xludf.DUMMYFUNCTION("REGEXEXTRACT(A30, ""PRD-([^/]+)"")"),"PowerSip") -> PowerSip | F30: =IFERROR(__xludf.DUMMYFUNCTION("REGEXEXTRACT(A30, ""OPQ\s+(\d+)"")"),"20091") -> 20091 | G30: =IFERROR(__xludf.DUMMYFUNCTION("REGEXEXTRACT(A30, ""NPQ\[.*?\](\d+)"")"),"22502") -> 22502
A31: //Month1 //#W#City_Delhi//PRD-HappyGrow//OPQ 15244/NPQ[IPLMARKETING]15854 | B31: =IFERROR(__xludf.DUMMYFUNCTION("REGEXEXTRACT(A31, ""Month\d+"")"),"Month1") -> Month1 | C31: =IFERROR(__xludf.DUMMYFUNCTION("REGEXEXTRACT(A31, ""#([A-Z])#"") "),"W") -> W | D31: =IFERROR(__xludf.DUMMYFUNCTION("REGEXEXTRACT(A31, ""City_([^/]+)"")"),"Delhi") -> Delhi | E31: =IFERROR(__xludf.DUMMYFUNCTION("REGEXEXTRACT(A31, ""PRD-([^/]+)"")"),"HappyGrow") -> HappyGrow | F31: =IFERROR(__xludf.DUMMYFUNCTION("REGEXEXTRACT(A31, ""OPQ\s+(\d+)"")"),"15244") -> 15244 | G31: =IFERROR(__xludf.DUMMYFUNCTION("REGEXEXTRACT(A31, ""NPQ\[.*?\](\d+)"")"),"15854") -> 15854
A32: //Month1 //#S#City_Delhi//PRD-PowerSip//OPQ 17316/NPQ[IPLMARKETING]19394 | B32: =IFERROR(__xludf.DUMMYFUNCTION("REGEXEXTRACT(A32, ""Month\d+"")"),"Month1") -> Month1 | C32: =IFERROR(__xludf.DUMMYFUNCTION("REGEXEXTRACT(A32, ""#([A-Z])#"") "),"S") -> S | D32: =IFERROR(__xludf.DUMMYFUNCTION("REGEXEXTRACT(A32, ""City_([^/]+)"")"),"Delhi") -> Delhi | E32: =IFERROR(__xludf.DUMMYFUNCTION("REGEXEXTRACT(A32, ""PRD-([^/]+)"")"),"PowerSip") -> PowerSip | F32: =IFERROR(__xludf.DUMMYFUNCTION("REGEXEXTRACT(A32, ""OPQ\s+(\d+)"")"),"17316") -> 17316 | G32: =IFERROR(__xludf.DUMMYFUNCTION("REGEXEXTRACT(A32, ""NPQ\[.*?\](\d+)"")"),"19394") -> 19394
A33: //Month1 //#S#City_Delhi//PRD-HappyGrow//OPQ 22866/NPQ[IPLMARKETING]23781 | B33: =IFERROR(__xludf.DUMMYFUNCTION("REGEXEXTRACT(A33, ""Month\d+"")"),"Month1") -> Month1 | C33: =IFERROR(__xludf.DUMMYFUNCTION("REGEXEXTRACT(A33, ""#([A-Z])#"") "),"S") -> S | D33: =IFERROR(__xludf.DUMMYFUNCTION("REGEXEXTRACT(A33, ""City_([^/]+)"")"),"Delhi") -> Delhi | E33: =IFERROR(__xludf.DUMMYFUNCTION("REGEXEXTRACT(A33, ""PRD-([^/]+)"")"),"HappyGrow") -> HappyGrow | F33: =IFERROR(__xludf.DUMMYFUNCTION("REGEXEXTRACT(A33, ""OPQ\s+(\d+)"")"),"22866") -> 22866 | G33: =IFERROR(__xludf.DUMMYFUNCTION("REGEXEXTRACT(A33, ""NPQ\[.*?\](\d+)"")"),"23781") -> 23781
A34: //Month2 //#N#City_Chennai//PRD-PowerSip//OPQ 23647/NPQ[IPLMARKETING]26485 | B34: =IFERROR(__xludf.DUMMYFUNCTION("REGEXEXTRACT(A34, ""Month\d+"")"),"Month2") -> Month2 | C34: =IFERROR(__xludf.DUMMYFUNCTION("REGEXEXTRACT(A34, ""#([A-Z])#"") "),"N") -> N | D34: =IFERROR(__xludf.DUMMYFUNCTION("REGEXEXTRACT(A34, ""City_([^/]+)"")"),"Chennai") -> Chennai | E34: =IFERROR(__xludf.DUMMYFUNCTION("REGEXEXTRACT(A34, ""PRD-([^/]+)"")"),"PowerSip") -> PowerSip | F34: =IFERROR(__xludf.DUMMYFUNCTION("REGEXEXTRACT(A34, ""OPQ\s+(\d+)"")"),"23647") -> 23647 | G34: =IFERROR(__xludf.DUMMYFUNCTION("REGEXEXTRACT(A34, ""NPQ\[.*?\](\d+)"")"),"26485") -> 26485
A35: //Month2 //#N#City_Chennai//PRD-HappyGrow//OPQ 17816/NPQ[IPLMARKETING]18529 | B35: =IFERROR(__xludf.DUMMYFUNCTION("REGEXEXTRACT(A35, ""Month\d+"")"),"Month2") -> Month2 | C35: =IFERROR(__xludf.DUMMYFUNCTION("REGEXEXTRACT(A35, ""#([A-Z])#"") "),"N") -> N | D35: =IFERROR(__xludf.DUMMYFUNCTION("REGEXEXTRACT(A35, ""City_([^/]+)"")"),"Chennai") -> Chennai | E35: =IFERROR(__xludf.DUMMYFUNCTION("REGEXEXTRACT(A35, ""PRD-([^/]+)"")"),"HappyGrow") -> HappyGrow | F35: =IFERROR(__xludf.DUMMYFUNCTION("REGEXEXTRACT(A35, ""OPQ\s+(\d+)"")"),"17816") -> 17816 | G35: =IFERROR(__xludf.DUMMYFUNCTION("REGEXEXTRACT(A35, ""NPQ\[.*?\](\d+)"")"),"18529") -> 18529
A36: //Month2 //#E#City_Chennai//PRD-PowerSip//OPQ 12617/NPQ[IPLMARKETING]14258 | B36: =IFERROR(__xludf.DUMMYFUNCTION("REGEXEXTRACT(A36, ""Month\d+"")"),"Month2") -> Month2 | C36: =IFERROR(__xludf.DUMMYFUNCTION("REGEXEXTRACT(A36, ""#([A-Z])#"") "),"E") -> E | D36: =IFERROR(__xludf.DUMMYFUNCTION("REGEXEXTRACT(A36, ""City_([^/]+)"")"),"Chennai") -> Chennai | E36: =IFERROR(__xludf.DUMMYFUNCTION("REGEXEXTRACT(A36, ""PRD-([^/]+)"")"),"PowerSip") -> PowerSip | F36: =IFERROR(__xludf.DUMMYFUNCTION("REGEXEXTRACT(A36, ""OPQ\s+(\d+)"")"),"12617") -> 12617 | G36: =IFERROR(__xludf.DUMMYFUNCTION("REGEXEXTRACT(A36, ""NPQ\[.*?\](\d+)"")"),"14258") -> 14258
A37: //Month2 //#E#City_Chennai//PRD-HappyGrow//OPQ 23912/NPQ[IPLMARKETING]25108 | B37: =IFERROR(__xludf.DUMMYFUNCTION("REGEXEXTRACT(A37, ""Month\d+"")"),"Month2") -> Month2 | C37: =IFERROR(__xludf.DUMMYFUNCTION("REGEXEXTRACT(A37, ""#([A-Z])#"") "),"E") -> E | D37: =IFERROR(__xludf.DUMMYFUNCTION("REGEXEXTRACT(A37, ""City_([^/]+)"")"),"Chennai") -> Chennai | E37: =IFERROR(__xludf.DUMMYFUNCTION("REGEXEXTRACT(A37, ""PRD-([^/]+)"")"),"HappyGrow") -> HappyGrow | F37: =IFERROR(__xludf.DUMMYFUNCTION("REGEXEXTRACT(A37, ""OPQ\s+(\d+)"")"),"23912") -> 23912 | G37: =IFERROR(__xludf.DUMMYFUNCTION("REGEXEXTRACT(A37, ""NPQ\[.*?\](\d+)"")"),"25108") -> 25108
A38: //Month2 //#W#City_Chennai//PRD-PowerSip//OPQ 15100/NPQ[IPLMARKETING]17063 | B38: =IFERROR(__xludf.DUMMYFUNCTION("REGEXEXTRACT(A38, ""Month\d+"")"),"Month2") -> Month2 | C38: =IFERROR(__xludf.DUMMYFUNCTION("REGEXEXTRACT(A38, ""#([A-Z])#"") "),"W") -> W | D38: =IFERROR(__xludf.DUMMYFUNCTION("REGEXEXTRACT(A38, ""City_([^/]+)"")"),"Chennai") -> Chennai | E38: =IFERROR(__xludf.DUMMYFUNCTION("REGEXEXTRACT(A38, ""PRD-([^/]+)"")"),"PowerSip") -> PowerSip | F38: =IFERROR(__xludf.DUMMYFUNCTION("REGEXEXTRACT(A38, ""OPQ\s+(\d+)"")"),"15100") -> 15100 | G38: =IFERROR(__xludf.DUMMYFUNCTION("REGEXEXTRACT(A38, ""NPQ\[.*?\](\d+)"")"),"17063") -> 17063
A39: //Month2 //#W#City_Chennai//PRD-HappyGrow//OPQ 16905/NPQ[IPLMARKETING]17751 | B39: =IFERROR(__xludf.DUMMYFUNCTION("REGEXEXTRACT(A39, ""Month\d+"")"),"Month2") -> Month2 | C39: =IFERROR(__xludf.DUMMYFUNCTION("REGEXEXTRACT(A39, ""#([A-Z])#"") "),"W") -> W | D39: =IFERROR(__xludf.DUMMYFUNCTION("REGEXEXTRACT(A39, ""City_([^/]+)"")"),"Chennai") -> Chennai | E39: =IFERROR(__xludf.DUMMYFUNCTION("REGEXEXTRACT(A39, ""PRD-([^/]+)"")"),"HappyGrow") -> HappyGrow | F39: =IFERROR(__xludf.DUMMYFUNCTION("REGEXEXTRACT(A39, ""OPQ\s+(\d+)"")"),"16905") -> 16905 | G39: =IFERROR(__xludf.DUMMYFUNCTION("REGEXEXTRACT(A39, ""NPQ\[.*?\](\d+)"")"),"17751") -> 17751
A40: //Month2 //#S#City_Chennai//PRD-PowerSip//OPQ 27310/NPQ[IPLMARKETING]30861 | B40: =IFERROR(__xludf.DUMMYFUNCTION("REGEXEXTRACT(A40, ""Month\d+"")"),"Month2") -> Month2 | C40: =IFERROR(__xludf.DUMMYFUNCTION("REGEXEXTRACT(A40, ""#([A-Z])#"") "),"S") -> S | D40: =IFERROR(__xludf.DUMMYFUNCTION("REGEXEXTRACT(A40, ""City_([^/]+)"")"),"Chennai") -> Chennai | E40: =IFERROR(__xludf.DUMMYFUNCTION("REGEXEXTRACT(A40, ""PRD-([^/]+)"")"),"PowerSip") -> PowerSip | F40: =IFERROR(__xludf.DUMMYFUNCTION("REGEXEXTRACT(A40, ""OPQ\s+(\d+)"")"),"27310") -> 27310 | G40: =IFERROR(__xludf.DUMMYFUNCTION("REGEXEXTRACT(A40, ""NPQ\[.*?\](\d+)"")"),"30861") -> 30861
A41: //Month2 //#S#City_Chennai//PRD-HappyGrow//OPQ 14411/NPQ[IPLMARKETING]15132 | B41: =IFERROR(__xludf.DUMMYFUNCTION("REGEXEXTRACT(A41, ""Month\d+"")"),"Month2") -> Month2 | C41: =IFERROR(__xludf.DUMMYFUNCTION("REGEXEXTRACT(A41, ""#([A-Z])#"") "),"S") -> S | D41: =IFERROR(__xludf.DUMMYFUNCTION("REGEXEXTRACT(A41, ""City_([^/]+)"")"),"Chennai") -> Chennai | E41: =IFERROR(__xludf.DUMMYFUNCTION("REGEXEXTRACT(A41, ""PRD-([^/]+)"")"),"HappyGrow") -> HappyGrow | F41: =IFERROR(__xludf.DUMMYFUNCTION("REGEXEXTRACT(A41, ""OPQ\s+(\d+)"")"),"14411") -> 14411 | G41: =IFERROR(__xludf.DUMMYFUNCTION("REGEXEXTRACT(A41, ""NPQ\[.*?\](\d+)"")"),"15132") -> 15132
A42: //Month2 //#N#City_Mumbai//PRD-PowerSip//OPQ 24461/NPQ[IPLMARKETING]27886 | B42: =IFERROR(__xludf.DUMMYFUNCTION("REGEXEXTRACT(A42, ""Month\d+"")"),"Month2") -> Month2 | C42: =IFERROR(__xludf.DUMMYFUNCTION("REGEXEXTRACT(A42, ""#([A-Z])#"") "),"N") -> N | D42: =IFERROR(__xludf.DUMMYFUNCTION("REGEXEXTRACT(A42, ""City_([^/]+)"")"),"Mumbai") -> Mumbai | E42: =IFERROR(__xludf.DUMMYFUNCTION("REGEXEXTRACT(A42, ""PRD-([^/]+)"")"),"PowerSip") -> PowerSip | F42: =IFERROR(__xludf.DUMMYFUNCTION("REGEXEXTRACT(A42, ""OPQ\s+(\d+)"")"),"24461") -> 24461 | G42: =IFERROR(__xludf.DUMMYFUNCTION("REGEXEXTRACT(A42, ""NPQ\[.*?\](\d+)"")"),"27886") -> 27886
A43: //Month2 //#N#City_Mumbai//PRD-HappyGrow//OPQ 25060/NPQ[IPLMARKETING]26313 | B43: =IFERROR(__xludf.DUMMYFUNCTION("REGEXEXTRACT(A43, ""Month\d+"")"),"Month2") -> Month2 | C43: =IFERROR(__xludf.DUMMYFUNCTION("REGEXEXTRACT(A43, ""#([A-Z])#"") "),"N") -> N | D43: =IFERROR(__xludf.DUMMYFUNCTION("REGEXEXTRACT(A43, ""City_([^/]+)"")"),"Mumbai") -> Mumbai | E43: =IFERROR(__xludf.DUMMYFUNCTION("REGEXEXTRACT(A43, ""PRD-([^/]+)"")"),"HappyGrow") -> HappyGrow | F43: =IFERROR(__xludf.DUMMYFUNCTION("REGEXEXTRACT(A43, ""OPQ\s+(\d+)"")"),"25060") -> 25060 | G43: =IFERROR(__xludf.DUMMYFUNCTION("REGEXEXTRACT(A43, ""NPQ\[.*?\](\d+)"")"),"26313") -> 26313
A44: //Month2 //#E#City_Mumbai//PRD-PowerSip//OPQ 13716/NPQ[IPLMARKETING]15637 | B44: =IFERROR(__xludf.DUMMYFUNCTION("REGEXEXTRACT(A44, ""Month\d+"")"),"Month2") -> Month2 | C44: =IFERROR(__xludf.DUMMYFUNCTION("REGEXEXTRACT(A44, ""#([A-Z])#"") "),"E") -> E | D44: =IFERROR(__xludf.DUMMYFUNCTION("REGEXEXTRACT(A44, ""City_([^/]+)"")"),"Mumbai") -> Mumbai | E44: =IFERROR(__xludf.DUMMYFUNCTION("REGEXEXTRACT(A44, ""PRD-([^/]+)"")"),"PowerSip") -> PowerSip | F44: =IFERROR(__xludf.DUMMYFUNCTION("REGEXEXTRACT(A44, ""OPQ\s+(\d+)"")"),"13716") -> 13716 | G44: =IFERROR(__xludf.DUMMYFUNCTION("REGEXEXTRACT(A44, ""NPQ\[.*?\](\d+)"")"),"15637") -> 15637
A45: //Month2 //#E#City_Mumbai//PRD-HappyGrow//OPQ 17499/NPQ[IPLMARKETING]18549 | B45: =IFERROR(__xludf.DUMMYFUNCTION("REGEXEXTRACT(A45, ""Month\d+"")"),"Month2") -> Month2 | C45: =IFERROR(__xludf.DUMMYFUNCTION("REGEXEXTRACT(A45, ""#([A-Z])#"") "),"E") -> E | D45: =IFERROR(__xludf.DUMMYFUNCTION("REGEXEXTRACT(A45, ""City_([^/]+)"")"),"Mumbai") -> Mumbai | E45: =IFERROR(__xludf.DUMMYFUNCTION("REGEXEXTRACT(A45, ""PRD-([^/]+)"")"),"HappyGrow") -> HappyGrow | F45: =IFERROR(__xludf.DUMMYFUNCTION("REGEXEXTRACT(A45, ""OPQ\s+(\d+)"")"),"17499") -> 17499 | G45: =IFERROR(__xludf.DUMMYFUNCTION("REGEXEXTRACT(A45, ""NPQ\[.*?\](\d+)"")"),"18549") -> 18549
A46: //Month2 //#W#City_Mumbai//PRD-PowerSip//OPQ 21490/NPQ[IPLMARKETING]24929 | B46: =IFERROR(__xludf.DUMMYFUNCTION("REGEXEXTRACT(A46, ""Month\d+"")"),"Month2") -> Month2 | C46: =IFERROR(__xludf.DUMMYFUNCTION("REGEXEXTRACT(A46, ""#([A-Z])#"") "),"W") -> W | D46: =IFERROR(__xludf.DUMMYFUNCTION("REGEXEXTRACT(A46, ""City_([^/]+)"")"),"Mumbai") -> Mumbai | E46: =IFERROR(__xludf.DUMMYFUNCTION("REGEXEXTRACT(A46, ""PRD-([^/]+)"")"),"PowerSip") -> PowerSip | F46: =IFERROR(__xludf.DUMMYFUNCTION("REGEXEXTRACT(A46, ""OPQ\s+(\d+)"")"),"21490") -> 21490 | G46: =IFERROR(__xludf.DUMMYFUNCTION("REGEXEXTRACT(A46, ""NPQ\[.*?\](\d+)"")"),"24929") -> 24929
A47: //Month2 //#W#City_Mumbai//PRD-HappyGrow//OPQ 12154/NPQ[IPLMARKETING]12884 | B47: =IFERROR(__xludf.DUMMYFUNCTION("REGEXEXTRACT(A47, ""Month\d+"")"),"Month2") -> Month2 | C47: =IFERROR(__xludf.DUMMYFUNCTION("REGEXEXTRACT(A47, ""#([A-Z])#"") "),"W") -> W | D47: =IFERROR(__xludf.DUMMYFUNCTION("REGEXEXTRACT(A47, ""City_([^/]+)"")"),"Mumbai") -> Mumbai | E47: =IFERROR(__xludf.DUMMYFUNCTION("REGEXEXTRACT(A47, ""PRD-([^/]+)"")"),"HappyGrow") -> HappyGrow | F47: =IFERROR(__xludf.DUMMYFUNCTION("REGEXEXTRACT(A47, ""OPQ\s+(\d+)"")"),"12154") -> 12154 | G47: =IFERROR(__xludf.DUMMYFUNCTION("REGEXEXTRACT(A47, ""NPQ\[.*?\](\d+)"")"),"12884") -> 12884
A48: //Month2 //#S#City_Mumbai//PRD-PowerSip//OPQ 13268/NPQ[IPLMARKETING]15391 | B48: =IFERROR(__xludf.DUMMYFUNCTION("REGEXEXTRACT(A48, ""Month\d+"")"),"Month2") -> Month2 | C48: =IFERROR(__xludf.DUMMYFUNCTION("REGEXEXTRACT(A48, ""#([A-Z])#"") "),"S") -> S | D48: =IFERROR(__xludf.DUMMYFUNCTION("REGEXEXTRACT(A48, ""City_([^/]+)"")"),"Mumbai") -> Mumbai | E48: =IFERROR(__xludf.DUMMYFUNCTION("REGEXEXTRACT(A48, ""PRD-([^/]+)"")"),"PowerSip") -> PowerSip | F48: =IFERROR(__xludf.DUMMYFUNCTION("REGEXEXTRACT(A48, ""OPQ\s+(\d+)"")"),"13268") -> 13268 | G48: =IFERROR(__xludf.DUMMYFUNCTION("REGEXEXTRACT(A48, ""NPQ\[.*?\](\d+)"")"),"15391") -> 15391
A49: //Month2 //#S#City_Mumbai//PRD-HappyGrow//OPQ 14530/NPQ[IPLMARKETING]15548 | B49: =IFERROR(__xludf.DUMMYFUNCTION("REGEXEXTRACT(A49, ""Month\d+"")"),"Month2") -> Month2 | C49: =IFERROR(__xludf.DUMMYFUNCTION("REGEXEXTRACT(A49, ""#([A-Z])#"") "),"S") -> S | D49: =IFERROR(__xludf.DUMMYFUNCTION("REGEXEXTRACT(A49, ""City_([^/]+)"")"),"Mumbai") -> Mumbai | E49: =IFERROR(__xludf.DUMMYFUNCTION("REGEXEXTRACT(A49, ""PRD-([^/]+)"")"),"HappyGrow") -> HappyGrow | F49: =IFERROR(__xludf.DUMMYFUNCTION("REGEXEXTRACT(A49, ""OPQ\s+(\d+)"")"),"14530") -> 14530 | G49: =IFERROR(__xludf.DUMMYFUNCTION("REGEXEXTRACT(A49, ""NPQ\[.*?\](\d+)"")"),"15548") -> 15548
A50: //Month2 //#N#City_Bengaluru//PRD-PowerSip//OPQ 23403/NPQ[IPLMARKETING]27382 | B50: =IFERROR(__xludf.DUMMYFUNCTION("REGEXEXTRACT(A50, ""Month\d+"")"),"Month2") -> Month2 | C50: =IFERROR(__xludf.DUMMYFUNCTION("REGEXEXTRACT(A50, ""#([A-Z])#"") "),"N") -> N | D50: =IFERROR(__xludf.DUMMYFUNCTION("REGEXEXTRACT(A50, ""City_([^/]+)"")"),"Bengaluru") -> Bengaluru | E50: =IFERROR(__xludf.DUMMYFUNCTION("REGEXEXTRACT(A50, ""PRD-([^/]+)"")"),"PowerSip") -> PowerSip | F50: =IFERROR(__xludf.DUMMYFUNCTION("REGEXEXTRACT(A50, ""OPQ\s+(\d+)"")"),"23403") -> 23403 | G50: =IFERROR(__xludf.DUMMYFUNCTION("REGEXEXTRACT(A50, ""NPQ\[.*?\](\d+)"")"),"27382") -> 27382
A51: //Month2 //#N#City_Bengaluru//PRD-HappyGrow//OPQ 19914/NPQ[IPLMARKETING]21308 | B51: =IFERROR(__xludf.DUMMYFUNCTION("REGEXEXTRACT(A51, ""Month\d+"")"),"Month2") -> Month2 | C51: =IFERROR(__xludf.DUMMYFUNCTION("REGEXEXTRACT(A51, ""#([A-Z])#"") "),"N") -> N | D51: =IFERROR(__xludf.DUMMYFUNCTION("REGEXEXTRACT(A51, ""City_([^/]+)"")"),"Bengaluru") -> Bengaluru | E51: =IFERROR(__xludf.DUMMYFUNCTION("REGEXEXTRACT(A51, ""PRD-([^/]+)"")"),"HappyGrow") -> HappyGrow | F51: =IFERROR(__xludf.DUMMYFUNCTION("REGEXEXTRACT(A51, ""OPQ\s+(\d+)"")"),"19914") -> 19914 | G51: =IFERROR(__xludf.DUMMYFUNCTION("REGEXEXTRACT(A51, ""NPQ\[.*?\](\d+)"")"),"21308") -> 21308
A52: //Month2 //#E#City_Bengaluru//PRD-PowerSip//OPQ 26455/NPQ[IPLMARKETING]30953 | B52: =IFERROR(__xludf.DUMMYFUNCTION("REGEXEXTRACT(A52, ""Month\d+"")"),"Month2") -> Month2 | C52: =IFERROR(__xludf.DUMMYFUNCTION("REGEXEXTRACT(A52, ""#([A-Z])#"") "),"E") -> E | D52: =IFERROR(__xludf.DUMMYFUNCTION("REGEXEXTRACT(A52, ""City_([^/]+)"")"),"Bengaluru") -> Bengaluru | E52: =IFERROR(__xludf.DUMMYFUNCTION("REGEXEXTRACT(A52, ""PRD-([^/]+)"")"),"PowerSip") -> PowerSip | F52: =IFERROR(__xludf.DUMMYFUNCTION("REGEXEXTRACT(A52, ""OPQ\s+(\d+)"")"),"26455") -> 26455 | G52: =IFERROR(__xludf.DUMMYFUNCTION("REGEXEXTRACT(A52, ""NPQ\[.*?\](\d+)"")"),"30953") -> 30953
A53: //Month2 //#E#City_Bengaluru//PRD-HappyGrow//OPQ 16192/NPQ[IPLMARKETING]17326 | B53: =IFERROR(__xludf.DUMMYFUNCTION("REGEXEXTRACT(A53, ""Month\d+"")"),"Month2") -> Month2 | C53: =IFERROR(__xludf.DUMMYFUNCTION("REGEXEXTRACT(A53, ""#([A-Z])#"") "),"E") -> E | D53: =IFERROR(__xludf.DUMMYFUNCTION("REGEXEXTRACT(A53, ""City_([^/]+)"")"),"Bengaluru") -> Bengaluru | E53: =IFERROR(__xludf.DUMMYFUNCTION("REGEXEXTRACT(A53, ""PRD-([^/]+)"")"),"HappyGrow") -> HappyGrow | F53: =IFERROR(__xludf.DUMMYFUNCTION("REGEXEXTRACT(A53, ""OPQ\s+(\d+)"")"),"16192") -> 16192 | G53: =IFERROR(__xludf.DUMMYFUNCTION("REGEXEXTRACT(A53, ""NPQ\[.*?\](\d+)"")"),"17326") -> 17326
A54: //Month2 //#W#City_Bengaluru//PRD-PowerSip//OPQ 19617/NPQ[IPLMARKETING]22952 | B54: =IFERROR(__xludf.DUMMYFUNCTION("REGEXEXTRACT(A54, ""Month\d+"")"),"Month2") -> Month2 | C54: =IFERROR(__xludf.DUMMYFUNCTION("REGEXEXTRACT(A54, ""#([A-Z])#"") "),"W") -> W | D54: =IFERROR(__xludf.DUMMYFUNCTION("REGEXEXTRACT(A54, ""City_([^/]+)"")"),"Bengaluru") -> Bengaluru | E54: =IFERROR(__xludf.DUMMYFUNCTION("REGEXEXTRACT(A54, ""PRD-([^/]+)"")"),"PowerSip") -> PowerSip | F54: =IFERROR(__xludf.DUMMYFUNCTION("REGEXEXTRACT(A54, ""OPQ\s+(\d+)"")"),"19617") -> 19617 | G54: =IFERROR(__xludf.DUMMYFUNCTION("REGEXEXTRACT(A54, ""NPQ\[.*?\](\d+)"")"),"22952") -> 22952
A55: //Month2 //#W#City_Bengaluru//PRD-HappyGrow//OPQ 15084/NPQ[IPLMARKETING]16140 | B55: =IFERROR(__xludf.DUMMYFUNCTION("REGEXEXTRACT(A55, ""Month\d+"")"),"Month2") -> Month2 | C55: =IFERROR(__xludf.DUMMYFUNCTION("REGEXEXTRACT(A55, ""#([A-Z])#"") "),"W") -> W | D55: =IFERROR(__xludf.DUMMYFUNCTION("REGEXEXTRACT(A55, ""City_([^/]+)"")"),"Bengaluru") -> Bengaluru | E55: =IFERROR(__xludf.DUMMYFUNCTION("REGEXEXTRACT(A55, ""PRD-([^/]+)"")"),"HappyGrow") -> HappyGrow | F55: =IFERROR(__xludf.DUMMYFUNCTION("REGEXEXTRACT(A55, ""OPQ\s+(\d+)"")"),"15084") -> 15084 | G55: =IFERROR(__xludf.DUMMYFUNCTION("REGEXEXTRACT(A55, ""NPQ\[.*?\](\d+)"")"),"16140") -> 16140
A56: //Month2 //#S#City_Bengaluru//PRD-PowerSip//OPQ 27106/NPQ[IPLMARKETING]31715 | B56: =IFERROR(__xludf.DUMMYFUNCTION("REGEXEXTRACT(A56, ""Month\d+"")"),"Month2") -> Month2 | C56: =IFERROR(__xludf.DUMMYFUNCTION("REGEXEXTRACT(A56, ""#([A-Z])#"") "),"S") -> S | D56: =IFERROR(__xludf.DUMMYFUNCTION("REGEXEXTRACT(A56, ""City_([^/]+)"")"),"Bengaluru") -> Bengaluru | E56: =IFERROR(__xludf.DUMMYFUNCTION("REGEXEXTRACT(A56, ""PRD-([^/]+)"")"),"PowerSip") -> PowerSip | F56: =IFERROR(__xludf.DUMMYFUNCTION("REGEXEXTRACT(A56, ""OPQ\s+(\d+)"")"),"27106") -> 27106 | G56: =IFERROR(__xludf.DUMMYFUNCTION("REGEXEXTRACT(A56, ""NPQ\[.*?\](\d+)"")"),"31715") -> 31715
A57: //Month2 //#S#City_Bengaluru//PRD-HappyGrow//OPQ 26604/NPQ[IPLMARKETING]28467 | B57: =IFERROR(__xludf.DUMMYFUNCTION("REGEXEXTRACT(A57, ""Month\d+"")"),"Month2") -> Month2 | C57: =IFERROR(__xludf.DUMMYFUNCTION("REGEXEXTRACT(A57, ""#([A-Z])#"") "),"S") -> S | D57: =IFERROR(__xludf.DUMMYFUNCTION("REGEXEXTRACT(A57, ""City_([^/]+)"")"),"Bengaluru") -> Bengaluru | E57: =IFERROR(__xludf.DUMMYFUNCTION("REGEXEXTRACT(A57, ""PRD-([^/]+)"")"),"HappyGrow") -> HappyGrow | F57: =IFERROR(__xludf.DUMMYFUNCTION("REGEXEXTRACT(A57, ""OPQ\s+(\d+)"")"),"26604") -> 26604 | G57: =IFERROR(__xludf.DUMMYFUNCTION("REGEXEXTRACT(A57, ""NPQ\[.*?\](\d+)"")"),"28467") -> 28467
A58: //Month2 //#N#City_Delhi//PRD-PowerSip//OPQ 21815/NPQ[IPLMARKETING]25524 | B58: =IFERROR(__xludf.DUMMYFUNCTION("REGEXEXTRACT(A58, ""Month\d+"")"),"Month2") -> Month2 | C58: =IFERROR(__xludf.DUMMYFUNCTION("REGEXEXTRACT(A58, ""#([A-Z])#"") "),"N") -> N | D58: =IFERROR(__xludf.DUMMYFUNCTION("REGEXEXTRACT(A58, ""City_([^/]+)"")"),"Delhi") -> Delhi | E58: =IFERROR(__xludf.DUMMYFUNCTION("REGEXEXTRACT(A58, ""PRD-([^/]+)"")"),"PowerSip") -> PowerSip | F58: =IFERROR(__xludf.DUMMYFUNCTION("REGEXEXTRACT(A58, ""OPQ\s+(\d+)"")"),"21815") -> 21815 | G58: =IFERROR(__xludf.DUMMYFUNCTION("REGEXEXTRACT(A58, ""NPQ\[.*?\](\d+)"")"),"25524") -> 25524
A59: //Month2 //#N#City_Delhi//PRD-HappyGrow//OPQ 13183/NPQ[IPLMARKETING]14238 | B59: =IFERROR(__xludf.DUMMYFUNCTION("REGEXEXTRACT(A59, ""Month\d+"")"),"Month2") -> Month2 | C59: =IFERROR(__xludf.DUMMYFUNCTION("REGEXEXTRACT(A59, ""#([A-Z])#"") "),"N") -> N | D59: =IFERROR(__xludf.DUMMYFUNCTION("REGEXEXTRACT(A59, ""City_([^/]+)"")"),"Delhi") -> Delhi | E59: =IFERROR(__xludf.DUMMYFUNCTION("REGEXEXTRACT(A59, ""PRD-([^/]+)"")"),"HappyGrow") -> HappyGrow | F59: =IFERROR(__xludf.DUMMYFUNCTION("REGEXEXTRACT(A59, ""OPQ\s+(\d+)"")"),"13183") -> 13183 | G59: =IFERROR(__xludf.DUMMYFUNCTION("REGEXEXTRACT(A59, ""NPQ\[.*?\](\d+)"")"),"14238") -> 14238
A60: //Month2 //#E#City_Delhi//PRD-PowerSip//OPQ 23728/NPQ[IPLMARKETING]27762 | B60: =IFERROR(__xludf.DUMMYFUNCTION("REGEXEXTRACT(A60, ""Month\d+"")"),"Month2") -> Month2 | C60: =IFERROR(__xludf.DUMMYFUNCTION("REGEXEXTRACT(A60, ""#([A-Z])#"") "),"E") -> E | D60: =IFERROR(__xludf.DUMMYFUNCTION("REGEXEXTRACT(A60, ""City_([^/]+)"")"),"Delhi") -> Delhi | E60: =IFERROR(__xludf.DUMMYFUNCTION("REGEXEXTRACT(A60, ""PRD-([^/]+)"")"),"PowerSip") -> PowerSip | F60: =IFERROR(__xludf.DUMMYFUNCTION("REGEXEXTRACT(A60, ""OPQ\s+(\d+)"")"),"23728") -> 23728 | G60: =IFERROR(__xludf.DUMMYFUNCTION("REGEXEXTRACT(A60, ""NPQ\[.*?\](\d+)"")"),"27762") -> 27762
A61: //Month2 //#E#City_Delhi//PRD-HappyGrow//OPQ 14252/NPQ[IPLMARKETING]15393 | B61: =IFERROR(__xludf.DUMMYFUNCTION("REGEXEXTRACT(A61, ""Month\d+"")"),"Month2") -> Month2 | C61: =IFERROR(__xludf.DUMMYFUNCTION("REGEXEXTRACT(A61, ""#([A-Z])#"") "),"E") -> E | D61: =IFERROR(__xludf.DUMMYFUNCTION("REGEXEXTRACT(A61, ""City_([^/]+)"")"),"Delhi") -> Delhi | E61: =IFERROR(__xludf.DUMMYFUNCTION("REGEXEXTRACT(A61, ""PRD-([^/]+)"")"),"HappyGrow") -> HappyGrow | F61: =IFERROR(__xludf.DUMMYFUNCTION("REGEXEXTRACT(A61, ""OPQ\s+(\d+)"")"),"14252") -> 14252 | G61: =IFERROR(__xludf.DUMMYFUNCTION("REGEXEXTRACT(A61, ""NPQ\[.*?\](\d+)"")"),"15393") -> 15393
A62: //Month2 //#W#City_Delhi//PRD-PowerSip//OPQ 22100/NPQ[IPLMARKETING]26078 | B62: =IFERROR(__xludf.DUMMYFUNCTION("REGEXEXTRACT(A62, ""Month\d+"")"),"Month2") -> Month2 | C62: =IFERROR(__xludf.DUMMYFUNCTION("REGEXEXTRACT(A62, ""#([A-Z])#"") "),"W") -> W | D62: =IFERROR(__xludf.DUMMYFUNCTION("REGEXEXTRACT(A62, ""City_([^/]+)"")"),"Delhi") -> Delhi | E62: =IFERROR(__xludf.DUMMYFUNCTION("REGEXEXTRACT(A62, ""PRD-([^/]+)"")"),"PowerSip") -> PowerSip | F62: =IFERROR(__xludf.DUMMYFUNCTION("REGEXEXTRACT(A62, ""OPQ\s+(\d+)"")"),"22100") -> 22100 | G62: =IFERROR(__xludf.DUMMYFUNCTION("REGEXEXTRACT(A62, ""NPQ\[.*?\](\d+)"")"),"26078") -> 26078
A63: //Month2 //#W#City_Delhi//PRD-HappyGrow//OPQ 16311/NPQ[IPLMARKETING]17616 | B63: =IFERROR(__xludf.DUMMYFUNCTION("REGEXEXTRACT(A63, ""Month\d+"")"),"Month2") -> Month2 | C63: =IFERROR(__xludf.DUMMYFUNCTION("REGEXEXTRACT(A63, ""#([A-Z])#"") "),"W") -> W | D63: =IFERROR(__xludf.DUMMYFUNCTION("REGEXEXTRACT(A63, ""City_([^/]+)"")"),"Delhi") -> Delhi | E63: =IFERROR(__xludf.DUMMYFUNCTION("REGEXEXTRACT(A63, ""PRD-([^/]+)"")"),"HappyGrow") -> HappyGrow | F63: =IFERROR(__xludf.DUMMYFUNCTION("REGEXEXTRACT(A63, ""OPQ\s+(\d+)"")"),"16311") -> 16311 | G63: =IFERROR(__xludf.DUMMYFUNCTION("REGEXEXTRACT(A63, ""NPQ\[.*?\](\d+)"")"),"17616") -> 17616
A64: //Month2 //#S#City_Delhi//PRD-PowerSip//OPQ 19048/NPQ[IPLMARKETING]22477 | B64: =IFERROR(__xludf.DUMMYFUNCTION("REGEXEXTRACT(A64, ""Month\d+"")"),"Month2") -> Month2 | C64: =IFERROR(__xludf.DUMMYFUNCTION("REGEXEXTRACT(A64, ""#([A-Z])#"") "),"S") -> S | D64: =IFERROR(__xludf.DUMMYFUNCTION("REGEXEXTRACT(A64, ""City_([^/]+)"")"),"Delhi") -> Delhi | E64: =IFERROR(__xludf.DUMMYFUNCTION("REGEXEXTRACT(A64, ""PRD-([^/]+)"")"),"PowerSip") -> PowerSip | F64: =IFERROR(__xludf.DUMMYFUNCTION("REGEXEXTRACT(A64, ""OPQ\s+(\d+)"")"),"19048") -> 19048 | G64: =IFERROR(__xludf.DUMMYFUNCTION("REGEXEXTRACT(A64, ""NPQ\[.*?\](\d+)"")"),"22477") -> 22477
A65: //Month2 //#S#City_Delhi//PRD-HappyGrow//OPQ 24467/NPQ[IPLMARKETING]26425 | B65: =IFERROR(__xludf.DUMMYFUNCTION("REGEXEXTRACT(A65, ""Month\d+"")"),"Month2") -> Month2 | C65: =IFERROR(__xludf.DUMMYFUNCTION("REGEXEXTRACT(A65, ""#([A-Z])#"") "),"S") -> S | D65: =IFERROR(__xludf.DUMMYFUNCTION("REGEXEXTRACT(A65, ""City_([^/]+)"")"),"Delhi") -> Delhi | E65: =IFERROR(__xludf.DUMMYFUNCTION("REGEXEXTRACT(A65, ""PRD-([^/]+)"")"),"HappyGrow") -> HappyGrow | F65: =IFERROR(__xludf.DUMMYFUNCTION("REGEXEXTRACT(A65, ""OPQ\s+(\d+)"")"),"24467") -> 24467 | G65: =IFERROR(__xludf.DUMMYFUNCTION("REGEXEXTRACT(A65, ""NPQ\[.*?\](\d+)"")"),"26425") -> 26425
A66: //Month3 //#N#City_Chennai//PRD-PowerSip//OPQ 26012/NPQ[IPLMARKETING]30695 | B66: =IFERROR(__xludf.DUMMYFUNCTION("REGEXEXTRACT(A66, ""Month\d+"")"),"Month3") -> Month3 | C66: =IFERROR(__xludf.DUMMYFUNCTION("REGEXEXTRACT(A66, ""#([A-Z])#"") "),"N") -> N | D66: =IFERROR(__xludf.DUMMYFUNCTION("REGEXEXTRACT(A66, ""City_([^/]+)"")"),"Chennai") -> Chennai | E66: =IFERROR(__xludf.DUMMYFUNCTION("REGEXEXTRACT(A66, ""PRD-([^/]+)"")"),"PowerSip") -> PowerSip | F66: =IFERROR(__xludf.DUMMYFUNCTION("REGEXEXTRACT(A66, ""OPQ\s+(\d+)"")"),"26012") -> 26012 | G66: =IFERROR(__xludf.DUMMYFUNCTION("REGEXEXTRACT(A66, ""NPQ\[.*?\](\d+)"")"),"30695") -> 30695
A67: //Month3 //#N#City_Chennai//PRD-HappyGrow//OPQ 19063/NPQ[IPLMARKETING]20589 | B67: =IFERROR(__xludf.DUMMYFUNCTION("REGEXEXTRACT(A67, ""Month\d+"")"),"Month3") -> Month3 | C67: =IFERROR(__xludf.DUMMYFUNCTION("REGEXEXTRACT(A67, ""#([A-Z])#"") "),"N") -> N | D67: =IFERROR(__xludf.DUMMYFUNCTION("REGEXEXTRACT(A67, ""City_([^/]+)"")"),"Chennai") -> Chennai | E67: =IFERROR(__xludf.DUMMYFUNCTION("REGEXEXTRACT(A67, ""PRD-([^/]+)"")"),"HappyGrow") -> HappyGrow | F67: =IFERROR(__xludf.DUMMYFUNCTION("REGEXEXTRACT(A67, ""OPQ\s+(\d+)"")"),"19063") -> 19063 | G67: =IFERROR(__xludf.DUMMYFUNCTION("REGEXEXTRACT(A67, ""NPQ\[.*?\](\d+)"")"),"20589") -> 20589
A68: //Month3 //#E#City_Chennai//PRD-PowerSip//OPQ 13879/NPQ[IPLMARKETING]16378 | B68: =IFERROR(__xludf.DUMMYFUNCTION("REGEXEXTRACT(A68, ""Month\d+"")"),"Month3") -> Month3 | C68: =IFERROR(__xludf.DUMMYFUNCTION("REGEXEXTRACT(A68, ""#([A-Z])#"") "),"E") -> E | D68: =IFERROR(__xludf.DUMMYFUNCTION("REGEXEXTRACT(A68, ""City_([^/]+)"")"),"Chennai") -> Chennai | E68: =IFERROR(__xludf.DUMMYFUNCTION("REGEXEXTRACT(A68, ""PRD-([^/]+)"")"),"PowerSip") -> PowerSip | F68: =IFERROR(__xludf.DUMMYFUNCTION("REGEXEXTRACT(A68, ""OPQ\s+(\d+)"")"),"13879") -> 13879 | G68: =IFERROR(__xludf.DUMMYFUNCTION("REGEXEXTRACT(A68, ""NPQ\[.*?\](\d+)"")"),"16378") -> 16378
A69: //Month3 //#E#City_Chennai//PRD-HappyGrow//OPQ 25586/NPQ[IPLMARKETING]27889 | B69: =IFERROR(__xludf.DUMMYFUNCTION("REGEXEXTRACT(A69, ""Month\d+"")"),"Month3") -> Month3 | C69: =IFERROR(__xludf.DUMMYFUNCTION("REGEXEXTRACT(A69, ""#([A-Z])#"") "),"E") -> E | D69: =IFERROR(__xludf.DUMMYFUNCTION("REGEXEXTRACT(A69, ""City_([^/]+)"")"),"Chennai") -> Chennai | E69: =IFERROR(__xludf.DUMMYFUNCTION("REGEXEXTRACT(A69, ""PRD-([^/]+)"")"),"HappyGrow") -> HappyGrow | F69: =IFERROR(__xludf.DUMMYFUNCTION("REGEXEXTRACT(A69, ""OPQ\s+(\d+)"")"),"25586") -> 25586 | G69: =IFERROR(__xludf.DUMMYFUNCTION("REGEXEXTRACT(A69, ""NPQ\[.*?\](\d+)"")"),"27889") -> 27889
A70: //Month3 //#W#City_Chennai//PRD-PowerSip//OPQ 16610/NPQ[IPLMARKETING]19600 | B70: =IFERROR(__xludf.DUMMYFUNCTION("REGEXEXTRACT(A70, ""Month\d+"")"),"Month3") -> Month3 | C70: =IFERROR(__xludf.DUMMYFUNCTION("REGEXEXTRACT(A70, ""#([A-Z])#"") "),"W") -> W | D70: =IFERROR(__xludf.DUMMYFUNCTION("REGEXEXTRACT(A70, ""City_([^/]+)"")"),"Chennai") -> Chennai | E70: =IFERROR(__xludf.DUMMYFUNCTION("REGEXEXTRACT(A70, ""PRD-([^/]+)"")"),"PowerSip") -> PowerSip | F70: =IFERROR(__xludf.DUMMYFUNCTION("REGEXEXTRACT(A70, ""OPQ\s+(\d+)"")"),"16610") -> 16610 | G70: =IFERROR(__xludf.DUMMYFUNCTION("REGEXEXTRACT(A70, ""NPQ\[.*?\](\d+)"")"),"19600") -> 19600
A71: //Month3 //#W#City_Chennai//PRD-HappyGrow//OPQ 18088/NPQ[IPLMARKETING]19716 | B71: =IFERROR(__xludf.DUMMYFUNCTION("REGEXEXTRACT(A71, ""Month\d+"")"),"Month3") -> Month3 | C71: =IFERROR(__xludf.DUMMYFUNCTION("REGEXEXTRACT(A71, ""#([A-Z])#"") "),"W") -> W | D71: =IFERROR(__xludf.DUMMYFUNCTION("REGEXEXTRACT(A71, ""City_([^/]+)"")"),"Chennai") -> Chennai | E71: =IFERROR(__xludf.DUMMYFUNCTION("REGEXEXTRACT(A71, ""PRD-([^/]+)"")"),"HappyGrow") -> HappyGrow | F71: =IFERROR(__xludf.DUMMYFUNCTION("REGEXEXTRACT(A71, ""OPQ\s+(\d+)"")"),"18088") -> 18088 | G71: =IFERROR(__xludf.DUMMYFUNCTION("REGEXEXTRACT(A71, ""NPQ\[.*?\](\d+)"")"),"19716") -> 19716
A72: //Month3 //#S#City_Chennai//PRD-PowerSip//OPQ 30041/NPQ[IPLMARKETING]35449 | B72: =IFERROR(__xludf.DUMMYFUNCTION("REGEXEXTRACT(A72, ""Month\d+"")"),"Month3") -> Month3 | C72: =IFERROR(__xludf.DUMMYFUNCTION("REGEXEXTRACT(A72, ""#([A-Z])#"") "),"S") -> S | D72: =IFERROR(__xludf.DUMMYFUNCTION("REGEXEXTRACT(A72, ""City_([^/]+)"")"),"Chennai") -> Chennai | E72: =IFERROR(__xludf.DUMMYFUNCTION("REGEXEXTRACT(A72, ""PRD-([^/]+)"")"),"PowerSip") -> PowerSip | F72: =IFERROR(__xludf.DUMMYFUNCTION("REGEXEXTRACT(A72, ""OPQ\s+(\d+)"")"),"30041") -> 30041 | G72: =IFERROR(__xludf.DUMMYFUNCTION("REGEXEXTRACT(A72, ""NPQ\[.*?\](\d+)"")"),"35449") -> 35449
A73: //Month3 //#S#City_Chennai//PRD-HappyGrow//OPQ 15420/NPQ[IPLMARKETING]16808 | B73: =IFERROR(__xludf.DUMMYFUNCTION("REGEXEXTRACT(A73, ""Month\d+"")"),"Month3") -> Month3 | C73: =IFERROR(__xludf.DUMMYFUNCTION("REGEXEXTRACT(A73, ""#([A-Z])#"") "),"S") -> S | D73: =IFERROR(__xludf.DUMMYFUNCTION("REGEXEXTRACT(A73, ""City_([^/]+)"")"),"Chennai") -> Chennai | E73: =IFERROR(__xludf.DUMMYFUNCTION("REGEXEXTRACT(A73, ""PRD-([^/]+)"")"),"HappyGrow") -> HappyGrow | F73: =IFERROR(__xludf.DUMMYFUNCTION("REGEXEXTRACT(A73, ""OPQ\s+(\d+)"")"),"15420") -> 15420 | G73: =IFERROR(__xludf.DUMMYFUNCTION("REGEXEXTRACT(A73, ""NPQ\[.*?\](\d+)"")"),"16808") -> 16808
A74: //Month3 //#N#City_Mumbai//PRD-PowerSip//OPQ 26907/NPQ[IPLMARKETING]31751 | B74: =IFERROR(__xludf.DUMMYFUNCTION("REGEXEXTRACT(A74, ""Month\d+"")"),"Month3") -> Month3 | C74: =IFERROR(__xludf.DUMMYFUNCTION("REGEXEXTRACT(A74, ""#([A-Z])#"") "),"N") -> N | D74: =IFERROR(__xludf.DUMMYFUNCTION("REGEXEXTRACT(A74, ""City_([^/]+)"")"),"Mumbai") -> Mumbai | E74: =IFERROR(__xludf.DUMMYFUNCTION("REGEXEXTRACT(A74, ""PRD-([^/]+)"")"),"PowerSip") -> PowerSip | F74: =IFERROR(__xludf.DUMMYFUNCTION("REGEXEXTRACT(A74, ""OPQ\s+(\d+)"")"),"26907") -> 26907 | G74: =IFERROR(__xludf.DUMMYFUNCTION("REGEXEXTRACT(A74, ""NPQ\[.*?\](\d+)"")"),"31751") -> 31751
A75: //Month3 //#N#City_Mumbai//PRD-HappyGrow//OPQ 26814/NPQ[IPLMARKETING]29228 | B75: =IFERROR(__xludf.DUMMYFUNCTION("REGEXEXTRACT(A75, ""Month\d+"")"),"Month3") -> Month3 | C75: =IFERROR(__xludf.DUMMYFUNCTION("REGEXEXTRACT(A75, ""#([A-Z])#"") "),"N") -> N | D75: =IFERROR(__xludf.DUMMYFUNCTION("REGEXEXTRACT(A75, ""City_([^/]+)"")"),"Mumbai") -> Mumbai | E75: =IFERROR(__xludf.DUMMYFUNCTION("REGEXEXTRACT(A75, ""PRD-([^/]+)"")"),"HappyGrow") -> HappyGrow | F75: =IFERROR(__xludf.DUMMYFUNCTION("REGEXEXTRACT(A75, ""OPQ\s+(\d+)"")"),"26814") -> 26814 | G75: =IFERROR(__xludf.DUMMYFUNCTION("REGEXEXTRACT(A75, ""NPQ\[.*?\](\d+)"")"),"29228") -> 29228
A76: //Month3 //#E#City_Mumbai//PRD-PowerSip//OPQ 15088/NPQ[IPLMARKETING]17804 | B76: =IFERROR(__xludf.DUMMYFUNCTION("REGEXEXTRACT(A76, ""Month\d+"")"),"Month3") -> Month3 | C76: =IFERROR(__xludf.DUMMYFUNCTION("REGEXEXTRACT(A76, ""#([A-Z])#"") "),"E") -> E | D76: =IFERROR(__xludf.DUMMYFUNCTION("REGEXEXTRACT(A76, ""City_([^/]+)"")"),"Mumbai") -> Mumbai | E76: =IFERROR(__xludf.DUMMYFUNCTION("REGEXEXTRACT(A76, ""PRD-([^/]+)"")"),"PowerSip") -> PowerSip | F76: =IFERROR(__xludf.DUMMYFUNCTION("REGEXEXTRACT(A76, ""OPQ\s+(\d+)"")"),"15088") -> 15088 | G76: =IFERROR(__xludf.DUMMYFUNCTION("REGEXEXTRACT(A76, ""NPQ\[.*?\](\d+)"")"),"17804") -> 17804
A77: //Month3 //#E#City_Mumbai//PRD-HappyGrow//OPQ 18724/NPQ[IPLMARKETING]20410 | B77: =IFERROR(__xludf.DUMMYFUNCTION("REGEXEXTRACT(A77, ""Month\d+"")"),"Month3") -> Month3 | C77: =IFERROR(__xludf.DUMMYFUNCTION("REGEXEXTRACT(A77, ""#([A-Z])#"") "),"E") -> E | D77: =IFERROR(__xludf.DUMMYFUNCTION("REGEXEXTRACT(A77, ""City_([^/]+)"")"),"Mumbai") -> Mumbai | E77: =IFERROR(__xludf.DUMMYFUNCTION("REGEXEXTRACT(A77, ""PRD-([^/]+)"")"),"HappyGrow") -> HappyGrow | F77: =IFERROR(__xludf.DUMMYFUNCTION("REGEXEXTRACT(A77, ""OPQ\s+(\d+)"")"),"18724") -> 18724 | G77: =IFERROR(__xludf.DUMMYFUNCTION("REGEXEXTRACT(A77, ""NPQ\[.*?\](\d+)"")"),"20410") -> 20410
A78: //Month3 //#W#City_Mumbai//PRD-PowerSip//OPQ 23639/NPQ[IPLMARKETING]27895 | B78: =IFERROR(__xludf.DUMMYFUNCTION("REGEXEXTRACT(A78, ""Month\d+"")"),"Month3") -> Month3 | C78: =IFERROR(__xludf.DUMMYFUNCTION("REGEXEXTRACT(A78, ""#([A-Z])#"") "),"W") -> W | D78: =IFERROR(__xludf.DUMMYFUNCTION("REGEXEXTRACT(A78, ""City_([^/]+)"")"),"Mumbai") -> Mumbai | E78: =IFERROR(__xludf.DUMMYFUNCTION("REGEXEXTRACT(A78, ""PRD-([^/]+)"")"),"PowerSip") -> PowerSip | F78: =IFERROR(__xludf.DUMMYFUNCTION("REGEXEXTRACT(A78, ""OPQ\s+(\d+)"")"),"23639") -> 23639 | G78: =IFERROR(__xludf.DUMMYFUNCTION("REGEXEXTRACT(A78, ""NPQ\[.*?\](\d+)"")"),"27895") -> 27895
A79: //Month3 //#W#City_Mumbai//PRD-HappyGrow//OPQ 13005/NPQ[IPLMARKETING]14306 | B79: =IFERROR(__xludf.DUMMYFUNCTION("REGEXEXTRACT(A79, ""Month\d+"")"),"Month3") -> Month3 | C79: =IFERROR(__xludf.DUMMYFUNCTION("REGEXEXTRACT(A79, ""#([A-Z])#"") "),"W") -> W | D79: =IFERROR(__xludf.DUMMYFUNCTION("REGEXEXTRACT(A79, ""City_([^/]+)"")"),"Mumbai") -> Mumbai | E79: =IFERROR(__xludf.DUMMYFUNCTION("REGEXEXTRACT(A79, ""PRD-([^/]+)"")"),"HappyGrow") -> HappyGrow | F79: =IFERROR(__xludf.DUMMYFUNCTION("REGEXEXTRACT(A79, ""OPQ\s+(\d+)"")"),"13005") -> 13005 | G79: =IFERROR(__xludf.DUMMYFUNCTION("REGEXEXTRACT(A79, ""NPQ\[.*?\](\d+)"")"),"14306") -> 14306
A80: //Month3 //#S#City_Mumbai//PRD-PowerSip//OPQ 14595/NPQ[IPLMARKETING]17369 | B80: =IFERROR(__xludf.DUMMYFUNCTION("REGEXEXTRACT(A80, ""Month\d+"")"),"Month3") -> Month3 | C80: =IFERROR(__xludf.DUMMYFUNCTION("REGEXEXTRACT(A80, ""#([A-Z])#"") "),"S") -> S | D80: =IFERROR(__xludf.DUMMYFUNCTION("REGEXEXTRACT(A80, ""City_([^/]+)"")"),"Mumbai") -> Mumbai | E80: =IFERROR(__xludf.DUMMYFUNCTION("REGEXEXTRACT(A80, ""PRD-([^/]+)"")"),"PowerSip") -> PowerSip | F80: =IFERROR(__xludf.DUMMYFUNCTION("REGEXEXTRACT(A80, ""OPQ\s+(\d+)"")"),"14595") -> 14595 | G80: =IFERROR(__xludf.DUMMYFUNCTION("REGEXEXTRACT(A80, ""NPQ\[.*?\](\d+)"")"),"17369") -> 17369
A81: //Month3 //#S#City_Mumbai//PRD-HappyGrow//OPQ 15547/NPQ[IPLMARKETING]17258 | B81: =IFERROR(__xludf.DUMMYFUNCTION("REGEXEXTRACT(A81, ""Month\d+"")"),"Month3") -> Month3 | C81: =IFERROR(__xludf.DUMMYFUNCTION("REGEXEXTRACT(A81, ""#([A-Z])#"") "),"S") -> S | D81: =IFERROR(__xludf.DUMMYFUNCTION("REGEXEXTRACT(A81, ""City_([^/]+)"")"),"Mumbai") -> Mumbai | E81: =IFERROR(__xludf.DUMMYFUNCTION("REGEXEXTRACT(A81, ""PRD-([^/]+)"")"),"HappyGrow") -> HappyGrow | F81: =IFERROR(__xludf.DUMMYFUNCTION("REGEXEXTRACT(A81, ""OPQ\s+(\d+)"")"),"15547") -> 15547 | G81: =IFERROR(__xludf.DUMMYFUNCTION("REGEXEXTRACT(A81, ""NPQ\[.*?\](\d+)"")"),"17258") -> 17258
A82: //Month3 //#N#City_Bengaluru//PRD-PowerSip//OPQ 25743/NPQ[IPLMARKETING]30635 | B82: =IFERROR(__xludf.DUMMYFUNCTION("REGEXEXTRACT(A82, ""Month\d+"")"),"Month3") -> Month3 | C82: =IFERROR(__xludf.DUMMYFUNCTION("REGEXEXTRACT(A82, ""#([A-Z])#"") "),"N") -> N | D82: =IFERROR(__xludf.DUMMYFUNCTION("REGEXEXTRACT(A82, ""City_([^/]+)"")"),"Bengaluru") -> Bengaluru | E82: =IFERROR(__xludf.DUMMYFUNCTION("REGEXEXTRACT(A82, ""PRD-([^/]+)"")"),"PowerSip") -> PowerSip | F82: =IFERROR(__xludf.DUMMYFUNCTION("REGEXEXTRACT(A82, ""OPQ\s+(\d+)"")"),"25743") -> 25743 | G82: =IFERROR(__xludf.DUMMYFUNCTION("REGEXEXTRACT(A82, ""NPQ\[.*?\](\d+)"")"),"30635") -> 30635
A83: //Month3 //#N#City_Bengaluru//PRD-HappyGrow//OPQ 21308/NPQ[IPLMARKETING]23652 | B83: =IFERROR(__xludf.DUMMYFUNCTION("REGEXEXTRACT(A83, ""Month\d+"")"),"Month3") -> Month3 | C83: =IFERROR(__xludf.DUMMYFUNCTION("REGEXEXTRACT(A83, ""#([A-Z])#"") "),"N") -> N | D83: =IFERROR(__xludf.DUMMYFUNCTION("REGEXEXTRACT(A83, ""City_([^/]+)"")"),"Bengaluru") -> Bengaluru | E83: =IFERROR(__xludf.DUMMYFUNCTION("REGEXEXTRACT(A83, ""PRD-([^/]+)"")"),"HappyGrow") -> HappyGrow | F83: =IFERROR(__xludf.DUMMYFUNCTION("REGEXEXTRACT(A83, ""OPQ\s+(\d+)"")"),"21308") -> 21308 | G83: =IFERROR(__xludf.DUMMYFUNCTION("REGEXEXTRACT(A83, ""NPQ\[.*?\](\d+)"")"),"23652") -> 23652
A84: //Month3 //#E#City_Bengaluru//PRD-PowerSip//OPQ 29101/NPQ[IPLMARKETING]34631 | B84: =IFERROR(__xludf.DUMMYFUNCTION("REGEXEXTRACT(A84, ""Month\d+"")"),"Month3") -> Month3 | C84: =IFERROR(__xludf.DUMMYFUNCTION("REGEXEXTRACT(A84, ""#([A-Z])#"") "),"E") -> E | D84: =IFERROR(__xludf.DUMMYFUNCTION("REGEXEXTRACT(A84, ""City_([^/]+)"")"),"Bengaluru") -> Bengaluru | E84: =IFERROR(__xludf.DUMMYFUNCTION("REGEXEXTRACT(A84, ""PRD-([^/]+)"")"),"PowerSip") -> PowerSip | F84: =IFERROR(__xludf.DUMMYFUNCTION("REGEXEXTRACT(A84, ""OPQ\s+(\d+)"")"),"29101") -> 29101 | G84: =IFERROR(__xludf.DUMMYFUNCTION("REGEXEXTRACT(A84, ""NPQ\[.*?\](\d+)"")"),"34631") -> 34631
A85: //Month3 //#E#City_Bengaluru//PRD-HappyGrow//OPQ 17325/NPQ[IPLMARKETING]19231 | B85: =IFERROR(__xludf.DUMMYFUNCTION("REGEXEXTRACT(A85, ""Month\d+"")"),"Month3") -> Month3 | C85: =IFERROR(__xludf.DUMMYFUNCTION("REGEXEXTRACT(A85, ""#([A-Z])#"") "),"E") -> E | D85: =IFERROR(__xludf.DUMMYFUNCTION("REGEXEXTRACT(A85, ""City_([^/]+)"")"),"Bengaluru") -> Bengaluru | E85: =IFERROR(__xludf.DUMMYFUNCTION("REGEXEXTRACT(A85, ""PRD-([^/]+)"")"),"HappyGrow") -> HappyGrow | F85: =IFERROR(__xludf.DUMMYFUNCTION("REGEXEXTRACT(A85, ""OPQ\s+(\d+)"")"),"17325") -> 17325 | G85: =IFERROR(__xludf.DUMMYFUNCTION("REGEXEXTRACT(A85, ""NPQ\[.*?\](\d+)"")"),"19231") -> 19231
A86: //Month3 //#W#City_Bengaluru//PRD-PowerSip//OPQ 21579/NPQ[IPLMARKETING]25895 | B86: =IFERROR(__xludf.DUMMYFUNCTION("REGEXEXTRACT(A86, ""Month\d+"")"),"Month3") -> Month3 | C86: =IFERROR(__xludf.DUMMYFUNCTION("REGEXEXTRACT(A86, ""#([A-Z])#"") "),"W") -> W | D86: =IFERROR(__xludf.DUMMYFUNCTION("REGEXEXTRACT(A86, ""City_([^/]+)"")"),"Bengaluru") -> Bengaluru | E86: =IFERROR(__xludf.DUMMYFUNCTION("REGEXEXTRACT(A86, ""PRD-([^/]+)"")"),"PowerSip") -> PowerSip | F86: =IFERROR(__xludf.DUMMYFUNCTION("REGEXEXTRACT(A86, ""OPQ\s+(\d+)"")"),"21579") -> 21579 | G86: =IFERROR(__xludf.DUMMYFUNCTION("REGEXEXTRACT(A86, ""NPQ\[.*?\](\d+)"")"),"25895") -> 25895
A87: //Month3 //#W#City_Bengaluru//PRD-HappyGrow//OPQ 16140/NPQ[IPLMARKETING]17916 | B87: =IFERROR(__xludf.DUMMYFUNCTION("REGEXEXTRACT(A87, ""Month\d+"")"),"Month3") -> Month3 | C87: =IFERROR(__xludf.DUMMYFUNCTION("REGEXEXTRACT(A87, ""#([A-Z])#"") "),"W") -> W | D87: =IFERROR(__xludf.DUMMYFUNCTION("REGEXEXTRACT(A87, ""City_([^/]+)"")"),"Bengaluru") -> Bengaluru | E87: =IFERROR(__xludf.DUMMYFUNCTION("REGEXEXTRACT(A87, ""PRD-([^/]+)"")"),"HappyGrow") -> HappyGrow | F87: =IFERROR(__xludf.DUMMYFUNCTION("REGEXEXTRACT(A87, ""OPQ\s+(\d+)"")"),"16140") -> 16140 | G87: =IFERROR(__xludf.DUMMYFUNCTION("REGEXEXTRACT(A87, ""NPQ\[.*?\](\d+)"")"),"17916") -> 17916
A88: //Month3 //#S#City_Bengaluru//PRD-PowerSip//OPQ 29817/NPQ[IPLMARKETING]35781 | B88: =IFERROR(__xludf.DUMMYFUNCTION("REGEXEXTRACT(A88, ""Month\d+"")"),"Month3") -> Month3 | C88: =IFERROR(__xludf.DUMMYFUNCTION("REGEXEXTRACT(A88, ""#([A-Z])#"") "),"S") -> S | D88: =IFERROR(__xludf.DUMMYFUNCTION("REGEXEXTRACT(A88, ""City_([^/]+)"")"),"Bengaluru") -> Bengaluru | E88: =IFERROR(__xludf.DUMMYFUNCTION("REGEXEXTRACT(A88, ""PRD-([^/]+)"")"),"PowerSip") -> PowerSip | F88: =IFERROR(__xludf.DUMMYFUNCTION("REGEXEXTRACT(A88, ""OPQ\s+(\d+)"")"),"29817") -> 29817 | G88: =IFERROR(__xludf.DUMMYFUNCTION("REGEXEXTRACT(A88, ""NPQ\[.*?\](\d+)"")"),"35781") -> 35781
A89: //Month3 //#S#City_Bengaluru//PRD-HappyGrow//OPQ 28466/NPQ[IPLMARKETING]31598 | B89: =IFERROR(__xludf.DUMMYFUNCTION("REGEXEXTRACT(A89, ""Month\d+"")"),"Month3") -> Month3 | C89: =IFERROR(__xludf.DUMMYFUNCTION("REGEXEXTRACT(A89, ""#([A-Z])#"") "),"S") -> S | D89: =IFERROR(__xludf.DUMMYFUNCTION("REGEXEXTRACT(A89, ""City_([^/]+)"")"),"Bengaluru") -> Bengaluru | E89: =IFERROR(__xludf.DUMMYFUNCTION("REGEXEXTRACT(A89, ""PRD-([^/]+)"")"),"HappyGrow") -> HappyGrow | F89: =IFERROR(__xludf.DUMMYFUNCTION("REGEXEXTRACT(A89, ""OPQ\s+(\d+)"")"),"28466") -> 28466 | G89: =IFERROR(__xludf.DUMMYFUNCTION("REGEXEXTRACT(A89, ""NPQ\[.*?\](\d+)"")"),"31598") -> 31598
A90: //Month3 //#N#City_Delhi//PRD-PowerSip//OPQ 23997/NPQ[IPLMARKETING]28797 | B90: =IFERROR(__xludf.DUMMYFUNCTION("REGEXEXTRACT(A90, ""Month\d+"")"),"Month3") -> Month3 | C90: =IFERROR(__xludf.DUMMYFUNCTION("REGEXEXTRACT(A90, ""#([A-Z])#"") "),"N") -> N | D90: =IFERROR(__xludf.DUMMYFUNCTION("REGEXEXTRACT(A90, ""City_([^/]+)"")"),"Delhi") -> Delhi | E90: =IFERROR(__xludf.DUMMYFUNCTION("REGEXEXTRACT(A90, ""PRD-([^/]+)"")"),"PowerSip") -> PowerSip | F90: =IFERROR(__xludf.DUMMYFUNCTION("REGEXEXTRACT(A90, ""OPQ\s+(\d+)"")"),"23997") -> 23997 | G90: =IFERROR(__xludf.DUMMYFUNCTION("REGEXEXTRACT(A90, ""NPQ\[.*?\](\d+)"")"),"28797") -> 28797
A91: //Month3 //#N#City_Delhi//PRD-HappyGrow//OPQ 14106/NPQ[IPLMARKETING]15799 | B91: =IFERROR(__xludf.DUMMYFUNCTION("REGEXEXTRACT(A91, ""Month\d+"")"),"Month3") -> Month3 | C91: =IFERROR(__xludf.DUMMYFUNCTION("REGEXEXTRACT(A91, ""#([A-Z])#"") "),"N") -> N | D91: =IFERROR(__xludf.DUMMYFUNCTION("REGEXEXTRACT(A91, ""City_([^/]+)"")"),"Delhi") -> Delhi | E91: =IFERROR(__xludf.DUMMYFUNCTION("REGEXEXTRACT(A91, ""PRD-([^/]+)"")"),"HappyGrow") -> HappyGrow | F91: =IFERROR(__xludf.DUMMYFUNCTION("REGEXEXTRACT(A91, ""OPQ\s+(\d+)"")"),"14106") -> 14106 | G91: =IFERROR(__xludf.DUMMYFUNCTION("REGEXEXTRACT(A91, ""NPQ\[.*?\](\d+)"")"),"15799") -> 15799
A92: //Month3 //#E#City_Delhi//PRD-PowerSip//OPQ 26101/NPQ[IPLMARKETING]31583 | B92: =IFERROR(__xludf.DUMMYFUNCTION("REGEXEXTRACT(A92, ""Month\d+"")"),"Month3") -> Month3 | C92: =IFERROR(__xludf.DUMMYFUNCTION("REGEXEXTRACT(A92, ""#([A-Z])#"") "),"E") -> E | D92: =IFERROR(__xludf.DUMMYFUNCTION("REGEXEXTRACT(A92, ""City_([^/]+)"")"),"Delhi") -> Delhi | E92: =IFERROR(__xludf.DUMMYFUNCTION("REGEXEXTRACT(A92, ""PRD-([^/]+)"")"),"PowerSip") -> PowerSip | F92: =IFERROR(__xludf.DUMMYFUNCTION("REGEXEXTRACT(A92, ""OPQ\s+(\d+)"")"),"26101") -> 26101 | G92: =IFERROR(__xludf.DUMMYFUNCTION("REGEXEXTRACT(A92, ""NPQ\[.*?\](\d+)"")"),"31583") -> 31583
A93: //Month3 //#E#City_Delhi//PRD-HappyGrow//OPQ 15250/NPQ[IPLMARKETING]17080 | B93: =IFERROR(__xludf.DUMMYFUNCTION("REGEXEXTRACT(A93, ""Month\d+"")"),"Month3") -> Month3 | C93: =IFERROR(__xludf.DUMMYFUNCTION("REGEXEXTRACT(A93, ""#([A-Z])#"") "),"E") -> E | D93: =IFERROR(__xludf.DUMMYFUNCTION("REGEXEXTRACT(A93, ""City_([^/]+)"")"),"Delhi") -> Delhi | E93: =IFERROR(__xludf.DUMMYFUNCTION("REGEXEXTRACT(A93, ""PRD-([^/]+)"")"),"HappyGrow") -> HappyGrow | F93: =IFERROR(__xludf.DUMMYFUNCTION("REGEXEXTRACT(A93, ""OPQ\s+(\d+)"")"),"15250") -> 15250 | G93: =IFERROR(__xludf.DUMMYFUNCTION("REGEXEXTRACT(A93, ""NPQ\[.*?\](\d+)"")"),"17080") -> 17080
A94: //Month3 //#W#City_Delhi//PRD-PowerSip//OPQ 24310/NPQ[IPLMARKETING]29416 | B94: =IFERROR(__xludf.DUMMYFUNCTION("REGEXEXTRACT(A94, ""Month\d+"")"),"Month3") -> Month3 | C94: =IFERROR(__xludf.DUMMYFUNCTION("REGEXEXTRACT(A94, ""#([A-Z])#"") "),"W") -> W | D94: =IFERROR(__xludf.DUMMYFUNCTION("REGEXEXTRACT(A94, ""City_([^/]+)"")"),"Delhi") -> Delhi | E94: =IFERROR(__xludf.DUMMYFUNCTION("REGEXEXTRACT(A94, ""PRD-([^/]+)"")"),"PowerSip") -> PowerSip | F94: =IFERROR(__xludf.DUMMYFUNCTION("REGEXEXTRACT(A94, ""OPQ\s+(\d+)"")"),"24310") -> 24310 | G94: =IFERROR(__xludf.DUMMYFUNCTION("REGEXEXTRACT(A94, ""NPQ\[.*?\](\d+)"")"),"29416") -> 29416
A95: //Month3 //#W#City_Delhi//PRD-HappyGrow//OPQ 17453/NPQ[IPLMARKETING]19548 | B95: =IFERROR(__xludf.DUMMYFUNCTION("REGEXEXTRACT(A95, ""Month\d+"")"),"Month3") -> Month3 | C95: =IFERROR(__xludf.DUMMYFUNCTION("REGEXEXTRACT(A95, ""#([A-Z])#"") "),"W") -> W | D95: =IFERROR(__xludf.DUMMYFUNCTION("REGEXEXTRACT(A95, ""City_([^/]+)"")"),"Delhi") -> Delhi | E95: =IFERROR(__xludf.DUMMYFUNCTION("REGEXEXTRACT(A95, ""PRD-([^/]+)"")"),"HappyGrow") -> HappyGrow | F95: =IFERROR(__xludf.DUMMYFUNCTION("REGEXEXTRACT(A95, ""OPQ\s+(\d+)"")"),"17453") -> 17453 | G95: =IFERROR(__xludf.DUMMYFUNCTION("REGEXEXTRACT(A95, ""NPQ\[.*?\](\d+)"")"),"19548") -> 19548
A96: //Month3 //#S#City_Delhi//PRD-PowerSip//OPQ 20953/NPQ[IPLMARKETING]25354 | B96: =IFERROR(__xludf.DUMMYFUNCTION("REGEXEXTRACT(A96, ""Month\d+"")"),"Month3") -> Month3 | C96: =IFERROR(__xludf.DUMMYFUNCTION("REGEXEXTRACT(A96, ""#([A-Z])#"") "),"S") -> S | D96: =IFERROR(__xludf.DUMMYFUNCTION("REGEXEXTRACT(A96, ""City_([^/]+)"")"),"Delhi") -> Delhi | E96: =IFERROR(__xludf.DUMMYFUNCTION("REGEXEXTRACT(A96, ""PRD-([^/]+)"")"),"PowerSip") -> PowerSip | F96: =IFERROR(__xludf.DUMMYFUNCTION("REGEXEXTRACT(A96, ""OPQ\s+(\d+)"")"),"20953") -> 20953 | G96: =IFERROR(__xludf.DUMMYFUNCTION("REGEXEXTRACT(A96, ""NPQ\[.*?\](\d+)"")"),"25354") -> 25354
A97: //Month3 //#S#City_Delhi//PRD-HappyGrow//OPQ 26180/NPQ[IPLMARKETING]29322 | B97: =IFERROR(__xludf.DUMMYFUNCTION("REGEXEXTRACT(A97, ""Month\d+"")"),"Month3") -> Month3 | C97: =IFERROR(__xludf.DUMMYFUNCTION("REGEXEXTRACT(A97, ""#([A-Z])#"") "),"S") -> S | D97: =IFERROR(__xludf.DUMMYFUNCTION("REGEXEXTRACT(A97, ""City_([^/]+)"")"),"Delhi") -> Delhi | E97: =IFERROR(__xludf.DUMMYFUNCTION("REGEXEXTRACT(A97, ""PRD-([^/]+)"")"),"HappyGrow") -> HappyGrow | F97: =IFERROR(__xludf.DUMMYFUNCTION("REGEXEXTRACT(A97, ""OPQ\s+(\d+)"")"),"26180") -> 26180 | G97: =IFERROR(__xludf.DUMMYFUNCTION("REGEXEXTRACT(A97, ""NPQ\[.*?\](\d+)"")"),"29322") -> 29322
A98: //Month4 //#N#City_Chennai//PRD-PowerSip//OPQ 28613/NPQ[IPLMARKETING]34908 | B98: =IFERROR(__xludf.DUMMYFUNCTION("REGEXEXTRACT(A98, ""Month\d+"")"),"Month4") -> Month4 | C98: =IFERROR(__xludf.DUMMYFUNCTION("REGEXEXTRACT(A98, ""#([A-Z])#"") "),"N") -> N | D98: =IFERROR(__xludf.DUMMYFUNCTION("REGEXEXTRACT(A98, ""City_([^/]+)"")"),"Chennai") -> Chennai | E98: =IFERROR(__xludf.DUMMYFUNCTION("REGEXEXTRACT(A98, ""PRD-([^/]+)"")"),"PowerSip") -> PowerSip | F98: =IFERROR(__xludf.DUMMYFUNCTION("REGEXEXTRACT(A98, ""OPQ\s+(\d+)"")"),"28613") -> 28613 | G98: =IFERROR(__xludf.DUMMYFUNCTION("REGEXEXTRACT(A98, ""NPQ\[.*?\](\d+)"")"),"34908") -> 34908
A99: //Month4 //#N#City_Chennai//PRD-HappyGrow//OPQ 20397/NPQ[IPLMARKETING]23049 | B99: =IFERROR(__xludf.DUMMYFUNCTION("REGEXEXTRACT(A99, ""Month\d+"")"),"Month4") -> Month4 | C99: =IFERROR(__xludf.DUMMYFUNCTION("REGEXEXTRACT(A99, ""#([A-Z])#"") "),"N") -> N | D99: =IFERROR(__xludf.DUMMYFUNCTION("REGEXEXTRACT(A99, ""City_([^/]+)"")"),"Chennai") -> Chennai | E99: =IFERROR(__xludf.DUMMYFUNCTION("REGEXEXTRACT(A99, ""PRD-([^/]+)"")"),"HappyGrow") -> HappyGrow | F99: =IFERROR(__xludf.DUMMYFUNCTION("REGEXEXTRACT(A99, ""OPQ\s+(\d+)"")"),"20397") -> 20397 | G99: =IFERROR(__xludf.DUMMYFUNCTION("REGEXEXTRACT(A99, ""NPQ\[.*?\](\d+)"")"),"23049") -> 23049
A100: //Month4 //#E#City_Chennai//PRD-PowerSip//OPQ 15267/NPQ[IPLMARKETING]18626 | B100: =IFERROR(__xludf.DUMMYFUNCTION("REGEXEXTRACT(A100, ""Month\d+"")"),"Month4") -> Month4 | C100: =IFERROR(__xludf.DUMMYFUNCTION("REGEXEXTRACT(A100, ""#([A-Z])#"") "),"E") -> E | D100: =IFERROR(__xludf.DUMMYFUNCTION("REGEXEXTRACT(A100, ""City_([^/]+)"")"),"Chennai") -> Chennai | E100: =IFERROR(__xludf.DUMMYFUNCTION("REGEXEXTRACT(A100, ""PRD-([^/]+)"")"),"PowerSip") -> PowerSip | F100: =IFERROR(__xludf.DUMMYFUNCTION("REGEXEXTRACT(A100, ""OPQ\s+(\d+)"")"),"15267") -> 15267 | G100: =IFERROR(__xludf.DUMMYFUNCTION("REGEXEXTRACT(A100, ""NPQ\[.*?\](\d+)"")"),"18626") -> 18626
...

Sheet Data Format
A1: Data Format | B1: //Month//#First Letter of Region#City_City Name//PRD-Product Name//OPQ Quantity/NPQ[IPLMARKETING]Quantity
A3: Example | B3: //Month1 //#N#City_Chennai//PRD-PowerSip//OPQ 21497/NPQ[IPLMARKETING]22572
A5: Month1 | B5: Month
A6: N | B6: First Letter of Region
A7: Chennai | B7: City Name
A8: PowerSip | B8: Product Name
A9: 21497 | B9: Sale quantity as per Old Plan
A10: 22572 | B10: Sale quantity as per New Plan
A12: Other Abbreviations used in Data
A13: Abbreviation | B13: Meaning
A14: PRD | B14: Product
A15: OPQ | B15: Old plan Quantity
A16: NPQ | B16: New plan Quantity

Sheet Details
A2: N | B2: North | D2: Month1 | E2: January
A3: E | B3: East | D3: Month2 | E3: February
A4: W | B4: West | D4: Month3 | E4: March
A5: S | B5: South | D5: Month4 | E5: April
D6: Month5 | E6: May
D7: Month6 | E7: June
D8: Month7 | E8: July
D9: Month8 | E9: August
D10: Month9 | E10: September
D11: Month10 | E11: October
D12: Month11 | E12: November
D13: Month12 | E13: December
A14: Month1 | B14: Month2 | C14: Month3 | D14: Month4 | E14: Month5 | F14: Month6 | G14: Month7 | H14: Month8 | I14: Month9 | J14: Month10 | K14: Month11 | L14: Month12
A15: January | B15: February | C15: March | D15: April | E15: May | F15: June | G15: July | H15: August | I15: September | J15: October | K15: November | L15: December
